Workbook
Name Approval_ApproversSL4_SL5: #REF!
Name Approval_ApproversSL4_SL5: #REF!
Name Approval_ApproversSL4_SL5: '[1]Strategy Attributes'!#REF!
Name AttributeRange: #REF!
Name AttributeRange: #REF!
Name AttributeRange: [1]!Input_Requirements[[#All],[Attribute]]
Name FlowType_Step1: Transform_Logic_Prod_LEGACY!$M$13
Name HeaderRange: 'Dev Fields'!$A$1:$L$1
Name HeaderRange: 'Prod Fields'!$A$1:$N$1
Name HeaderRange: 'SBA Fields'!$A$1:$G$1
Name Prod_WorkType: Transform_Logic_Prod_LEGACY!$M$20
Name VAL_DeferedRisk: #REF!
Name VAL_DeferedRisk: #REF!
Name VAL_DeferedRisk: VAL_RiskLevel[]
Name VAL_DefferedRisk: #REF!
Name VAL_DefferedRisk: #REF!
Name VAL_DefferedRisk: VAL_RiskLevel[]
Name VAL_ValueFramework: #REF!
Name VAL_ValueFramework: #REF!
Name VAL_ValueFramework: VAL_ValueFramework1[]
Name WAVE_InScope: #REF!
Name WR53_DemandSubType: Transform_Logic_Prod_LEGACY!$M$50

Sheet ReadME
A1: Worksheet Name | B1: Usage
A2: Config_Tech_Enabled | B2: This is where we should store all of our configuration requirements for Tech_enabled Value Bundles and their respective epics. We will expand to the financial lines as well when it is time. Goal is to eventually also include the Strategic Program Configuration Requirements in the same tab

Sheet Open Stakeholder Questions
A1: Topic | B1: Question | C1: Owner | D1: Answer | E1: Status | F1: Date Answered
A2: Missing Attributes in Work Structure | B2: There is no home for the following attributes from Prod in the work hierarchy. Should they be created so we don't lose the data: -L1 Net Recurring Benefits ($, annualized)-P&L/Hard -L2 Net Recurring Benefits ($, annualized)-P&L/Hard -Special Projects -L1 One-time Benefit ($)-Total -Initial Net Recurring Benefits ($, annualized)-P&L/Hard -NRB (Exit Rate) 2028 (Latest Estimate) -Enterprise Strategic Initiative (ESI) -Azure Subscription Group -MS Azure Usage Size | C2: Bibhusha | E2: Open
A3: Flow Type | B3: NRB (both exit rate and the L1 field) are used as a mechanism for classifying the flow type; however, the exit rate is allowed to be massively negative. How would we want to treat this in the estimated value range that is consolidated from the 3 fields? Is it Low because it's under $10M, or do we consider this an error in understanding, and so we should take the absolute value of the number | C3: Jodi | D3: negative values are considered low. We should not do absolute values | E3: Addressed in Code
A4: Flow Type | B4: Is Flow Type to remain null if it is Business Only Demand? | C4: Jodi | D4: Yes | E4: Addressed in Code
A5: Flow Type | B5: If Initiative is Biz w/ tech but is $<10M and has a t-size of L or XL then what should the flow type be? | C5: Jodi | D5: Addressed in the flow logic now. | E5: Addressed in Code
A6: Mismatch - Domain vs Home Portfolio or Domain | B6: "Domain" and "Domain or Home Portfolio" do not match always (~120 records). Which field is most appropriate to place the demand. Note this is likely most relevant for business demand. Here are the unique options that happened: | C6: Jodi and Bibhusha | D6: Use Domain, not Home Domain or Portfolio | E6: Answered
A7: Work Hierarchy | B7: In the work hierarchy, are we keeping both "C-" and "P&C-" tree leaves? Does C represent confidential and P&C represents ultra-confidential? | D7: Yes, C represents confidential and P&C represents ultra-confidential | E7: Addressed in Code
A8: Attributes | B8: Why are both Demand SubType and Risk SubType needed? They are the same dropdown options. | D8: Demand Subtype is no longer used in the new design. Risk Subtype is used instead. And this applies only to work going under the Tech Enabled Intake Work Type (aka Discretionary/Non- Discretionary Demand Type) | E8: Open
A9: Visibility | B9: Can WR56 be made available as a column? | C9: Bibhusha | D9: Was made available as a column | E9: Answered | F9: 46161
A10: Execution Type | B10: Should I be filtering out this "Initiative Milestones & Risks"? It might be a placeholder epic and not really be valuable but it's hard to tell | C10: TJ | D10: Yes, filter out the execution type initiative milestone & Risks but do not remove its children milestones and tasks | E10: Answered
A11: Impacted Portfolios | B11: In SBA, Impacted Portfolios appears inconsistent with the columns that say "Impact X Portfolio".. Should we just consolidate the Yes's into a new column and ignore "Impacted Portfolios" column | D11: Technically, "Impacts X Portfolio" aligns 1:1 with the final Prod attributes so these should be accurately filled. Can you please follow up with business takeholders on the discrepancy in data entered? Please confirm with Christina Dunphy & Eryn Walter for DRIVE bundles. Emilee James & Jodi McDowell for D&T value bundles. [C Dunphy] - The impacted portfolios are filled in as the information is obtained. We do not have lifecycle steps in SBA so we cannot make every future required field, required in SBA, as they wouldn't be able to save the data upon creation. This data will continue to be populated in SBA as they work their way through L2 | E11: Answered
A12: Missing data in SBA | B12: The following attributes in SBA are not filled (all null). Can we just exclude them from the migration scripts? Note the ones that are marked as issues need to be resolved ASAP. See table in worksheet "SBA Empty attributes" | C12: Christina | D12: Can you remove the Epic fields from that list because Epics are migrated from Prod, not from SBA. Outside those, if required fields are not filled out, then Christina Dunphy & Eryn Walter are the contacts for DRIVE. Emilee James & Jodi McDowell are the contacts for D&T. | E12: Open
A13: New Attribute SBA | B13: Can we add a mapping attribute in SBA for the legacy Sequence ID? | C13: Cynthia | D13: Created | E13: Answered
A14: Work Hierarchy | B14: What do you want to do about existing Freight demand | C14: Christina | D14: TJ thinks we might be eliminating these work items | E14: Open
A15: Attributes | B15: In Dev, STR136 has an extra space at the end of the attribute name. Please delete this space | C15: TJ-->Jill | E15: Open
A16: SBA Cleanup | B16: When will the cleanup be done in SBA given the PPL+1 for existing data seems incorrect | C16: TJ | E16: Open
A17: Logbook Migration | B17: Do we have a view of the attributes and their validation options in logbook? What are the codes to migrate? | C17: TJ | D17: Asnwered in email on 6/1. Technical IDs translation will be done directly by planview. TJ to see if we need another attribute custom made for risk owner | E17: Open
A18: Prod Cleanup | B18: What do we do about the orphaned Epics in the work structure | C18: TJ | D18: Orphaned epics should not occur and will be handled via data quality cleanup/triage rather than adding migration logic to support them. Own communications + next steps for orphaned epics post-cleanup (publish list of items NOT migrated + exceptions) | E18: Open | F18: 46162
A19: Removal of Initiative milestones & Risks containers | B19: In the work structure, we will not migrate Execution Type where "Initiative Milestones & Risks", regardless of the demand type being business only or Biz w/ Tech. | C19: TJ | D19: For the milestone containers, we need the milestones but not the containers itself. Max will handle the removal in the final migration step | E19: Answered
A20: Orphaned Epics | B20: Any Biz w/ Tech Epic without a parent Initiative will not be migrated | C20: TJ | D20: Orphaned epics should not occur and will be handled via data quality cleanup/triage rather than adding migration logic to support them. Own communications + next steps for orphaned epics post-cleanup (publish list of items NOT migrated + exceptions) | E20: Open | F20: 46162
A21: SBA Replacement Attribute format - Strategy | B21: I don't think "Previous Strategy Seq. ID" (fdx_a_prev_str_seqid) is meant to be used, right? This is in the strategy structure which doesn't help us | C21: TJ | D21: Removed | E21: Answered
A22: SBA Replacement Attribute format - Work | B22: Can you rename the field "Previous Work Seq. ID" to "Previous Seq_ID" (fdx_a_prev_wrk_seqid). Then afterwards, can you fill it with a few examples. Please let me know if there's a scenario where there are multiple and how that format will be added. Also give guidance on how to treat the multiple… Do we wish to combine all the items underneath this one item? | C22: TJ | D22: Modified the name | E22: Answered
A23: Milestones/Tasks | B23: Do we understand the requirement right? All tasks / milestones will be converted into milestones with no duration and no start date. This applies to all items, business only, LE/LM, biz w/ tech epic. Also what do we want to apply for execution types on the PPL+2 items that are not SBA and not Epics | C23: TJ | D23: Max misunderstood this. It's not a thing | E23: Answered
A24: Agility Sync Attributes | B24: What does the transformation table need to look like for flipping (IN AGILITY) the previous work ID with the new one from Dev | C24: Steven | E24: Open
A25: SBA Extract | B25: 1) Did you pull the right column for its parent Sequence ID? It shouldn't be going to its Value bundle, but rather its execution package 2) Can you share with us the methodology for filtering out the PPL+2 items? 3) If Epics are at the same level as the tasks, wouldn't it be safer for us to just do a main extract of everything at PPL+ 0, then PPL+1 then PPL+2 rather than breaking out the PPL+2 into Epics vs tasks | C25: Bert | E25: Open
A26: Show on Roadmap | B26: Do we want to set "Show on Roadmap" to "Show on Strategy & Project" for all Epics that came from prod? | C26: TJ | D26: Yes | E26: Answered | F26: 46174

Sheet Config_Strategic_Program
A1: Source Tab | B1: Lifecycle Stage | C1: Source Demand Type | D1: Target Demand Type | E1: Target Entity | F1: Target Field Name | G1: Required | H1: Source FDXSANDBOXA ID | I1: Target DEV SB ID | J1: Type | K1: Selection Type | L1: Has Dropdown | M1: Entity_Flag_Manual_Review
A2: L1 - Strategy Def | B2: L1 | F2: Name | G2: Required | H2: strat_name | I2: strat_name | J2: Field | L2: No | M2: YES
A3: L1 - Strategy Def | B3: L1 | F3: Strategic Parent | G3: Required | H3: StratRoot | I3: StratRoot | J3: Strategic Hierarchy | L3: No | M3: YES
A4: L1 - Strategy Def | B4: L1 | F4: Brief Demand Description | G4: Required | H4: strat_descr | I4: strat_descr | J4: Field | L4: No | M4: YES
A5: L1 - Strategy Def | B5: L1 | F5: Target Start | G5: Optional | H5: strat_target_start | I5: strat_target_start | J5: Field | L5: No | M5: YES
A6: L1 - Strategy Def | B6: L1 | F6: Target Finish | G6: Optional | H6: strat_target_finish | I6: strat_target_finish | J6: Field | L6: No | M6: YES
A7: L1 - Strategy Def | B7: L1 | F7: Program Owner | G7: Required | H7: 178308 | I7: 190983 | J7: Field | K7: Single | L7: Yes | M7: YES
A8: L1 - Strategy Def | B8: L1 | F8: Program Manager | G8: Required | H8: 178309 | I8: 190984 | J8: Field | K8: Multi | L8: Yes | M8: YES
A9: L1 - Strategy Def | B9: L1 | F9: D&T Captain | G9: Required | H9: 178311 | I9: 190985 | J9: Field | K9: Single | L9: Yes | M9: YES
A10: L1 - Strategy Def | B10: L1 | F10: ESPM | G10: Required | H10: 178312 | I10: 190986 | J10: Field | K10: Multi | L10: Yes | M10: YES
A11: L1 - Strategy Def | B11: L1 | F11: Business Finance | G11: Required | H11: 178340 | I11: 190987 | J11: Field | K11: Multi | L11: Yes | M11: YES
A12: L1 - Strategy Def | B12: L1 | F12: Architecture Program Manager | G12: Optional | H12: 178310 | I12: 190988 | J12: Field | K12: Single | L12: Yes | M12: YES
A13: L1 - Strategy Def | B13: L1 | F13: TO Finance | G13: Required | H13: 3399 | I13: 3399 | J13: Field | K13: Single | L13: Yes | M13: YES
A14: L1 - Strategy Def | B14: L1 | F14: TO Approver | G14: Required | H14: 178339 | I14: 190989 | J14: Field | K14: Multi | L14: Yes | M14: YES
A15: L1 - Strategy Def | B15: L1 | F15: EPM | G15: Required | H15: 4181 | I15: 4181 | J15: Field | K15: Multi | L15: Yes | M15: YES
A16: L1 - Strategy Def | B16: L1 | F16: Expected Business Outcome | G16: Optional | H16: fdx_biz_out_strat | I16: fdx_biz_out_strat | J16: Field | L16: No | M16: YES
A17: L1 - Strategy Def | B17: L1 | F17: Initial Net Recurring Benefits ($, annualized)-P&L/Hard | G17: Optional | H17: fdx_l1_nrb_hard | I17: fdx_l1_nrb_hard | J17: Field | L17: No | M17: YES
A18: L1 - Strategy Def | B18: L1 | F18: Initial Net Recurring Benefits ($, annualized)-Soft | G18: Optional | H18: fdx_l1_nrb_soft | I18: fdx_l1_nrb_soft | J18: Field | L18: No | M18: YES
A19: L1 - Strategy Def | B19: L1 | F19: Initial Net Recurring Benefits ($, annualized)-Total | G19: Optional | H19: 1044 | I19: 1044 | J19: Calculated | L19: No | M19: YES
A20: L1 - Strategy Def | B20: L1 | F20: Initial One-time Benefit ($) | G20: Optional | H20: fdx_l1_otb_total | I20: fdx_l1_otb_total | J20: Field | L20: No | M20: YES
A21: L1 - Strategy Def | B21: L1 | F21: Key Assumptions Made in Quantifying Impact | G21: Optional | H21: fdx_calc_explan | I21: fdx_calc_explan | J21: Field | L21: No | M21: YES
A22: L1 - Strategy Def | B22: L1 | F22: Primary Type of Value | G22: Required | H22: Str119 | I22: Str119 | J22: Alt. Struct | K22: Single | L22: Yes | M22: YES
A23: L1 - Strategy Def | B23: L1 | F23: Does this Program impact Customer Experience? | G23: Optional | H23: Str136 | I23: Str32 | J23: Alt. Struct | K23: Single | L23: Yes | M23: YES
A24: L1 - Strategy Def | B24: L1 | F24: If yes, indicate level of Customer Experience impact | G24: Optional | H24: Wbs125 | I24: Wbs57 | J24: Alt. Struct | K24: Single | L24: Yes | M24: YES
A25: L1 - Strategy Def | B25: L1 | F25: Does this Program impact Service? | G25: Optional | H25: Str137 | I25: Str48 | J25: Alt. Struct | K25: Single | L25: Yes | M25: YES
A26: L1 - Strategy Def | B26: L1 | F26: If yes, indicate level of Service impact | G26: Optional | H26: Wbs126 | I26: Wbs59 | J26: Alt. Struct | K26: Single | L26: Yes | M26: YES
A27: L1 - Strategy Def | B27: L1 | F27: OKRs: | G27: - | H27: - | I27: - | J27: static text | L27: No | M27: YES
A28: L1 - Strategy Def | B28: L1 | F28: Enterprise KPI | G28: Required | H28: Str134 | I28: Str134 | J28: Alt. Struct | K28: Multi | L28: Yes | M28: YES
A29: L1 - Strategy Def | B29: L1 | F29: Program Dependencies | G29: - | H29: - | I29: - | J29: Dependency container | L29: No | M29: YES
A30: L1 - Strategy Def | B30: L1 | F30: Commercial Dependencies | G30: Optional | H30: Str138 | I30: Str49 | J30: Alt. Struct | K30: Multi | L30: Yes | M30: YES
A31: L1 - Strategy Def | B31: L1 | F31: SL2 Business Finance Approval | G31: Required | H31: Str140 | I31: Str52 | J31: Alt. Struct | K31: Single | L31: Yes | M31: YES
A32: L1 - Strategy Def | B32: L1 | F32: SL2 Business Finance Approval Notes | G32: Required | H32: fdx_bfin_appv_notes | I32: fdx_bfin_appv_notes | J32: Field | L32: No | M32: YES
A33: L1 - Strategy Def | B33: L1 | F33: SL2 Program Owner Approval | G33: Required | H33: Str141 | I33: Str53 | J33: Alt. Struct | K33: Single | L33: Yes | M33: YES
A34: L1 - Strategy Def | B34: L1 | F34: SL2 Program Owner Approval Notes | G34: Required | H34: fdx_pgo_appv_notes | I34: fdx_pgo_appv_notes | J34: Field | L34: No | M34: YES
A35: L1 - Strategy Def | B35: L1 | F35: SL2 ESPM Review | G35: Required | H35: Str142 | I35: Str54 | J35: Alt. Struct | K35: Single | L35: Yes | M35: YES
A36: L1 - Strategy Def | B36: L1 | F36: SL2 ESPM Review Notes | G36: Required | H36: fdx_espm_rev_notes | I36: fdx_espm_rev_notes | J36: Field | L36: No | M36: YES
A37: L1 - Strategy Def | B37: L1 | F37: SL2 TO Approval | G37: Required | H37: Str143 | I37: Str55 | J37: Alt. Struct | K37: Single | L37: Yes | M37: YES
A38: L1 - Strategy Def | B38: L1 | F38: SL2 TO Approval Notes | G38: Required | H38: fdx_to_appv_notes | I38: fdx_to_appv_notes | J38: Field | L38: No | M38: YES
A39: L1 - Strategy Def | B39: L1 | F39: Status | G39: Read Only | H39: SpsStatus | I39: SpsStatus | J39: Alt. Struct | K39: Single | L39: Yes | M39: YES
A40: L1 - Strategy Def | B40: L1 | F40: Program Type | H40: Str144 | I40: Str61 | J40: Alt. Struct | K40: Single | L40: Yes | M40: YES
A41: L1 - Strategy Def | B41: L1 | F41: SL2 D&T Finance Approval | H41: Str146 | I41: Str92 | J41: Alt. Struct | K41: Single | L41: Yes | M41: YES
A42: L1 - Strategy Def | B42: L1 | F42: SL2 D&T Finance Approval Notes | H42: fdx_dtfin_appv_notes | I42: fdx_dtfin_appv_notes | J42: Field | L42: No | M42: YES
A43: L1 - Strategy Def | B43: L1 | F43: SL2 DTU Approval | H43: Str148 | I43: Str102 | J43: Alt. Struct | K43: Single | L43: Yes | M43: YES
A44: L1 - Strategy Def | B44: L1 | F44: SL2 DTU Approval Notes | H44: fdx_dtu_appv_notes | I44: fdx_dtu_appv_notes | J44: Field | L44: No | M44: YES
A45: L2 - Design | B45: L2 | E45: Program | F45: Start | H45: strat_target_start | I45: Field | L45: No
A46: L2 - Design | B46: L2 | E46: Program | F46: Finish | H46: strat_target_finish | I46: Field | L46: No
A47: L2 - Design | B47: L2 | E47: Program | F47: Type | H47: MsTpS | I47: MsTpS | J47: Alt. Struct | K47: Single | L47: Yes
A48: L2 - Design | B48: L2 | E48: Program | F48: Name | H48: DESCR | I48: DESCR | J48: Field | L48: No
A49: L2 - Design | B49: L2 | E49: Program | F49: Category | H49: MsCtS | I49: MsCtS | J49: Alt. Struct | K49: Single | L49: Yes
A50: L2 - Design | B50: L2 | E50: Program | F50: Target | H50: STRAT_WK_ACT_FIN | I50: STRAT_WK_ACT_FIN | J50: Field | L50: No
A51: L2 - Design | B51: L2 | E51: Program | F51: Actual/Schedule | H51: STRAT_WK_SCH_ACT_FIN | I51: STRAT_WK_SCH_ACT_FIN | J51: Field | L51: No
A52: L2 - Design | B52: L2 | E52: Program | F52: Work Parent | G52: Required | H52: PARENT_DESCR | I52: PARENT_DESCR | J52: Predefined | L52: No
A53: L2 - Design | B53: L2 | E53: Program | F53: Work Type | G53: Required | H53: Wbs22 | I53: Wbs22 | J53: Alt. Struct | K53: Single | L53: Yes
A54: L2 - Design | B54: L2 | E54: Program | F54: Work Name | G54: Required | H54: DESCR | I54: DESCR | J54: Field | L54: No
A55: L2 - Design | B55: L2 | E55: Program | F55: Does this work support either of these type of Programs? | I55: Wbs174 | J55: Alt. Struct | K55: Single | L55: No
A56: L2 - Design | B56: L2 | E56: Program | F56: Is this demand Business Only? | G56: Required | H56: Wbs138 | I56: Wbs66 | J56: Alt. Struct | K56: Single | L56: Yes
A57: L2 - Design | B57: L2 | E57: Program | F57: Is this Limited Visibility? Does this require Limited Visibility? | H57: WR31 | I57: Wbs154 | J57: Alt. Struct | K57: Single | L57: Yes
A58: L2 - Design | B58: L2 | E58: Value Bundle | F58: Value Bundle Manager | G58: Required | H58: 178353 | I58: 191003 | J58: Field | K58: Multi | L58: Yes
A59: L2 - Design | B59: L2 | E59: Value Bundle | F59: Program Owner | G59: Required | H59: 178308 | I59: 191003 | J59: Field | K59: Single | L59: Yes
A60: L2 - Design | B60: L2 | E60: Value Bundle | F60: Program Manager | G60: Required | H60: 178309 | I60: 190984 | J60: Field | K60: Multi | L60: Yes
A61: L2 - Design | B61: L2 | E61: Value Bundle | F61: D&T Captain | G61: Required | H61: 178311 | I61: 190985 | J61: Field | K61: Single | L61: Yes
A62: L2 - Design | B62: L2 | E62: Value Bundle | F62: D&T Finance | G62: Required | H62: 178521 | I62: 191004 | J62: Field | K62: Single | L62: Yes
A63: L2 - Design | B63: L2 | E63: Value Bundle | F63: EPG | G63: Required | H63: 179115 | I63: 191005 | J63: Field | K63: Multi | L63: Yes
A64: L2 - Design | B64: L2 | E64: Value Bundle | F64: ESPM | G64: Required | H64: 178312 | I64: 190986 | J64: Field | K64: Multi | L64: Yes
A65: L2 - Design | B65: L2 | E65: Value Bundle | F65: Business Finance | G65: Required | H65: 178340 | I65: 190987 | J65: Field | K65: Multi | L65: Yes
A66: L2 - Design | B66: L2 | E66: Value Bundle | F66: Architecture Program Manager | G66: Required | H66: 178310 | I66: 190988 | J66: Field | K66: Single | L66: Yes
A67: L2 - Design | B67: L2 | E67: Value Bundle | F67: TO Finance | H67: 3399 | I67: 3399 | J67: Field | K67: Single | L67: Yes
A68: L2 - Design | B68: L2 | E68: Value Bundle | F68: TO Approver | G68: Required | H68: 178339 | I68: 190989 | J68: Field | K68: Multi | L68: Yes
A69: L2 - Design | B69: L2 | E69: Value Bundle | F69: Associated Program | G69: Required | H69: STRATEGY_ALLO | I69: STRATEGY_ALLO | J69: Predefined | L69: No
A70: L2 - Design | B70: L2 | E70: Value Bundle | F70: Sub Program | G70: Optional | H70: Wbs110 | I70: Wbs67 | J70: Alt. Struct | K70: Single | L70: Yes
A71: L2 - Design | B71: L2 | E71: Value Bundle | F71: Description | G71: Required | H71: PE01 | I71: PE01 | J71: Field | L71: No
A72: L2 - Design | B72: L2 | E72: Value Bundle | F72: Work Status | H72: Wbs20 | I72: Wbs20 | J72: Alt. Struct | K72: Single | L72: Yes
A73: L2 - Design | B73: L2 | E73: Value Bundle | F73: Stage | H73: Wbs28 | I73: Wbs28 | J73: Alt. Struct | K73: Single | L73: Yes
A74: L2 - Design | B74: L2 | E74: Value Bundle | F74: In Scope | G74: Required | H74: fdx_in_scope | I74: fdx_in_scope | J74: Field | L74: No
A75: L2 - Design | B75: L2 | E75: Value Bundle | F75: Out of Scope | G75: Required | H75: fdx_out_of_scope | I75: fdx_out_of_scope | J75: Field | L75: No
A76: L2 - Design | B76: L2 | E76: Value Bundle | F76: Expected Business Outcome | G76: Required | H76: fdx_biz_out_work | I76: fdx_biz_out_work | J76: Field | L76: No
A77: L2 - Design | B77: L2 | E77: Value Bundle | F77: Business Complexity Estimate | G77: Required | H77: Str36 | I77: Str36 | J77: Alt. Struct | K77: Single | L77: Yes
A78: L2 - Design | B78: L2 | E78: Value Bundle | F78: Business Process and/or Operational Impact | G78: Required | H78: fdx_biz_impact_work | I78: fdx_biz_impact_work | J78: Field | L78: No
A79: L2 - Design | B79: L2 | E79: Value Bundle | F79: Region(s) Impacted | G79: Required | H79: Wbs94 | I79: Wbs94 | J79: Alt. Struct | K79: Multi | L79: Yes
A80: L2 - Design | B80: L2 | E80: Value Bundle | F80: T-Shirt Size | G80: Required | H80: Str62 | I80: Str62 | J80: Alt. Struct | K80: Single | L80: Yes
A81: L2 - Design | B81: L2 | E81: Value Bundle | F81: Impacts Commercial Portfolio? | G81: Required | H81: Str109 | I81: Str109 | J81: Alt. Struct | K81: Single | L81: Yes
A82: L2 - Design | B82: L2 | E82: Value Bundle | F82: Impacts Enterprise Services Portfolio? | H82: Str111 | I82: Str111 | J82: Alt. Struct | K82: Single | L82: Yes
A83: L2 - Design | B83: L2 | E83: Value Bundle | F83: Impacts Platforms Portfolio? | H83: Str110 | I83: Str110 | J83: Alt. Struct | K83: Single | L83: Yes
A84: L2 - Design | B84: L2 | E84: Value Bundle | F84: Impacts Supply Chain Operations Portfolio? | H84: Str113 | I84: Str113 | J84: Alt. Struct | K84: Single | L84: Yes
A85: L2 - Design | B85: L2 | E85: Value Bundle | F85: EAI # | G85: Optional | H85: fdx_eai_work | I85: fdx_eai_work | J85: Field | L85: No
A86: L2 - Design | B86: L2 | E86: Value Bundle | F86: Architectural Documentation | G86: Required | H86: fdx_epic_archdoc_URL | I86: fdx_epic_archdoc_URL | J86: Field | L86: No
A87: L2 - Design | B87: L2 | E87: Value Bundle | F87: Actual/Schedule Start | G87: Read Only | H87: AC_START | I87: AC_START | J87: Predefined | L87: No
A88: L2 - Design | B88: L2 | E88: Value Bundle | F88: Actual/Schedule Finish | G88: Read Only | H88: AC_FINISH | I88: AC_FINISH | J88: Predefined | L88: No
A89: L2 - Design | B89: L2 | E89: Value Bundle | F89: Key Assumptions Made in Quantifying Impact | G89: Required | H89: fdx_assump_work | I89: fdx_assump_work | J89: Field | K89: n/a | L89: No
A90: L2 - Design | B90: L2 | E90: Value Bundle | F90: Baseline Fiscal Year | G90: Required | H90: Str33 | I90: Str33 | J90: Alt. Struct | K90: Single | L90: Yes
A91: L2 - Design | B91: L2 | E91: Value Bundle | F91: Net Recurring Benefits P&L/Hard Exit Rate CY '29 | G91: Required | H91: fdx_vbnrb_pnl_exit | I91: fdx_vbnrb_pnl_exit | J91: Field | L91: No
A92: L2 - Design | B92: L2 | E92: Value Bundle | F92: Net Recurring Benefits CY '27 -P&L/Hard | G92: Required | H92: fdx_vbnrb_cy27_hard | I92: fdx_vbnrb_cy27_hard | J92: Field | K92: n/a | L92: No
A93: L2 - Design | B93: L2 | E93: Value Bundle | F93: Net Recurring Benefits CY '28 -P&L/Hard | G93: Required | H93: fdx_vbnrb_cy28_hard | I93: fdx_vbnrb_cy28_hard | J93: Field | K93: n/a | L93: No
A94: L2 - Design | B94: L2 | E94: Value Bundle | F94: Net Recurring Benefits CY '29 -P&L/Hard | G94: Required | H94: fdx_vbnrb_cy29_hard | I94: fdx_vbnrb_cy29_hard | J94: Field | K94: n/a | L94: No
A95: L2 - Design | B95: L2 | E95: Value Bundle | F95: Net Recurring Benefits TY '26 -P&L/Hard | G95: Required | H95: fdx_vbnrb_ty26_hard | I95: fdx_vbnrb_ty26_hard | J95: Field | K95: n/a | L95: No
A96: L2 - Design | B96: L2 | E96: Value Bundle | F96: Net Recurring Benefits -Soft | G96: Required | H96: fdx_l1_nrb_soft | I96: fdx_l1_nrb_soft_wrk | J96: Field | K96: n/a | L96: No
A97: L2 - Design | B97: L2 | E97: Value Bundle | F97: Net Recurring Benefits -Total | G97: Required | H97: fdx_vbnrb_total | I97: fdx_vbnrb_total | J97: Field | K97: n/a | L97: No
A98: L2 - Design | B98: L2 | E98: Value Bundle | F98: One-time Benefit ($) | G98: Required | H98: fdzx_l1_otb_total | I98: fdx_l1_otb_total_wrk | J98: Field | K98: n/a | L98: No
A99: L2 - Design | B99: L2 | E99: Value Bundle | F99: Enterprise KPI | G99: Required | H99: Str134 | I99: Str134 | J99: Alt. Struct | K99: Multi | L99: Yes
A100: L2 - Design | B100: L2 | E100: Value Bundle | F100: Primary Type of Value | G100: Required | H100: Str119 | I100: Str119 | J100: Alt. Struct | K100: Single | L100: Yes
...

Sheet Work Hierarchy
A1: Work Structure
A3: Level Names
A4: Level | B4: Name | E4: Comments and Design Decisions
A5: 1 | B5: Lvl1:
A6: 2 | B6: Lvl2:
A7: 3 | B7: Lvl3:
A8: 4 | B8: Lvl4:
A9: 5 | B9: Lvl5:
A10: 6 | B10: >
A11: 7 | B11: >>
A12: 8 | B12: >>>
A15: Structure
A16: Lvl1: | B16: Column1 | C16: Lvl2: | D16: Lvl3: | E16: Column2 | F16: Lvl4: | G16: Column3 | H16: Column4 | I16: Consolidated Name | J16: Level | K16: Normalized Name | L16: Normalized Sequence ID
A17: FedEx (PlanRoot) | I17: =IF(A17<>"",A17,IF(C17<>"",C17,IF(D17<>"",D17,IF(F17<>"",F17,"Error")))) -> FedEx (PlanRoot) | J17: =IF(A17<>"",1,IF(C17<>"",2,IF(D17<>"",3,IF(F17<>"",4,"Error")))) -> 1 | K17: =LEFT(I17, FIND("§", SUBSTITUTE(I17," (","§", (LEN(I17)-LEN(SUBSTITUTE(I17," (","")))/2)) - 1) -> FedEx | L17: =_xlfn.LET( _xlpm.p,FIND("§",SUBSTITUTE(I17," (","§",(LEN(I17)-LEN(SUBSTITUTE(I17," (","")))/2)), MID(I17,_xlpm.p+2,LEN(I17)-_xlpm.p-2)) -> PlanRoot
C18: DRIVE (190945) | I18: =IF(A18<>"",A18,IF(C18<>"",C18,IF(D18<>"",D18,IF(F18<>"",F18,"Error")))) -> DRIVE (190945) | J18: =IF(A18<>"",1,IF(C18<>"",2,IF(D18<>"",3,IF(F18<>"",4,"Error")))) -> 2 | K18: =LEFT(I18, FIND("§", SUBSTITUTE(I18," (","§", (LEN(I18)-LEN(SUBSTITUTE(I18," (","")))/2)) - 1) -> DRIVE | L18: =_xlfn.LET( _xlpm.p,FIND("§",SUBSTITUTE(I18," (","§",(LEN(I18)-LEN(SUBSTITUTE(I18," (","")))/2)), MID(I18,_xlpm.p+2,LEN(I18)-_xlpm.p-2)) -> 190945
D19: DRIVE (190946) | I19: =IF(A19<>"",A19,IF(C19<>"",C19,IF(D19<>"",D19,IF(F19<>"",F19,"Error")))) -> DRIVE (190946) | J19: =IF(A19<>"",1,IF(C19<>"",2,IF(D19<>"",3,IF(F19<>"",4,"Error")))) -> 3 | K19: =LEFT(I19, FIND("§", SUBSTITUTE(I19," (","§", (LEN(I19)-LEN(SUBSTITUTE(I19," (","")))/2)) - 1) -> DRIVE | L19: =_xlfn.LET( _xlpm.p,FIND("§",SUBSTITUTE(I19," (","§",(LEN(I19)-LEN(SUBSTITUTE(I19," (","")))/2)), MID(I19,_xlpm.p+2,LEN(I19)-_xlpm.p-2)) -> 190946
F20: DRIVE (190947) | I20: =IF(A20<>"",A20,IF(C20<>"",C20,IF(D20<>"",D20,IF(F20<>"",F20,"Error")))) -> DRIVE (190947) | J20: =IF(A20<>"",1,IF(C20<>"",2,IF(D20<>"",3,IF(F20<>"",4,"Error")))) -> 4 | K20: =LEFT(I20, FIND("§", SUBSTITUTE(I20," (","§", (LEN(I20)-LEN(SUBSTITUTE(I20," (","")))/2)) - 1) -> DRIVE | L20: =_xlfn.LET( _xlpm.p,FIND("§",SUBSTITUTE(I20," (","§",(LEN(I20)-LEN(SUBSTITUTE(I20," (","")))/2)), MID(I20,_xlpm.p+2,LEN(I20)-_xlpm.p-2)) -> 190947
F21: C-DRIVE (190948) | I21: =IF(A21<>"",A21,IF(C21<>"",C21,IF(D21<>"",D21,IF(F21<>"",F21,"Error")))) -> C-DRIVE (190948) | J21: =IF(A21<>"",1,IF(C21<>"",2,IF(D21<>"",3,IF(F21<>"",4,"Error")))) -> 4 | K21: =LEFT(I21, FIND("§", SUBSTITUTE(I21," (","§", (LEN(I21)-LEN(SUBSTITUTE(I21," (","")))/2)) - 1) -> C-DRIVE | L21: =_xlfn.LET( _xlpm.p,FIND("§",SUBSTITUTE(I21," (","§",(LEN(I21)-LEN(SUBSTITUTE(I21," (","")))/2)), MID(I21,_xlpm.p+2,LEN(I21)-_xlpm.p-2)) -> 190948
F22: P&C-DRIVE (191311) | I22: =IF(A22<>"",A22,IF(C22<>"",C22,IF(D22<>"",D22,IF(F22<>"",F22,"Error")))) -> P&C-DRIVE (191311) | J22: =IF(A22<>"",1,IF(C22<>"",2,IF(D22<>"",3,IF(F22<>"",4,"Error")))) -> 4 | K22: =LEFT(I22, FIND("§", SUBSTITUTE(I22," (","§", (LEN(I22)-LEN(SUBSTITUTE(I22," (","")))/2)) - 1) -> P&C-DRIVE | L22: =_xlfn.LET( _xlpm.p,FIND("§",SUBSTITUTE(I22," (","§",(LEN(I22)-LEN(SUBSTITUTE(I22," (","")))/2)), MID(I22,_xlpm.p+2,LEN(I22)-_xlpm.p-2)) -> 191311
C23: Non-DRIVE (190949) | I23: =IF(A23<>"",A23,IF(C23<>"",C23,IF(D23<>"",D23,IF(F23<>"",F23,"Error")))) -> Non-DRIVE (190949) | J23: =IF(A23<>"",1,IF(C23<>"",2,IF(D23<>"",3,IF(F23<>"",4,"Error")))) -> 2 | K23: =LEFT(I23, FIND("§", SUBSTITUTE(I23," (","§", (LEN(I23)-LEN(SUBSTITUTE(I23," (","")))/2)) - 1) -> Non-DRIVE | L23: =_xlfn.LET( _xlpm.p,FIND("§",SUBSTITUTE(I23," (","§",(LEN(I23)-LEN(SUBSTITUTE(I23," (","")))/2)), MID(I23,_xlpm.p+2,LEN(I23)-_xlpm.p-2)) -> 190949
D24: D&T (190950) | I24: =IF(A24<>"",A24,IF(C24<>"",C24,IF(D24<>"",D24,IF(F24<>"",F24,"Error")))) -> D&T (190950) | J24: =IF(A24<>"",1,IF(C24<>"",2,IF(D24<>"",3,IF(F24<>"",4,"Error")))) -> 3 | K24: =LEFT(I24, FIND("§", SUBSTITUTE(I24," (","§", (LEN(I24)-LEN(SUBSTITUTE(I24," (","")))/2)) - 1) -> D&T | L24: =_xlfn.LET( _xlpm.p,FIND("§",SUBSTITUTE(I24," (","§",(LEN(I24)-LEN(SUBSTITUTE(I24," (","")))/2)), MID(I24,_xlpm.p+2,LEN(I24)-_xlpm.p-2)) -> 190950
F25: Tech-Enabled Intake (191086) | I25: =IF(A25<>"",A25,IF(C25<>"",C25,IF(D25<>"",D25,IF(F25<>"",F25,"Error")))) -> Tech-Enabled Intake (191086) | J25: =IF(A25<>"",1,IF(C25<>"",2,IF(D25<>"",3,IF(F25<>"",4,"Error")))) -> 4 | K25: =LEFT(I25, FIND("§", SUBSTITUTE(I25," (","§", (LEN(I25)-LEN(SUBSTITUTE(I25," (","")))/2)) - 1) -> Tech-Enabled Intake | L25: =_xlfn.LET( _xlpm.p,FIND("§",SUBSTITUTE(I25," (","§",(LEN(I25)-LEN(SUBSTITUTE(I25," (","")))/2)), MID(I25,_xlpm.p+2,LEN(I25)-_xlpm.p-2)) -> 191086
F26: D&T Cross-Portfolio Demand (190951) | I26: =IF(A26<>"",A26,IF(C26<>"",C26,IF(D26<>"",D26,IF(F26<>"",F26,"Error")))) -> D&T Cross-Portfolio Demand (190951) | J26: =IF(A26<>"",1,IF(C26<>"",2,IF(D26<>"",3,IF(F26<>"",4,"Error")))) -> 4 | K26: =LEFT(I26, FIND("§", SUBSTITUTE(I26," (","§", (LEN(I26)-LEN(SUBSTITUTE(I26," (","")))/2)) - 1) -> D&T Cross-Portfolio Demand | L26: =_xlfn.LET( _xlpm.p,FIND("§",SUBSTITUTE(I26," (","§",(LEN(I26)-LEN(SUBSTITUTE(I26," (","")))/2)), MID(I26,_xlpm.p+2,LEN(I26)-_xlpm.p-2)) -> 190951
F27: C-D&T Cross-Portfolio Demand (191085) | I27: =IF(A27<>"",A27,IF(C27<>"",C27,IF(D27<>"",D27,IF(F27<>"",F27,"Error")))) -> C-D&T Cross-Portfolio Demand (191085) | J27: =IF(A27<>"",1,IF(C27<>"",2,IF(D27<>"",3,IF(F27<>"",4,"Error")))) -> 4 | K27: =LEFT(I27, FIND("§", SUBSTITUTE(I27," (","§", (LEN(I27)-LEN(SUBSTITUTE(I27," (","")))/2)) - 1) -> C-D&T Cross-Portfolio Demand | L27: =_xlfn.LET( _xlpm.p,FIND("§",SUBSTITUTE(I27," (","§",(LEN(I27)-LEN(SUBSTITUTE(I27," (","")))/2)), MID(I27,_xlpm.p+2,LEN(I27)-_xlpm.p-2)) -> 191085
F28: P&C-D&T Cross-Portfolio Demand (191312) | I28: =IF(A28<>"",A28,IF(C28<>"",C28,IF(D28<>"",D28,IF(F28<>"",F28,"Error")))) -> P&C-D&T Cross-Portfolio Demand (191312) | J28: =IF(A28<>"",1,IF(C28<>"",2,IF(D28<>"",3,IF(F28<>"",4,"Error")))) -> 4 | K28: =LEFT(I28, FIND("§", SUBSTITUTE(I28," (","§", (LEN(I28)-LEN(SUBSTITUTE(I28," (","")))/2)) - 1) -> P&C-D&T Cross-Portfolio Demand | L28: =_xlfn.LET( _xlpm.p,FIND("§",SUBSTITUTE(I28," (","§",(LEN(I28)-LEN(SUBSTITUTE(I28," (","")))/2)), MID(I28,_xlpm.p+2,LEN(I28)-_xlpm.p-2)) -> 191312
F29: D&T Strategic Demand (191179) | I29: =IF(A29<>"",A29,IF(C29<>"",C29,IF(D29<>"",D29,IF(F29<>"",F29,"Error")))) -> D&T Strategic Demand (191179) | J29: =IF(A29<>"",1,IF(C29<>"",2,IF(D29<>"",3,IF(F29<>"",4,"Error")))) -> 4 | K29: =LEFT(I29, FIND("§", SUBSTITUTE(I29," (","§", (LEN(I29)-LEN(SUBSTITUTE(I29," (","")))/2)) - 1) -> D&T Strategic Demand | L29: =_xlfn.LET( _xlpm.p,FIND("§",SUBSTITUTE(I29," (","§",(LEN(I29)-LEN(SUBSTITUTE(I29," (","")))/2)), MID(I29,_xlpm.p+2,LEN(I29)-_xlpm.p-2)) -> 191179
F30: C-D&T Strategic Demand (191180) | I30: =IF(A30<>"",A30,IF(C30<>"",C30,IF(D30<>"",D30,IF(F30<>"",F30,"Error")))) -> C-D&T Strategic Demand (191180) | J30: =IF(A30<>"",1,IF(C30<>"",2,IF(D30<>"",3,IF(F30<>"",4,"Error")))) -> 4 | K30: =LEFT(I30, FIND("§", SUBSTITUTE(I30," (","§", (LEN(I30)-LEN(SUBSTITUTE(I30," (","")))/2)) - 1) -> C-D&T Strategic Demand | L30: =_xlfn.LET( _xlpm.p,FIND("§",SUBSTITUTE(I30," (","§",(LEN(I30)-LEN(SUBSTITUTE(I30," (","")))/2)), MID(I30,_xlpm.p+2,LEN(I30)-_xlpm.p-2)) -> 191180
F31: P&C-D&T Strategic Demand (191313) | I31: =IF(A31<>"",A31,IF(C31<>"",C31,IF(D31<>"",D31,IF(F31<>"",F31,"Error")))) -> P&C-D&T Strategic Demand (191313) | J31: =IF(A31<>"",1,IF(C31<>"",2,IF(D31<>"",3,IF(F31<>"",4,"Error")))) -> 4 | K31: =LEFT(I31, FIND("§", SUBSTITUTE(I31," (","§", (LEN(I31)-LEN(SUBSTITUTE(I31," (","")))/2)) - 1) -> P&C-D&T Strategic Demand | L31: =_xlfn.LET( _xlpm.p,FIND("§",SUBSTITUTE(I31," (","§",(LEN(I31)-LEN(SUBSTITUTE(I31," (","")))/2)), MID(I31,_xlpm.p+2,LEN(I31)-_xlpm.p-2)) -> 191313
C32: C-Business Demand (191314) | I32: =IF(A32<>"",A32,IF(C32<>"",C32,IF(D32<>"",D32,IF(F32<>"",F32,"Error")))) -> C-Business Demand (191314) | J32: =IF(A32<>"",1,IF(C32<>"",2,IF(D32<>"",3,IF(F32<>"",4,"Error")))) -> 2 | K32: =LEFT(I32, FIND("§", SUBSTITUTE(I32," (","§", (LEN(I32)-LEN(SUBSTITUTE(I32," (","")))/2)) - 1) -> C-Business Demand | L32: =_xlfn.LET( _xlpm.p,FIND("§",SUBSTITUTE(I32," (","§",(LEN(I32)-LEN(SUBSTITUTE(I32," (","")))/2)), MID(I32,_xlpm.p+2,LEN(I32)-_xlpm.p-2)) -> 191314
D33: Americas International (191465) | I33: =IF(A33<>"",A33,IF(C33<>"",C33,IF(D33<>"",D33,IF(F33<>"",F33,"Error")))) -> Americas International (191465) | J33: =IF(A33<>"",1,IF(C33<>"",2,IF(D33<>"",3,IF(F33<>"",4,"Error")))) -> 3 | K33: =LEFT(I33, FIND("§", SUBSTITUTE(I33," (","§", (LEN(I33)-LEN(SUBSTITUTE(I33," (","")))/2)) - 1) -> Americas International | L33: =_xlfn.LET( _xlpm.p,FIND("§",SUBSTITUTE(I33," (","§",(LEN(I33)-LEN(SUBSTITUTE(I33," (","")))/2)), MID(I33,_xlpm.p+2,LEN(I33)-_xlpm.p-2)) -> 191465
D34: APAC (191466) | I34: =IF(A34<>"",A34,IF(C34<>"",C34,IF(D34<>"",D34,IF(F34<>"",F34,"Error")))) -> APAC (191466) | J34: =IF(A34<>"",1,IF(C34<>"",2,IF(D34<>"",3,IF(F34<>"",4,"Error")))) -> 3 | K34: =LEFT(I34, FIND("§", SUBSTITUTE(I34," (","§", (LEN(I34)-LEN(SUBSTITUTE(I34," (","")))/2)) - 1) -> APAC | L34: =_xlfn.LET( _xlpm.p,FIND("§",SUBSTITUTE(I34," (","§",(LEN(I34)-LEN(SUBSTITUTE(I34," (","")))/2)), MID(I34,_xlpm.p+2,LEN(I34)-_xlpm.p-2)) -> 191466
D35: Airline (191467) | I35: =IF(A35<>"",A35,IF(C35<>"",C35,IF(D35<>"",D35,IF(F35<>"",F35,"Error")))) -> Airline (191467) | J35: =IF(A35<>"",1,IF(C35<>"",2,IF(D35<>"",3,IF(F35<>"",4,"Error")))) -> 3 | K35: =LEFT(I35, FIND("§", SUBSTITUTE(I35," (","§", (LEN(I35)-LEN(SUBSTITUTE(I35," (","")))/2)) - 1) -> Airline | L35: =_xlfn.LET( _xlpm.p,FIND("§",SUBSTITUTE(I35," (","§",(LEN(I35)-LEN(SUBSTITUTE(I35," (","")))/2)), MID(I35,_xlpm.p+2,LEN(I35)-_xlpm.p-2)) -> 191467
D36: Commercial (191468) | I36: =IF(A36<>"",A36,IF(C36<>"",C36,IF(D36<>"",D36,IF(F36<>"",F36,"Error")))) -> Commercial (191468) | J36: =IF(A36<>"",1,IF(C36<>"",2,IF(D36<>"",3,IF(F36<>"",4,"Error")))) -> 3 | K36: =LEFT(I36, FIND("§", SUBSTITUTE(I36," (","§", (LEN(I36)-LEN(SUBSTITUTE(I36," (","")))/2)) - 1) -> Commercial | L36: =_xlfn.LET( _xlpm.p,FIND("§",SUBSTITUTE(I36," (","§",(LEN(I36)-LEN(SUBSTITUTE(I36," (","")))/2)), MID(I36,_xlpm.p+2,LEN(I36)-_xlpm.p-2)) -> 191468
D37: Data and Tech (191469) | I37: =IF(A37<>"",A37,IF(C37<>"",C37,IF(D37<>"",D37,IF(F37<>"",F37,"Error")))) -> Data and Tech (191469) | J37: =IF(A37<>"",1,IF(C37<>"",2,IF(D37<>"",3,IF(F37<>"",4,"Error")))) -> 3 | K37: =LEFT(I37, FIND("§", SUBSTITUTE(I37," (","§", (LEN(I37)-LEN(SUBSTITUTE(I37," (","")))/2)) - 1) -> Data and Tech | L37: =_xlfn.LET( _xlpm.p,FIND("§",SUBSTITUTE(I37," (","§",(LEN(I37)-LEN(SUBSTITUTE(I37," (","")))/2)), MID(I37,_xlpm.p+2,LEN(I37)-_xlpm.p-2)) -> 191469
D38: Dock (191470) | I38: =IF(A38<>"",A38,IF(C38<>"",C38,IF(D38<>"",D38,IF(F38<>"",F38,"Error")))) -> Dock (191470) | J38: =IF(A38<>"",1,IF(C38<>"",2,IF(D38<>"",3,IF(F38<>"",4,"Error")))) -> 3 | K38: =LEFT(I38, FIND("§", SUBSTITUTE(I38," (","§", (LEN(I38)-LEN(SUBSTITUTE(I38," (","")))/2)) - 1) -> Dock | L38: =_xlfn.LET( _xlpm.p,FIND("§",SUBSTITUTE(I38," (","§",(LEN(I38)-LEN(SUBSTITUTE(I38," (","")))/2)), MID(I38,_xlpm.p+2,LEN(I38)-_xlpm.p-2)) -> 191470
D39: Europe (191471) | I39: =IF(A39<>"",A39,IF(C39<>"",C39,IF(D39<>"",D39,IF(F39<>"",F39,"Error")))) -> Europe (191471) | J39: =IF(A39<>"",1,IF(C39<>"",2,IF(D39<>"",3,IF(F39<>"",4,"Error")))) -> 3 | K39: =LEFT(I39, FIND("§", SUBSTITUTE(I39," (","§", (LEN(I39)-LEN(SUBSTITUTE(I39," (","")))/2)) - 1) -> Europe | L39: =_xlfn.LET( _xlpm.p,FIND("§",SUBSTITUTE(I39," (","§",(LEN(I39)-LEN(SUBSTITUTE(I39," (","")))/2)), MID(I39,_xlpm.p+2,LEN(I39)-_xlpm.p-2)) -> 191471
D40: Freight (this one will likely not be included) (191472) | I40: =IF(A40<>"",A40,IF(C40<>"",C40,IF(D40<>"",D40,IF(F40<>"",F40,"Error")))) -> Freight (this one will likely not be included) (191472) | J40: =IF(A40<>"",1,IF(C40<>"",2,IF(D40<>"",3,IF(F40<>"",4,"Error")))) -> 3 | K40: =LEFT(I40, FIND("§", SUBSTITUTE(I40," (","§", (LEN(I40)-LEN(SUBSTITUTE(I40," (","")))/2)) - 1) -> Freight (this one will likely not be included) | L40: =_xlfn.LET( _xlpm.p,FIND("§",SUBSTITUTE(I40," (","§",(LEN(I40)-LEN(SUBSTITUTE(I40," (","")))/2)), MID(I40,_xlpm.p+2,LEN(I40)-_xlpm.p-2)) -> 191472
D41: Global Air Hubs & Ramps (191473) | I41: =IF(A41<>"",A41,IF(C41<>"",C41,IF(D41<>"",D41,IF(F41<>"",F41,"Error")))) -> Global Air Hubs & Ramps (191473) | J41: =IF(A41<>"",1,IF(C41<>"",2,IF(D41<>"",3,IF(F41<>"",4,"Error")))) -> 3 | K41: =LEFT(I41, FIND("§", SUBSTITUTE(I41," (","§", (LEN(I41)-LEN(SUBSTITUTE(I41," (","")))/2)) - 1) -> Global Air Hubs & Ramps | L41: =_xlfn.LET( _xlpm.p,FIND("§",SUBSTITUTE(I41," (","§",(LEN(I41)-LEN(SUBSTITUTE(I41," (","")))/2)), MID(I41,_xlpm.p+2,LEN(I41)-_xlpm.p-2)) -> 191473
D42: Global Capabilities Strategy (191474) | I42: =IF(A42<>"",A42,IF(C42<>"",C42,IF(D42<>"",D42,IF(F42<>"",F42,"Error")))) -> Global Capabilities Strategy (191474) | J42: =IF(A42<>"",1,IF(C42<>"",2,IF(D42<>"",3,IF(F42<>"",4,"Error")))) -> 3 | K42: =LEFT(I42, FIND("§", SUBSTITUTE(I42," (","§", (LEN(I42)-LEN(SUBSTITUTE(I42," (","")))/2)) - 1) -> Global Capabilities Strategy | L42: =_xlfn.LET( _xlpm.p,FIND("§",SUBSTITUTE(I42," (","§",(LEN(I42)-LEN(SUBSTITUTE(I42," (","")))/2)), MID(I42,_xlpm.p+2,LEN(I42)-_xlpm.p-2)) -> 191474
D43: Global Clearance (191475) | I43: =IF(A43<>"",A43,IF(C43<>"",C43,IF(D43<>"",D43,IF(F43<>"",F43,"Error")))) -> Global Clearance (191475) | J43: =IF(A43<>"",1,IF(C43<>"",2,IF(D43<>"",3,IF(F43<>"",4,"Error")))) -> 3 | K43: =LEFT(I43, FIND("§", SUBSTITUTE(I43," (","§", (LEN(I43)-LEN(SUBSTITUTE(I43," (","")))/2)) - 1) -> Global Clearance | L43: =_xlfn.LET( _xlpm.p,FIND("§",SUBSTITUTE(I43," (","§",(LEN(I43)-LEN(SUBSTITUTE(I43," (","")))/2)), MID(I43,_xlpm.p+2,LEN(I43)-_xlpm.p-2)) -> 191475
D44: Linehaul (191476) | I44: =IF(A44<>"",A44,IF(C44<>"",C44,IF(D44<>"",D44,IF(F44<>"",F44,"Error")))) -> Linehaul (191476) | J44: =IF(A44<>"",1,IF(C44<>"",2,IF(D44<>"",3,IF(F44<>"",4,"Error")))) -> 3 | K44: =LEFT(I44, FIND("§", SUBSTITUTE(I44," (","§", (LEN(I44)-LEN(SUBSTITUTE(I44," (","")))/2)) - 1) -> Linehaul | L44: =_xlfn.LET( _xlpm.p,FIND("§",SUBSTITUTE(I44," (","§",(LEN(I44)-LEN(SUBSTITUTE(I44," (","")))/2)), MID(I44,_xlpm.p+2,LEN(I44)-_xlpm.p-2)) -> 191476
... D55: Revenue Growth (191487) | I55: =IF(A55<>"",A55,IF(C55<>"",C55,IF(D55<>"",D55,IF(F55<>"",F55,"Error")))) -> Revenue Growth (191487) | J55: =IF(A55<>"",1,IF(C55<>"",2,IF(D55<>"",3,IF(F55<>"",4,"Error")))) -> 3 | K55: =LEFT(I55, FIND("§", SUBSTITUTE(I55," (","§", (LEN(I55)-LEN(SUBSTITUTE(I55," (","")))/2)) - 1) -> Revenue Growth | L55: =_xlfn.LET( _xlpm.p,FIND("§",SUBSTITUTE(I55," (","§",(LEN(I55)-LEN(SUBSTITUTE(I55," (","")))/2)), MID(I55,_xlpm.p+2,LEN(I55)-_xlpm.p-2)) -> 191487
C56: P&C-Business Demand (191315) | I56: =IF(A56<>"",A56,IF(C56<>"",C56,IF(D56<>"",D56,IF(F56<>"",F56,"Error")))) -> P&C-Business Demand (191315) | J56: =IF(A56<>"",1,IF(C56<>"",2,IF(D56<>"",3,IF(F56<>"",4,"Error")))) -> 2 | K56: =LEFT(I56, FIND("§", SUBSTITUTE(I56," (","§", (LEN(I56)-LEN(SUBSTITUTE(I56," (","")))/2)) - 1) -> P&C-Business Demand | L56: =_xlfn.LET( _xlpm.p,FIND("§",SUBSTITUTE(I56," (","§",(LEN(I56)-LEN(SUBSTITUTE(I56," (","")))/2)), MID(I56,_xlpm.p+2,LEN(I56)-_xlpm.p-2)) -> 191315
D57: Americas International (191488) | I57: =IF(A57<>"",A57,IF(C57<>"",C57,IF(D57<>"",D57,IF(F57<>"",F57,"Error")))) -> Americas International (191488) | J57: =IF(A57<>"",1,IF(C57<>"",2,IF(D57<>"",3,IF(F57<>"",4,"Error")))) -> 3 | K57: =LEFT(I57, FIND("§", SUBSTITUTE(I57," (","§", (LEN(I57)-LEN(SUBSTITUTE(I57," (","")))/2)) - 1) -> Americas International | L57: =_xlfn.LET( _xlpm.p,FIND("§",SUBSTITUTE(I57," (","§",(LEN(I57)-LEN(SUBSTITUTE(I57," (","")))/2)), MID(I57,_xlpm.p+2,LEN(I57)-_xlpm.p-2)) -> 191488
D58: APAC (191489) | I58: =IF(A58<>"",A58,IF(C58<>"",C58,IF(D58<>"",D58,IF(F58<>"",F58,"Error")))) -> APAC (191489) | J58: =IF(A58<>"",1,IF(C58<>"",2,IF(D58<>"",3,IF(F58<>"",4,"Error")))) -> 3 | K58: =LEFT(I58, FIND("§", SUBSTITUTE(I58," (","§", (LEN(I58)-LEN(SUBSTITUTE(I58," (","")))/2)) - 1) -> APAC | L58: =_xlfn.LET( _xlpm.p,FIND("§",SUBSTITUTE(I58," (","§",(LEN(I58)-LEN(SUBSTITUTE(I58," (","")))/2)), MID(I58,_xlpm.p+2,LEN(I58)-_xlpm.p-2)) -> 191489
D59: Airline (191490) | I59: =IF(A59<>"",A59,IF(C59<>"",C59,IF(D59<>"",D59,IF(F59<>"",F59,"Error")))) -> Airline (191490) | J59: =IF(A59<>"",1,IF(C59<>"",2,IF(D59<>"",3,IF(F59<>"",4,"Error")))) -> 3 | K59: =LEFT(I59, FIND("§", SUBSTITUTE(I59," (","§", (LEN(I59)-LEN(SUBSTITUTE(I59," (","")))/2)) - 1) -> Airline | L59: =_xlfn.LET( _xlpm.p,FIND("§",SUBSTITUTE(I59," (","§",(LEN(I59)-LEN(SUBSTITUTE(I59," (","")))/2)), MID(I59,_xlpm.p+2,LEN(I59)-_xlpm.p-2)) -> 191490
D60: Commercial (191491) | I60: =IF(A60<>"",A60,IF(C60<>"",C60,IF(D60<>"",D60,IF(F60<>"",F60,"Error")))) -> Commercial (191491) | J60: =IF(A60<>"",1,IF(C60<>"",2,IF(D60<>"",3,IF(F60<>"",4,"Error")))) -> 3 | K60: =LEFT(I60, FIND("§", SUBSTITUTE(I60," (","§", (LEN(I60)-LEN(SUBSTITUTE(I60," (","")))/2)) - 1) -> Commercial | L60: =_xlfn.LET( _xlpm.p,FIND("§",SUBSTITUTE(I60," (","§",(LEN(I60)-LEN(SUBSTITUTE(I60," (","")))/2)), MID(I60,_xlpm.p+2,LEN(I60)-_xlpm.p-2)) -> 191491
D61: Data and Tech (191492) | I61: =IF(A61<>"",A61,IF(C61<>"",C61,IF(D61<>"",D61,IF(F61<>"",F61,"Error")))) -> Data and Tech (191492) | J61: =IF(A61<>"",1,IF(C61<>"",2,IF(D61<>"",3,IF(F61<>"",4,"Error")))) -> 3 | K61: =LEFT(I61, FIND("§", SUBSTITUTE(I61," (","§", (LEN(I61)-LEN(SUBSTITUTE(I61," (","")))/2)) - 1) -> Data and Tech | L61: =_xlfn.LET( _xlpm.p,FIND("§",SUBSTITUTE(I61," (","§",(LEN(I61)-LEN(SUBSTITUTE(I61," (","")))/2)), MID(I61,_xlpm.p+2,LEN(I61)-_xlpm.p-2)) -> 191492
D62: Dock (191493) | I62: =IF(A62<>"",A62,IF(C62<>"",C62,IF(D62<>"",D62,IF(F62<>"",F62,"Error")))) -> Dock (191493) | J62: =IF(A62<>"",1,IF(C62<>"",2,IF(D62<>"",3,IF(F62<>"",4,"Error")))) -> 3 | K62: =LEFT(I62, FIND("§", SUBSTITUTE(I62," (","§", (LEN(I62)-LEN(SUBSTITUTE(I62," (","")))/2)) - 1) -> Dock | L62: =_xlfn.LET( _xlpm.p,FIND("§",SUBSTITUTE(I62," (","§",(LEN(I62)-LEN(SUBSTITUTE(I62," (","")))/2)), MID(I62,_xlpm.p+2,LEN(I62)-_xlpm.p-2)) -> 191493
D63: Europe (191494) | I63: =IF(A63<>"",A63,IF(C63<>"",C63,IF(D63<>"",D63,IF(F63<>"",F63,"Error")))) -> Europe (191494) | J63: =IF(A63<>"",1,IF(C63<>"",2,IF(D63<>"",3,IF(F63<>"",4,"Error")))) -> 3 | K63: =LEFT(I63, FIND("§", SUBSTITUTE(I63," (","§", (LEN(I63)-LEN(SUBSTITUTE(I63," (","")))/2)) - 1) -> Europe | L63: =_xlfn.LET( _xlpm.p,FIND("§",SUBSTITUTE(I63," (","§",(LEN(I63)-LEN(SUBSTITUTE(I63," (","")))/2)), MID(I63,_xlpm.p+2,LEN(I63)-_xlpm.p-2)) -> 191494
D64: Freight (this one will likely not be included) (191495) | I64: =IF(A64<>"",A64,IF(C64<>"",C64,IF(D64<>"",D64,IF(F64<>"",F64,"Error")))) -> Freight (this one will likely not be included) (191495) | J64: =IF(A64<>"",1,IF(C64<>"",2,IF(D64<>"",3,IF(F64<>"",4,"Error")))) -> 3 | K64: =LEFT(I64, FIND("§", SUBSTITUTE(I64," (","§", (LEN(I64)-LEN(SUBSTITUTE(I64," (","")))/2)) - 1) -> Freight (this one will likely not be included) | L64: =_xlfn.LET( _xlpm.p,FIND("§",SUBSTITUTE(I64," (","§",(LEN(I64)-LEN(SUBSTITUTE(I64," (","")))/2)), MID(I64,_xlpm.p+2,LEN(I64)-_xlpm.p-2)) -> 191495
D65: Global Air Hubs & Ramps (191496) | I65: =IF(A65<>"",A65,IF(C65<>"",C65,IF(D65<>"",D65,IF(F65<>"",F65,"Error")))) -> Global Air Hubs & Ramps (191496) | J65: =IF(A65<>"",1,IF(C65<>"",2,IF(D65<>"",3,IF(F65<>"",4,"Error")))) -> 3 | K65: =LEFT(I65, FIND("§", SUBSTITUTE(I65," (","§", (LEN(I65)-LEN(SUBSTITUTE(I65," (","")))/2)) - 1) -> Global Air Hubs & Ramps | L65: =_xlfn.LET( _xlpm.p,FIND("§",SUBSTITUTE(I65," (","§",(LEN(I65)-LEN(SUBSTITUTE(I65," (","")))/2)), MID(I65,_xlpm.p+2,LEN(I65)-_xlpm.p-2)) -> 191496
D66: Global Capabilities Strategy (191497) | I66: =IF(A66<>"",A66,IF(C66<>"",C66,IF(D66<>"",D66,IF(F66<>"",F66,"Error")))) -> Global Capabilities Strategy (191497) | J66: =IF(A66<>"",1,IF(C66<>"",2,IF(D66<>"",3,IF(F66<>"",4,"Error")))) -> 3 | K66: =LEFT(I66, FIND("§", SUBSTITUTE(I66," (","§", (LEN(I66)-LEN(SUBSTITUTE(I66," (","")))/2)) - 1) -> Global Capabilities Strategy | L66: =_xlfn.LET( _xlpm.p,FIND("§",SUBSTITUTE(I66," (","§",(LEN(I66)-LEN(SUBSTITUTE(I66," (","")))/2)), MID(I66,_xlpm.p+2,LEN(I66)-_xlpm.p-2)) -> 191497
D67: Global Clearance (191498) | I67: =IF(A67<>"",A67,IF(C67<>"",C67,IF(D67<>"",D67,IF(F67<>"",F67,"Error")))) -> Global Clearance (191498) | J67: =IF(A67<>"",1,IF(C67<>"",2,IF(D67<>"",3,IF(F67<>"",4,"Error")))) -> 3 | K67: =LEFT(I67, FIND("§", SUBSTITUTE(I67," (","§", (LEN(I67)-LEN(SUBSTITUTE(I67," (","")))/2)) - 1) -> Global Clearance | L67: =_xlfn.LET( _xlpm.p,FIND("§",SUBSTITUTE(I67," (","§",(LEN(I67)-LEN(SUBSTITUTE(I67," (","")))/2)), MID(I67,_xlpm.p+2,LEN(I67)-_xlpm.p-2)) -> 191498
D68: Linehaul (191499) | I68: =IF(A68<>"",A68,IF(C68<>"",C68,IF(D68<>"",D68,IF(F68<>"",F68,"Error")))) -> Linehaul (191499) | J68: =IF(A68<>"",1,IF(C68<>"",2,IF(D68<>"",3,IF(F68<>"",4,"Error")))) -> 3 | K68: =LEFT(I68, FIND("§", SUBSTITUTE(I68," (","§", (LEN(I68)-LEN(SUBSTITUTE(I68," (","")))/2)) - 1) -> Linehaul | L68: =_xlfn.LET( _xlpm.p,FIND("§",SUBSTITUTE(I68," (","§",(LEN(I68)-LEN(SUBSTITUTE(I68," (","")))/2)), MID(I68,_xlpm.p+2,LEN(I68)-_xlpm.p-2)) -> 191499
... D79: Revenue Growth (191510) | I79: =IF(A79<>"",A79,IF(C79<>"",C79,IF(D79<>"",D79,IF(F79<>"",F79,"Error")))) -> Revenue Growth (191510) | J79: =IF(A79<>"",1,IF(C79<>"",2,IF(D79<>"",3,IF(F79<>"",4,"Error")))) -> 3 | K79: =LEFT(I79, FIND("§", SUBSTITUTE(I79," (","§", (LEN(I79)-LEN(SUBSTITUTE(I79," (","")))/2)) - 1) -> Revenue Growth | L79: =_xlfn.LET( _xlpm.p,FIND("§",SUBSTITUTE(I79," (","§",(LEN(I79)-LEN(SUBSTITUTE(I79," (","")))/2)), MID(I79,_xlpm.p+2,LEN(I79)-_xlpm.p-2)) -> 191510
C80: Business Demand (191464) | I80: =IF(A80<>"",A80,IF(C80<>"",C80,IF(D80<>"",D80,IF(F80<>"",F80,"Error")))) -> Business Demand (191464) | J80: =IF(A80<>"",1,IF(C80<>"",2,IF(D80<>"",3,IF(F80<>"",4,"Error")))) -> 2 | K80: =LEFT(I80, FIND("§", SUBSTITUTE(I80," (","§", (LEN(I80)-LEN(SUBSTITUTE(I80," (","")))/2)) - 1) -> Business Demand | L80: =_xlfn.LET( _xlpm.p,FIND("§",SUBSTITUTE(I80," (","§",(LEN(I80)-LEN(SUBSTITUTE(I80," (","")))/2)), MID(I80,_xlpm.p+2,LEN(I80)-_xlpm.p-2)) -> 191464
D81: Americas International (191435) | I81: =IF(A81<>"",A81,IF(C81<>"",C81,IF(D81<>"",D81,IF(F81<>"",F81,"Error")))) -> Americas International (191435) | J81: =IF(A81<>"",1,IF(C81<>"",2,IF(D81<>"",3,IF(F81<>"",4,"Error")))) -> 3 | K81: =LEFT(I81, FIND("§", SUBSTITUTE(I81," (","§", (LEN(I81)-LEN(SUBSTITUTE(I81," (","")))/2)) - 1) -> Americas International | L81: =_xlfn.LET( _xlpm.p,FIND("§",SUBSTITUTE(I81," (","§",(LEN(I81)-LEN(SUBSTITUTE(I81," (","")))/2)), MID(I81,_xlpm.p+2,LEN(I81)-_xlpm.p-2)) -> 191435
D82: APAC (191436) | I82: =IF(A82<>"",A82,IF(C82<>"",C82,IF(D82<>"",D82,IF(F82<>"",F82,"Error")))) -> APAC (191436) | J82: =IF(A82<>"",1,IF(C82<>"",2,IF(D82<>"",3,IF(F82<>"",4,"Error")))) -> 3 | K82: =LEFT(I82, FIND("§", SUBSTITUTE(I82," (","§", (LEN(I82)-LEN(SUBSTITUTE(I82," (","")))/2)) - 1) -> APAC | L82: =_xlfn.LET( _xlpm.p,FIND("§",SUBSTITUTE(I82," (","§",(LEN(I82)-LEN(SUBSTITUTE(I82," (","")))/2)), MID(I82,_xlpm.p+2,LEN(I82)-_xlpm.p-2)) -> 191436
D83: Airline (191437) | I83: =IF(A83<>"",A83,IF(C83<>"",C83,IF(D83<>"",D83,IF(F83<>"",F83,"Error")))) -> Airline (191437) | J83: =IF(A83<>"",1,IF(C83<>"",2,IF(D83<>"",3,IF(F83<>"",4,"Error")))) -> 3 | K83: =LEFT(I83, FIND("§", SUBSTITUTE(I83," (","§", (LEN(I83)-LEN(SUBSTITUTE(I83," (","")))/2)) - 1) -> Airline | L83: =_xlfn.LET( _xlpm.p,FIND("§",SUBSTITUTE(I83," (","§",(LEN(I83)-LEN(SUBSTITUTE(I83," (","")))/2)), MID(I83,_xlpm.p+2,LEN(I83)-_xlpm.p-2)) -> 191437
D84: Commercial (191438) | I84: =IF(A84<>"",A84,IF(C84<>"",C84,IF(D84<>"",D84,IF(F84<>"",F84,"Error")))) -> Commercial (191438) | J84: =IF(A84<>"",1,IF(C84<>"",2,IF(D84<>"",3,IF(F84<>"",4,"Error")))) -> 3 | K84: =LEFT(I84, FIND("§", SUBSTITUTE(I84," (","§", (LEN(I84)-LEN(SUBSTITUTE(I84," (","")))/2)) - 1) -> Commercial | L84: =_xlfn.LET( _xlpm.p,FIND("§",SUBSTITUTE(I84," (","§",(LEN(I84)-LEN(SUBSTITUTE(I84," (","")))/2)), MID(I84,_xlpm.p+2,LEN(I84)-_xlpm.p-2)) -> 191438
D85: Data and Tech (191439) | I85: =IF(A85<>"",A85,IF(C85<>"",C85,IF(D85<>"",D85,IF(F85<>"",F85,"Error")))) -> Data and Tech (191439) | J85: =IF(A85<>"",1,IF(C85<>"",2,IF(D85<>"",3,IF(F85<>"",4,"Error")))) -> 3 | K85: =LEFT(I85, FIND("§", SUBSTITUTE(I85," (","§", (LEN(I85)-LEN(SUBSTITUTE(I85," (","")))/2)) - 1) -> Data and Tech | L85: =_xlfn.LET( _xlpm.p,FIND("§",SUBSTITUTE(I85," (","§",(LEN(I85)-LEN(SUBSTITUTE(I85," (","")))/2)), MID(I85,_xlpm.p+2,LEN(I85)-_xlpm.p-2)) -> 191439
D86: Dock (191440) | I86: =IF(A86<>"",A86,IF(C86<>"",C86,IF(D86<>"",D86,IF(F86<>"",F86,"Error")))) -> Dock (191440) | J86: =IF(A86<>"",1,IF(C86<>"",2,IF(D86<>"",3,IF(F86<>"",4,"Error")))) -> 3 | K86: =LEFT(I86, FIND("§", SUBSTITUTE(I86," (","§", (LEN(I86)-LEN(SUBSTITUTE(I86," (","")))/2)) - 1) -> Dock | L86: =_xlfn.LET( _xlpm.p,FIND("§",SUBSTITUTE(I86," (","§",(LEN(I86)-LEN(SUBSTITUTE(I86," (","")))/2)), MID(I86,_xlpm.p+2,LEN(I86)-_xlpm.p-2)) -> 191440
D87: Europe (191441) | I87: =IF(A87<>"",A87,IF(C87<>"",C87,IF(D87<>"",D87,IF(F87<>"",F87,"Error")))) -> Europe (191441) | J87: =IF(A87<>"",1,IF(C87<>"",2,IF(D87<>"",3,IF(F87<>"",4,"Error")))) -> 3 | K87: =LEFT(I87, FIND("§", SUBSTITUTE(I87," (","§", (LEN(I87)-LEN(SUBSTITUTE(I87," (","")))/2)) - 1) -> Europe | L87: =_xlfn.LET( _xlpm.p,FIND("§",SUBSTITUTE(I87," (","§",(LEN(I87)-LEN(SUBSTITUTE(I87," (","")))/2)), MID(I87,_xlpm.p+2,LEN(I87)-_xlpm.p-2)) -> 191441
D88: Freight (likely not be included) (191442) | I88: =IF(A88<>"",A88,IF(C88<>"",C88,IF(D88<>"",D88,IF(F88<>"",F88,"Error")))) -> Freight (likely not be included) (191442) | J88: =IF(A88<>"",1,IF(C88<>"",2,IF(D88<>"",3,IF(F88<>"",4,"Error")))) -> 3 | K88: =LEFT(I88, FIND("§", SUBSTITUTE(I88," (","§", (LEN(I88)-LEN(SUBSTITUTE(I88," (","")))/2)) - 1) -> Freight (likely not be included) | L88: =_xlfn.LET( _xlpm.p,FIND("§",SUBSTITUTE(I88," (","§",(LEN(I88)-LEN(SUBSTITUTE(I88," (","")))/2)), MID(I88,_xlpm.p+2,LEN(I88)-_xlpm.p-2)) -> 191442
D89: Global Air Hubs & Ramps (191443) | I89: =IF(A89<>"",A89,IF(C89<>"",C89,IF(D89<>"",D89,IF(F89<>"",F89,"Error")))) -> Global Air Hubs & Ramps (191443) | J89: =IF(A89<>"",1,IF(C89<>"",2,IF(D89<>"",3,IF(F89<>"",4,"Error")))) -> 3 | K89: =LEFT(I89, FIND("§", SUBSTITUTE(I89," (","§", (LEN(I89)-LEN(SUBSTITUTE(I89," (","")))/2)) - 1) -> Global Air Hubs & Ramps | L89: =_xlfn.LET( _xlpm.p,FIND("§",SUBSTITUTE(I89," (","§",(LEN(I89)-LEN(SUBSTITUTE(I89," (","")))/2)), MID(I89,_xlpm.p+2,LEN(I89)-_xlpm.p-2)) -> 191443
D90: Global Capabilities Strategy (191444) | I90: =IF(A90<>"",A90,IF(C90<>"",C90,IF(D90<>"",D90,IF(F90<>"",F90,"Error")))) -> Global Capabilities Strategy (191444) | J90: =IF(A90<>"",1,IF(C90<>"",2,IF(D90<>"",3,IF(F90<>"",4,"Error")))) -> 3 | K90: =LEFT(I90, FIND("§", SUBSTITUTE(I90," (","§", (LEN(I90)-LEN(SUBSTITUTE(I90," (","")))/2)) - 1) -> Global Capabilities Strategy | L90: =_xlfn.LET( _xlpm.p,FIND("§",SUBSTITUTE(I90," (","§",(LEN(I90)-LEN(SUBSTITUTE(I90," (","")))/2)), MID(I90,_xlpm.p+2,LEN(I90)-_xlpm.p-2)) -> 191444
D91: Global Clearance (191445) | I91: =IF(A91<>"",A91,IF(C91<>"",C91,IF(D91<>"",D91,IF(F91<>"",F91,"Error")))) -> Global Clearance (191445) | J91: =IF(A91<>"",1,IF(C91<>"",2,IF(D91<>"",3,IF(F91<>"",4,"Error")))) -> 3 | K91: =LEFT(I91, FIND("§", SUBSTITUTE(I91," (","§", (LEN(I91)-LEN(SUBSTITUTE(I91," (","")))/2)) - 1) -> Global Clearance | L91: =_xlfn.LET( _xlpm.p,FIND("§",SUBSTITUTE(I91," (","§",(LEN(I91)-LEN(SUBSTITUTE(I91," (","")))/2)), MID(I91,_xlpm.p+2,LEN(I91)-_xlpm.p-2)) -> 191445
D92: Linehaul (191446) | I92: =IF(A92<>"",A92,IF(C92<>"",C92,IF(D92<>"",D92,IF(F92<>"",F92,"Error")))) -> Linehaul (191446) | J92: =IF(A92<>"",1,IF(C92<>"",2,IF(D92<>"",3,IF(F92<>"",4,"Error")))) -> 3 | K92: =LEFT(I92, FIND("§", SUBSTITUTE(I92," (","§", (LEN(I92)-LEN(SUBSTITUTE(I92," (","")))/2)) - 1) -> Linehaul | L92: =_xlfn.LET( _xlpm.p,FIND("§",SUBSTITUTE(I92," (","§",(LEN(I92)-LEN(SUBSTITUTE(I92," (","")))/2)), MID(I92,_xlpm.p+2,LEN(I92)-_xlpm.p-2)) -> 191446
... D103: Revenue Growth (191457) | I103: =IF(A103<>"",A103,IF(C103<>"",C103,IF(D103<>"",D103,IF(F103<>"",F103,"Error")))) -> Revenue Growth (191457) | J103: =IF(A103<>"",1,IF(C103<>"",2,IF(D103<>"",3,IF(F103<>"",4,"Error")))) -> 3 | K103: =LEFT(I103, FIND("§", SUBSTITUTE(I103," (","§", (LEN(I103)-LEN(SUBSTITUTE(I103," (","")))/2)) - 1) -> Revenue Growth | L103: =_xlfn.LET( _xlpm.p,FIND("§",SUBSTITUTE(I103," (","§",(LEN(I103)-LEN(SUBSTITUTE(I103," (","")))/2)), MID(I103,_xlpm.p+2,LEN(I103)-_xlpm.p-2)) -> 191457
C104: Archive (2862) | I104: =IF(A104<>"",A104,IF(C104<>"",C104,IF(D104<>"",D104,IF(F104<>"",F104,"Error")))) -> Archive (2862) | J104: =IF(A104<>"",1,IF(C104<>"",2,IF(D104<>"",3,IF(F104<>"",4,"Error")))) -> 2 | K104: =LEFT(I104, FIND("§", SUBSTITUTE(I104," (","§", (LEN(I104)-LEN(SUBSTITUTE(I104," (","")))/2)) - 1) -> Archive | L104: =_xlfn.LET( _xlpm.p,FIND("§",SUBSTITUTE(I104," (","§",(LEN(I104)-LEN(SUBSTITUTE(I104," (","")))/2)), MID(I104,_xlpm.p+2,LEN(I104)-_xlpm.p-2)) -> 2862
D105: Archive (191172) | I105: =IF(A105<>"",A105,IF(C105<>"",C105,IF(D105<>"",D105,IF(F105<>"",F105,"Error")))) -> Archive (191172) | J105: =IF(A105<>"",1,IF(C105<>"",2,IF(D105<>"",3,IF(F105<>"",4,"Error")))) -> 3 | K105: =LEFT(I105, FIND("§", SUBSTITUTE(I105," (","§", (LEN(I105)-LEN(SUBSTITUTE(I105," (","")))/2)) - 1) -> Archive | L105: =_xlfn.LET( _xlpm.p,FIND("§",SUBSTITUTE(I105," (","§",(LEN(I105)-LEN(SUBSTITUTE(I105," (","")))/2)), MID(I105,_xlpm.p+2,LEN(I105)-_xlpm.p-2)) -> 191172
F106: Archive (191173) | I106: =IF(A106<>"",A106,IF(C106<>"",C106,IF(D106<>"",D106,IF(F106<>"",F106,"Error")))) -> Archive (191173) | J106: =IF(A106<>"",1,IF(C106<>"",2,IF(D106<>"",3,IF(F106<>"",4,"Error")))) -> 4 | K106: =LEFT(I106, FIND("§", SUBSTITUTE(I106," (","§", (LEN(I106)-LEN(SUBSTITUTE(I106," (","")))/2)) - 1) -> Archive | L106: =_xlfn.LET( _xlpm.p,FIND("§",SUBSTITUTE(I106," (","§",(LEN(I106)-LEN(SUBSTITUTE(I106," (","")))/2)), MID(I106,_xlpm.p+2,LEN(I106)-_xlpm.p-2)) -> 191173
C107: Templates (2863) | I107: =IF(A107<>"",A107,IF(C107<>"",C107,IF(D107<>"",D107,IF(F107<>"",F107,"Error")))) -> Templates (2863) | J107: =IF(A107<>"",1,IF(C107<>"",2,IF(D107<>"",3,IF(F107<>"",4,"Error")))) -> 2 | K107: =LEFT(I107, FIND("§", SUBSTITUTE(I107," (","§", (LEN(I107)-LEN(SUBSTITUTE(I107," (","")))/2)) - 1) -> Templates | L107: =_xlfn.LET( _xlpm.p,FIND("§",SUBSTITUTE(I107," (","§",(LEN(I107)-LEN(SUBSTITUTE(I107," (","")))/2)), MID(I107,_xlpm.p+2,LEN(I107)-_xlpm.p-2)) -> 2863
D108: Templates (2864) | I108: =IF(A108<>"",A108,IF(C108<>"",C108,IF(D108<>"",D108,IF(F108<>"",F108,"Error")))) -> Templates (2864) | J108: =IF(A108<>"",1,IF(C108<>"",2,IF(D108<>"",3,IF(F108<>"",4,"Error")))) -> 3 | K108: =LEFT(I108, FIND("§", SUBSTITUTE(I108," (","§", (LEN(I108)-LEN(SUBSTITUTE(I108," (","")))/2)) - 1) -> Templates | L108: =_xlfn.LET( _xlpm.p,FIND("§",SUBSTITUTE(I108," (","§",(LEN(I108)-LEN(SUBSTITUTE(I108," (","")))/2)), MID(I108,_xlpm.p+2,LEN(I108)-_xlpm.p-2)) -> 2864
F109: Templates (2865) | I109: =IF(A109<>"",A109,IF(C109<>"",C109,IF(D109<>"",D109,IF(F109<>"",F109,"Error")))) -> Templates (2865) | J109: =IF(A109<>"",1,IF(C109<>"",2,IF(D109<>"",3,IF(F109<>"",4,"Error")))) -> 4 | K109: =LEFT(I109, FIND("§", SUBSTITUTE(I109," (","§", (LEN(I109)-LEN(SUBSTITUTE(I109," (","")))/2)) - 1) -> Templates | L109: =_xlfn.LET( _xlpm.p,FIND("§",SUBSTITUTE(I109," (","§",(LEN(I109)-LEN(SUBSTITUTE(I109," (","")))/2)), MID(I109,_xlpm.p+2,LEN(I109)-_xlpm.p-2)) -> 2865

Sheet View - Attributes by Screen
A4: Lifecycle Stage | B4: Order | C4: Target Field Name | D4: Add New Request Information | E4: Business Continuity Assessment | F4: Problem Opportunity Statement | G4: Triage Validation | H4: Request Approval | I4: Move Work and Assign Roles and Responsibilities | J4: Architecture Alignment | K4: Certified Business Case | L4: SL3 EPG Approval | M4: SL3 Finance Approval | N4: Demand Bundle Decomp and Conceptual Architecture | O4: Detailed Milestone Refinement | P4: EPM Quality Check 1 | Q4: Revised Implementation Plan/Sequence Delivery | R4: Epic Approval | S4: L3 Epic Solutioning | T4: L3 D&T Costing | U4: EPM Quality Check 2 | V4: L3: Execute and Release | W4: SL4 Close Demand Bundle Business Finance Approval | X4: Evaluate Outcome Achievement
A5: L1 | B5: 1 | C5: Work ID
A6: L1 | B6: 2 | C6: Work Name
A7: L1 | B7: 3 | C7: Work Parent
A8: L1 | B8: 4 | C8: Work Type
A9: L1 | B9: 5 | C9: Does this request support a DRIVE strategic program?
A10: L1 | B10: 6 | C10: Does this require Limited Visibility?
A11: L1 | B11: 7 | C11: Is this demand Business Only?
A12: L1 | B12: 9 | C12: Does this request support a D&T Digital Transformation Program?
A13: L1 | B13: 10 | C13: Demand Manager
A14: L1 | B14: 11 | C14: VP Sponsor
A15: L1 | B15: 12 | C15: Does this request support a planned application or infrastructure upgrade and/or a routine infrastructure refresh?
A16: L1 | B16: 13 | C16: Risk Subtype (Does this request address a risk or requirement to one of the following?)
... A25: L1 | B25: 22 | C25: Requested IT completion Date
A26: L1 | B26: 23 | C26: Demand Type | D26: RO | E26: RO | F26: RO | G26: RW
A27: L1 | B27: 24 | C27: What business problem are you looking to solve?
A28: L1 | B28: 25 | C28: Why is this needed?
A29: L1 | B29: 26 | C29: What is the risk if not done?
A30: L1 | B30: 27 | C30: Business Ability To Statements
A31: L1 | B31: 28 | C31: Expected Business Outcome
A32: L1 | B32: 29 | C32: T-shirt Size
A33: L1 | B33: 30 | C33: Estimated Annualized Value Range
A34: L1 | B34: 31 | C34: Explain how you arrived at the estimated value range above
A35: L1 | B35: 32 | C35: Primary Type of Value
A36: L1 | B36: 33 | C36: Primary Type of Value Impact
A37: L1 | B37: 34 | C37: Primary Impacted Portfolio
A38: L1 | B38: 35 | C38: Other Impacted Portfolios
... A58: L1 | B58: 4.1 | C58: Does this work support either of these type of Programs?
A59: L1 | B59: Drive001 | C59: Name
A60: L1 | B60: Drive002 | C60: Strategic Parent
A61: L1 | B61: Drive003 | C61: Brief Demand Description
A62: L1 | B62: Drive004 | C62: Target Start
A63: L1 | B63: Drive005 | C63: Target Finish
A64: L1 | B64: Drive006 | C64: Program Owner
A65: L1 | B65: Drive007 | C65: Program Manager
A66: L1 | B66: Drive009 | C66: ESPM
A67: L1 | B67: Drive011 | C67: Architecture Program Manager
A68: L1 | B68: Drive012 | C68: TO Finance
A69: L1 | B69: Drive013 | C69: TO Approver
A70: L1 | B70: Drive014 | C70: EPM
... A97: L1 | B97: DRIVE045 | C97: <TEMP-N/A
A98: L2 | B98: 56 | C98: Impacts Commercial Portfolio?
A99: L2 | B99: 57 | C99: Impacts Enterprise Services Portfolio?
A100: L2 | B100: 58 | C100: Impacts Platforms Portfolio?
A101: L2 | B101: 59 | C101: Impacts Supply Chain Operations Portfolio?
A102: L2 | B102: 60 | C102: T-shirt Size
A103: L2 | B103: 61 | C103: Business Complexity Estimate
A104: L2 | B104: 62 | C104: Key Assumptions Made in Quantifying Impact
A105: L2 | B105: 63 | C105: Baseline Fiscal Year of Work Bundle
A106: L2 | B106: 64 | C106: Net Recurring Benefits CY '27 -P&L/Hard
A107: L2 | B107: 65 | C107: Net Recurring Benefits CY '28 -P&L/Hard
A108: L2 | B108: 66 | C108: Net Recurring Benefits CY '29 -P&L/Hard
A109: L2 | B109: 67 | C109: Net Recurring Benefits TY '26 -P&L/Hard
... A123: L2 | B123: 81 | C123: SL3 Business Finance Approval Notes
A124: L2 | B124: RSK01 | C124: Name
A125: L2 | B125: RSK02 | C125: Description
A126: L2 | B126: RSK03 | C126: Risk Type
A127: L2 | B127: RSK04 | C127: Probability
A128: L2 | B128: RSK05 | C128: Impact
A129: L2 | B129: RSK06 | C129: Risk Mitigation Comments
A130: L2 | B130: RSK07 | C130: Assignee
A131: L2 | B131: RSK08 | C131: Due Date
A132: L2 | B132: RSK09 | C132: Created By
A133: L2 | B133: RSK10 | C133: Created On
A134: L2 | B134: RSK11 | C134: Last Updated By
A135: L2 | B135: RSK001 | C135: Parent Sequence ID
... A201: L2 | B201: FIN25 | C201: Home Portfolio
A202: L3 | B202: 82 | C202: Home Portfolio
A203: L3 | B203: 83 | C203: Impacts Commercial Portfolio?
A204: L3 | B204: 84 | C204: Impacts Enterprise Services Portfolio?
A205: L3 | B205: 85 | C205: Impacts Platforms Portfolio?
A206: L3 | B206: 86 | C206: Impacts Supply Chain Operations Portfolio?
A207: L3 | B207: 87 | C207: Actual/Schedule Start
A208: L3 | B208: 88 | C208: Actual/Schedule Finish
A209: L3 | B209: 89 | C209: Stage
A210: L3 | B210: 90 | C210: Work Type
A211: L3 | B211: 91 | C211: Demand Subtype
A212: L3 | B212: 92 | C212: Work Status
A213: L3 | B213: 93 | C213: Work Status
... A251: L3 | B251: 127.1 | C251: L3 EPM Review 2 Notes
A252: L3 | B252: (blank) | C252: Epic #
A253: L3 | B253: (blank) | C253: CLEAR
A254: L3 | B254: (blank) | C254: Labor Type
A255: L3 | B255: Drive183 | C255: Associated Program Seq ID
A256: L3 | B256: Drive185 | C256: Program Stage
A257: L3 | B257: Drive186 | C257: Epic Solution(s)
A258: L3 | B258: Drive187 | C258: Primary Epic Owner
A259: L3 | B259: Drive207 | C259: Resources Allocated?
A260: L3 | B260: Drive211 | C260: L3 ESPM Review
A261: L3 | B261: Drive212 | C261: L3 ESPM Review Notes
A262: L3 | B262: Drive213 | C262: L3 D&T SMO Review
A263: L3 | B263: Drive214 | C263: L3 D&T SMO Review Notes
A264: L4 | B264: 130 | C264: SL4 Close Work Bundle - Business Finance Approval
A265: L4 | B265: 131 | C265: SL4 Close Work Bundle - Business Finance Approval Notes
A266: L4 | B266: 132 | C266: Ready to Close: Work Bundle Intent has been met?
A267: L4 | B267: 133 | C267: Ready to Close: Epic Intent has been met?
A268: L4 | B268: Drive221 | C268: SL4 Close Program - Program Owner Approval
A269: L4 | B269: Drive222 | C269: SL4 Close Program - Program Owner Approval Notes
A270: L4 | B270: Drive223 | C270: SL4 Close Program - Business Finance Approval
A271: L4 | B271: Drive224 | C271: SL4 Close Program - Business Finance Approval Notes
...

Sheet View- Task & Risk Attributes
A1: Target Entity | B1: Epic - Task
A3: Order | B3: Target Field Name | C3: Source PROD ID | D3: Prod Source field name | E3: Sandbox A field name
A4: 95 | B4: Name | C4: DESCR | D4: Epic Name | E4: (blank)
A5: T01 | B5: Parent Sequence ID | C5: WORK_STRUCTURE_CODE | D5: Sequence ID | E5: (blank)
A6: T02 | B6: Parent Work ID | C6: PW_SHORT_NAME | D6: Work ID | E6: (blank)
A7: T03 | B7: Sequence ID | C7: WORK_STRUCTURE_CODE | D7: Sequence ID | E7: (blank)
A8: T04 | B8: Name | C8: pveDescription | D8: 0-Not Found | E8: (blank)
A9: T05 | B9: Description | C9: PE01 | D9: Work Description | E9: (blank)
A10: T06 | B10: Task or Milestone Type | C10: WBS712 | D10: Milestone Type | E10: (blank)
A11: T07 | B11: Execution Type | C11: ExecType | D11: Execution Type | E11: (blank)
A12: T08 | B12: Milestone Flag | C12: MILESTONE_FLAG | D12: Milestone Flag | E12: (blank)
A13: T09 | B13: Milestone/Task Owner | C13: fdx_task_owner | D13: Milestone/Task Owner | E13: (blank)
A14: T10 | B14: Work Status | C14: Wbs20 | D14: Work Status | E14: (blank)
A15: T11 | B15: Schedule Start | C15: SCHEDULE_START | D15: Schedule Start | E15: (blank)
A16: T12 | B16: Schedule Finish | C16: SCHEDULE_FINISH | D16: Schedule Finish | E16: (blank)
... A23: T19 | B23: Show on Roadmap | C23: Wbs19 | D23: Show on Roadmap | E23: (blank)
A28: Target Entity | B28: RISK
A30: Order | B30: Target Field Name | C30: Source PROD ID | D30: Prod Source field name | E30: Sandbox A field name
A31: RSK001 | B31: Parent Sequence ID | C31: WORK_STRUCTURE_CODE | D31: Sequence ID | E31: (blank)
A32: RSK002 | B32: Parent Work ID | C32: PW_SHORT_NAME | D32: Work ID | E32: (blank)
A33: RSK01 | B33: Name | C33: (blank) | D33: 0-Not Found | E33: (blank)
A34: RSK02 | B34: Description | C34: (blank) | D34: 0-Not Found | E34: (blank)
A35: RSK03 | B35: Risk Type | C35: Rsk31 | D35: Risk Type | E35: (blank)
A36: RSK04 | B36: Probability | C36: Rsk30 | D36: Risk Probability | E36: (blank)
A37: RSK05 | B37: Impact | C37: CRI8 | D37: 0-Not Found | E37: (blank)
A38: RSK06 | B38: Risk Mitigation Comments | C38: RISK_PLAN | D38: Risk Mitigation Comments | E38: (blank)
A39: RSK07 | B39: Assignee | C39: fdx_risk_owner | D39: Risk Owner | E39: (blank)
A40: RSK08 | B40: Due Date | C40: CRI_TARGETDATE | D40: Target Date | E40: (blank)
A41: RSK09 | B41: Created By | C41: CRI_OWNER | D41: Creator | E41: (blank)
... A43: RSK11 | B43: Last Updated By | C43: (blank) | D43: 0-Not Found | E43: (blank)

Sheet Strategic Req_historical
A1: Source Tab | B1: Primary Reviewer | C1: Op Model Step | D1: 1st Lifecycle Step Name | E1: Section Name | F1: Lifecycle Screen User Role | G1: Lifecycle Stage | H1: Order | I1: Source Demand Type | J1: Target Demand Type | K1: Target Entity | L1: Entity|ID | M1: Target Field Name | N1: Configuration Status | O1: Change Control Comments | P1: Notes/Comments | Q1: Current Attribute in FDXPROD? | R1: Current Attribute in FDXSANDBOXA? | S1: PROD ID | T1: FDXSANDBOXA ID | U1: DEV SB ID | V1: Data Migration Comments | W1: Able to Migrate Mock 1? | X1: Prod Source field name | Y1: Sandbox A field name | Z1: New instance Target field name | AA1: Field names Match (prod to new)? | AB1: Field names Match (Requirement to config)? | AC1: Type | AD1: Value Type | AE1: Selection Type | AF1: Has Dropdown | AG1: Values | AH1: Hover Text or Static Text | AI1: Options (Req./RO/Opt.) | AJ1: Editable After Submission | AK1: Permission Options | AL1: Restrict Permissions Forwarding | AM1: Needed in Roadmaps? | AN1: Column1 | AO1: Exists already? (ID) | AP1: Exists already (Name) | AQ1: Double mismatch? | AR1: Decision
A2: L1 - Strategy Def | B2: Christina | C2: L1: Program Established | D2: Add New Strategy | F2: ESPM | G2: L1 | H2: Drive001 | M2: Name | Q2: Yes | R2: Yes | S2: strat_name | T2: strat_name | U2: strat_name | AC2: Field | AD2: Text | AH2: Name of the strategic program | AI2: Req. | AJ2: Editable throughout | AM2: Yes | AO2: =IF(ISNUMBER(_xlfn.XMATCH(Table182[[#This Row],[DEV SB ID]],Platinum_Config[Target DEV SB ID],0))=FALSE,"No Match","Match") -> Match | AP2: =IF(ISNUMBER(_xlfn.XMATCH(Table182[[#This Row],[Target Field Name]],Platinum_Config[Target Field Name],0))=FALSE,"No Match","Match") -> Match | AQ2: =IF(AND(Table182[[#This Row],[Exists already? (ID)]]="No Match",Table182[[#This Row],[Exists already (Name)]]="No Match"),"No Match",IF(AND(Table182[[#This Row],[Exists already? (ID)]]="Match",Table182[[#This Row],[Exists already (Name)]]="Match"),"Double Match","One Match")) -> Double Match | AR2: Added
A3: L1 - Strategy Def | B3: Christina | C3: L1: Program Established | D3: Add New Strategy | F3: ESPM | G3: L1 | H3: Drive002 | M3: Strategic Parent | Q3: Yes | R3: Yes | S3: StratRoot | T3: StratRoot | U3: StratRoot | AC3: Strategic Hierarchy | AD3: L4 | AH3: Name of the strategic pillar the program is associated with | AI3: Req. | AJ3: Admin only | AO3: =IF(ISNUMBER(_xlfn.XMATCH(Table182[[#This Row],[DEV SB ID]],Platinum_Config[Target DEV SB ID],0))=FALSE,"No Match","Match") -> Match | AP3: =IF(ISNUMBER(_xlfn.XMATCH(Table182[[#This Row],[Target Field Name]],Platinum_Config[Target Field Name],0))=FALSE,"No Match","Match") -> Match | AQ3: =IF(AND(Table182[[#This Row],[Exists already? (ID)]]="No Match",Table182[[#This Row],[Exists already (Name)]]="No Match"),"No Match",IF(AND(Table182[[#This Row],[Exists already? (ID)]]="Match",Table182[[#This Row],[Exists already (Name)]]="Match"),"Double Match","One Match")) -> Double Match | AR3: Added
A4: L1 - Strategy Def | B4: Christina | C4: L1: Program Established | D4: Add New Strategy | F4: ESPM | G4: L1 | H4: Drive003 | M4: Brief Demand Description | Q4: Yes | R4: Yes | S4: strat_descr | T4: strat_descr | U4: strat_descr | AC4: Field | AD4: Text | AH4: A short summary (3-5 sentences) outlining the purpose and scope of the demand. Update: Describe how the program supports key organizational goals (e.g., growth, efficiency, compliance), the specific challenge or gap it addresses, and the defined scope of what is included and excluded. | AI4: Req. | AJ4: Editable throughout | AM4: Yes | AO4: =IF(ISNUMBER(_xlfn.XMATCH(Table182[[#This Row],[DEV SB ID]],Platinum_Config[Target DEV SB ID],0))=FALSE,"No Match","Match") -> Match | AP4: =IF(ISNUMBER(_xlfn.XMATCH(Table182[[#This Row],[Target Field Name]],Platinum_Config[Target Field Name],0))=FALSE,"No Match","Match") -> Match | AQ4: =IF(AND(Table182[[#This Row],[Exists already? (ID)]]="No Match",Table182[[#This Row],[Exists already (Name)]]="No Match"),"No Match",IF(AND(Table182[[#This Row],[Exists already? (ID)]]="Match",Table182[[#This Row],[Exists already (Name)]]="Match"),"Double Match","One Match")) -> Double Match | AR4: Added
A5: L1 - Strategy Def | B5: Christina | C5: L1: Program Established | D5: Add New Strategy | F5: ESPM | G5: L1 | H5: Drive004 | M5: Target Start | Q5: Yes | R5: Yes | S5: strat_target_start | T5: strat_target_start | U5: strat_target_start | AC5: Field | AD5: Date | AH5: Target Start of the strategic program | AI5: Opt. | AJ5: Editable up to Step 2 | AM5: Yes | AO5: =IF(ISNUMBER(_xlfn.XMATCH(Table182[[#This Row],[DEV SB ID]],Platinum_Config[Target DEV SB ID],0))=FALSE,"No Match","Match") -> Match | AP5: =IF(ISNUMBER(_xlfn.XMATCH(Table182[[#This Row],[Target Field Name]],Platinum_Config[Target Field Name],0))=FALSE,"No Match","Match") -> Match | AQ5: =IF(AND(Table182[[#This Row],[Exists already? (ID)]]="No Match",Table182[[#This Row],[Exists already (Name)]]="No Match"),"No Match",IF(AND(Table182[[#This Row],[Exists already? (ID)]]="Match",Table182[[#This Row],[Exists already (Name)]]="Match"),"Double Match","One Match")) -> Double Match | AR5: Added
A6: L1 - Strategy Def | B6: Christina | C6: L1: Program Established | D6: Add New Strategy | F6: ESPM | G6: L1 | H6: Drive005 | M6: Target Finish | Q6: Yes | R6: Yes | S6: strat_target_finish | T6: strat_target_finish | U6: strat_target_finish | AC6: Field | AD6: Date | AH6: Target Finish of the strategic program | AI6: Opt. | AJ6: Editable up to Step 2 | AM6: Yes | AO6: =IF(ISNUMBER(_xlfn.XMATCH(Table182[[#This Row],[DEV SB ID]],Platinum_Config[Target DEV SB ID],0))=FALSE,"No Match","Match") -> Match | AP6: =IF(ISNUMBER(_xlfn.XMATCH(Table182[[#This Row],[Target Field Name]],Platinum_Config[Target Field Name],0))=FALSE,"No Match","Match") -> Match | AQ6: =IF(AND(Table182[[#This Row],[Exists already? (ID)]]="No Match",Table182[[#This Row],[Exists already (Name)]]="No Match"),"No Match",IF(AND(Table182[[#This Row],[Exists already? (ID)]]="Match",Table182[[#This Row],[Exists already (Name)]]="Match"),"Double Match","One Match")) -> Double Match | AR6: Added
A7: L1 - Strategy Def | B7: Christina | C7: L1: Program Established | D7: Assign Roles and Responsibilities | F7: ESPM | G7: L1 | H7: Drive006 | M7: Program Owner | P7: Lifecycle Roles do not support Help/Hover text | Q7: No | R7: Yes | T7: 178308 | U7: 190983 | AC7: Field | AD7: Text | AE7: Single | AG7: dynamic | AH7: The individual responsible for overseeing the strategy, execution, governance, and outcomes of a program. This role ensures that all work within the program collectively achieves the intended business objectives and deliver measurable value.​ | AI7: Req. | AJ7: Editable throughout | AK7: RW | AL7: Yes | AO7: =IF(ISNUMBER(_xlfn.XMATCH(Table182[[#This Row],[DEV SB ID]],Platinum_Config[Target DEV SB ID],0))=FALSE,"No Match","Match") -> Match | AP7: =IF(ISNUMBER(_xlfn.XMATCH(Table182[[#This Row],[Target Field Name]],Platinum_Config[Target Field Name],0))=FALSE,"No Match","Match") -> Match | AQ7: =IF(AND(Table182[[#This Row],[Exists already? (ID)]]="No Match",Table182[[#This Row],[Exists already (Name)]]="No Match"),"No Match",IF(AND(Table182[[#This Row],[Exists already? (ID)]]="Match",Table182[[#This Row],[Exists already (Name)]]="Match"),"Double Match","One Match")) -> Double Match | AR7: Added
A8: L1 - Strategy Def | B8: Christina | C8: L1: Program Established | D8: Assign Roles and Responsibilities | F8: ESPM | G8: L1 | H8: Drive007 | M8: Program Manager | P8: Lifecycle Roles do not support Help/Hover text | Q8: No | R8: Yes | T8: 178309 | U8: 190984 | AC8: Field | AD8: Text | AE8: Multi | AG8: dynamic | AH8: The individual(s) is responsible for planning, coordinating, and overseeing the execution of a program to ensure it delivers its intended strategic business outcomes. This role focuses on integrated delivery, governance, risk management, and cross‑team alignment to ensure all workstreams operate cohesively and effectively.​ | AI8: Req. | AJ8: Editable throughout | AK8: RW | AL8: Yes | AO8: =IF(ISNUMBER(_xlfn.XMATCH(Table182[[#This Row],[DEV SB ID]],Platinum_Config[Target DEV SB ID],0))=FALSE,"No Match","Match") -> Match | AP8: =IF(ISNUMBER(_xlfn.XMATCH(Table182[[#This Row],[Target Field Name]],Platinum_Config[Target Field Name],0))=FALSE,"No Match","Match") -> Match | AQ8: =IF(AND(Table182[[#This Row],[Exists already? (ID)]]="No Match",Table182[[#This Row],[Exists already (Name)]]="No Match"),"No Match",IF(AND(Table182[[#This Row],[Exists already? (ID)]]="Match",Table182[[#This Row],[Exists already (Name)]]="Match"),"Double Match","One Match")) -> Double Match | AR8: Added
A9: L1 - Strategy Def | B9: Christina | C9: L1: Program Established | D9: Assign Roles and Responsibilities | F9: ESPM | G9: L1 | H9: Drive008 | M9: D&T Captain | P9: Lifecycle Roles do not support Help/Hover text | Q9: No | R9: Yes | T9: 178311 | U9: 190985 | AC9: Field | AD9: Text | AE9: Single | AG9: dynamic | AH9: The designated leader within a strategic program who is accountable for driving the data, technology, and systems‑related components required to achieve program goals. This role ensures that data capabilities, technical solutions, and digital processes are aligned with the program’s strategy, integrated effectively, and able to support long‑term scalability | AI9: Req. | AJ9: Editable throughout | AK9: RW | AL9: Yes | AO9: =IF(ISNUMBER(_xlfn.XMATCH(Table182[[#This Row],[DEV SB ID]],Platinum_Config[Target DEV SB ID],0))=FALSE,"No Match","Match") -> No Match | AP9: =IF(ISNUMBER(_xlfn.XMATCH(Table182[[#This Row],[Target Field Name]],Platinum_Config[Target Field Name],0))=FALSE,"No Match","Match") -> Match | AQ9: =IF(AND(Table182[[#This Row],[Exists already? (ID)]]="No Match",Table182[[#This Row],[Exists already (Name)]]="No Match"),"No Match",IF(AND(Table182[[#This Row],[Exists already? (ID)]]="Match",Table182[[#This Row],[Exists already (Name)]]="Match"),"Double Match","One Match")) -> One Match | AR9: Ignore
A10: L1 - Strategy Def | B10: Christina | C10: L1: Program Established | D10: Assign Roles and Responsibilities | F10: ESPM | G10: L1 | H10: Drive009 | M10: ESPM | P10: Lifecycle Roles do not support Help/Hover text | Q10: No | R10: Yes | T10: 178312 | U10: 190986 | AC10: Field | AD10: Text | AE10: Multi | AG10: dynamic | AH10: Centralized group that partners with program managers and business owners to guide the planning, alignment, and execution of strategic programs across the organization. They ensure programs are designed, prioritized, and managed in a way that advances enterprise‑level goals. | AI10: Req. | AJ10: Editable throughout | AK10: RW | AL10: Yes | AO10: =IF(ISNUMBER(_xlfn.XMATCH(Table182[[#This Row],[DEV SB ID]],Platinum_Config[Target DEV SB ID],0))=FALSE,"No Match","Match") -> Match | AP10: =IF(ISNUMBER(_xlfn.XMATCH(Table182[[#This Row],[Target Field Name]],Platinum_Config[Target Field Name],0))=FALSE,"No Match","Match") -> Match | AQ10: =IF(AND(Table182[[#This Row],[Exists already? (ID)]]="No Match",Table182[[#This Row],[Exists already (Name)]]="No Match"),"No Match",IF(AND(Table182[[#This Row],[Exists already? (ID)]]="Match",Table182[[#This Row],[Exists already (Name)]]="Match"),"Double Match","One Match")) -> Double Match | AR10: Added
A11: L1 - Strategy Def | B11: Christina | C11: L1: Program Established | D11: Assign Roles and Responsibilities | F11: ESPM | G11: L1 | H11: Drive010 | M11: Business Finance | P11: [CD] - Asked Matt Buxton for assistance with definition Lifecycle Roles do not support Help/Hover text | Q11: No | R11: Yes | T11: 178340 | U11: 190987 | AC11: Field | AD11: Text | AE11: Multi | AG11: dynamic | AI11: Req. | AJ11: Editable throughout | AK11: RW | AL11: Yes | AO11: =IF(ISNUMBER(_xlfn.XMATCH(Table182[[#This Row],[DEV SB ID]],Platinum_Config[Target DEV SB ID],0))=FALSE,"No Match","Match") -> No Match | AP11: =IF(ISNUMBER(_xlfn.XMATCH(Table182[[#This Row],[Target Field Name]],Platinum_Config[Target Field Name],0))=FALSE,"No Match","Match") -> Match | AQ11: =IF(AND(Table182[[#This Row],[Exists already? (ID)]]="No Match",Table182[[#This Row],[Exists already (Name)]]="No Match"),"No Match",IF(AND(Table182[[#This Row],[Exists already? (ID)]]="Match",Table182[[#This Row],[Exists already (Name)]]="Match"),"Double Match","One Match")) -> One Match | AR11: Ignore
A12: L1 - Strategy Def | B12: Christina | C12: L1: Program Established | D12: Assign Roles and Responsibilities | F12: ESPM | G12: L1 | H12: Drive011 | M12: Architecture Program Manager | P12: Should not have edit access to financials Lifecycle Roles do not support Help/Hover text | Q12: No | R12: Yes | T12: 178310 | U12: 190988 | AC12: Field | AD12: Text | AE12: Single | AG12: dynamic | AH12: Architectural role accountable for ensuring the program’s solutions align with enterprise strategy, architecture standards, and target-state blueprints. The EA Lead steers architectural direction, orchestrates cross-domain design decisions (business, data, application, integration, security, and infrastructure), and manages architectural risk and technical debt at the program level. The role facilitates decision-making and enforces guardrails through governance but does not directly own product delivery or approve business scope.​ | AI12: Opt. | AJ12: Editable throughout | AK12: RW | AL12: Yes | AO12: =IF(ISNUMBER(_xlfn.XMATCH(Table182[[#This Row],[DEV SB ID]],Platinum_Config[Target DEV SB ID],0))=FALSE,"No Match","Match") -> Match | AP12: =IF(ISNUMBER(_xlfn.XMATCH(Table182[[#This Row],[Target Field Name]],Platinum_Config[Target Field Name],0))=FALSE,"No Match","Match") -> Match | AQ12: =IF(AND(Table182[[#This Row],[Exists already? (ID)]]="No Match",Table182[[#This Row],[Exists already (Name)]]="No Match"),"No Match",IF(AND(Table182[[#This Row],[Exists already? (ID)]]="Match",Table182[[#This Row],[Exists already (Name)]]="Match"),"Double Match","One Match")) -> Double Match | AR12: Added
A13: L1 - Strategy Def | B13: Christina | C13: L1: Program Established | D13: Assign Roles and Responsibilities | F13: ESPM | G13: L1 | H13: Drive012 | M13: TO Finance | P13: [CD] - Asked Matt Buxton for assistance with definition Lifecycle Roles do not support Help/Hover text | Q13: Yes | R13: Yes | S13: 3399 | T13: 3399 | U13: 3399 | AC13: Field | AD13: Text | AE13: Single | AG13: dynamic | AH13: NA | AI13: Req. | AJ13: Editable throughout | AK13: RW | AL13: Yes | AO13: =IF(ISNUMBER(_xlfn.XMATCH(Table182[[#This Row],[DEV SB ID]],Platinum_Config[Target DEV SB ID],0))=FALSE,"No Match","Match") -> Match | AP13: =IF(ISNUMBER(_xlfn.XMATCH(Table182[[#This Row],[Target Field Name]],Platinum_Config[Target Field Name],0))=FALSE,"No Match","Match") -> Match | AQ13: =IF(AND(Table182[[#This Row],[Exists already? (ID)]]="No Match",Table182[[#This Row],[Exists already (Name)]]="No Match"),"No Match",IF(AND(Table182[[#This Row],[Exists already? (ID)]]="Match",Table182[[#This Row],[Exists already (Name)]]="Match"),"Double Match","One Match")) -> Double Match | AR13: Added
A14: L1 - Strategy Def | B14: Christina | C14: L1: Program Established | D14: Assign Roles and Responsibilities | F14: ESPM | G14: L1 | H14: Drive013 | M14: TO Approver | P14: Lifecycle Roles do not support Help/Hover text | Q14: No | R14: Yes | T14: 178339 | U14: 190989 | AC14: Field | AD14: Text | AE14: Multi | AG14: dynamic | AH14: Enterprise‑designated decision authority responsible for evaluating and formally approving programs and value bundles to progress to the next stage of the transformation lifecycle. This role ensures that each program and value bundle meets established strategic, financial, and operational criteria; aligns with enterprise priorities; and possesses the necessary readiness, resourcing, and value validation before advancing | AI14: Req. | AJ14: Editable throughout | AK14: RW | AL14: Yes | AO14: =IF(ISNUMBER(_xlfn.XMATCH(Table182[[#This Row],[DEV SB ID]],Platinum_Config[Target DEV SB ID],0))=FALSE,"No Match","Match") -> Match | AP14: =IF(ISNUMBER(_xlfn.XMATCH(Table182[[#This Row],[Target Field Name]],Platinum_Config[Target Field Name],0))=FALSE,"No Match","Match") -> Match | AQ14: =IF(AND(Table182[[#This Row],[Exists already? (ID)]]="No Match",Table182[[#This Row],[Exists already (Name)]]="No Match"),"No Match",IF(AND(Table182[[#This Row],[Exists already? (ID)]]="Match",Table182[[#This Row],[Exists already (Name)]]="Match"),"Double Match","One Match")) -> Double Match | AR14: Added
A15: L1 - Strategy Def | B15: Christina | C15: L1: Program Established | D15: Assign Roles and Responsibilities | F15: ESPM | G15: L1 | H15: Drive014 | M15: EPM | P15: Lifecycle Roles do not support Help/Hover text | Q15: Yes | R15: Yes | S15: 4181 | T15: 4181 | U15: 4181 | AC15: Field | AD15: Text | AE15: Multi | AG15: dynamic | AI15: Req. | AJ15: Editable throughout | AK15: RW | AL15: Yes | AO15: =IF(ISNUMBER(_xlfn.XMATCH(Table182[[#This Row],[DEV SB ID]],Platinum_Config[Target DEV SB ID],0))=FALSE,"No Match","Match") -> Match | AP15: =IF(ISNUMBER(_xlfn.XMATCH(Table182[[#This Row],[Target Field Name]],Platinum_Config[Target Field Name],0))=FALSE,"No Match","Match") -> Match | AQ15: =IF(AND(Table182[[#This Row],[Exists already? (ID)]]="No Match",Table182[[#This Row],[Exists already (Name)]]="No Match"),"No Match",IF(AND(Table182[[#This Row],[Exists already? (ID)]]="Match",Table182[[#This Row],[Exists already (Name)]]="Match"),"Double Match","One Match")) -> Double Match | AR15: Added
A16: L1 - Strategy Def | B16: Matt | C16: L1: Desired Business Outcomes and Business Case | D16: Initial Light Business Case | F16: Business Finance | G16: L1 | H16: Drive015 | M16: Expected Business Outcome | P16: Decide editability after L0/L1 | Q16: Yes | R16: Yes | S16: fdx_biz_out_strat | T16: fdx_biz_out_strat | U16: fdx_biz_out_strat | AC16: Field | AD16: Text | AH16: Summarize the why, what, and expected value of the program. | AI16: Opt. | AM16: Yes | AO16: =IF(ISNUMBER(_xlfn.XMATCH(Table182[[#This Row],[DEV SB ID]],Platinum_Config[Target DEV SB ID],0))=FALSE,"No Match","Match") -> Match | AP16: =IF(ISNUMBER(_xlfn.XMATCH(Table182[[#This Row],[Target Field Name]],Platinum_Config[Target Field Name],0))=FALSE,"No Match","Match") -> Match | AQ16: =IF(AND(Table182[[#This Row],[Exists already? (ID)]]="No Match",Table182[[#This Row],[Exists already (Name)]]="No Match"),"No Match",IF(AND(Table182[[#This Row],[Exists already? (ID)]]="Match",Table182[[#This Row],[Exists already (Name)]]="Match"),"Double Match","One Match")) -> Double Match | AR16: Added
A17: L1 - Strategy Def | B17: Matt | C17: L1: Desired Business Outcomes and Business Case | D17: Initial Light Business Case | F17: Business Finance | G17: L1 | H17: Drive016 | M17: Initial Net Recurring Benefits ($, annualized)-P&L/Hard | P17: Have static text above this saying "**Net Recurring Benefits = CY '29 Exit Rate, Annualized** | Q17: Yes | R17: Yes | S17: fdx_l1_nrb_hard | T17: fdx_l1_nrb_hard | U17: fdx_l1_nrb_hard | AC17: Field | AD17: Currency | AH17: Net Recurring Benefits = CY28 Exit Rate, Annualized P&L/Hard = direct impact to the P&L over baseline | AI17: Opt. | AM17: Yes | AO17: =IF(ISNUMBER(_xlfn.XMATCH(Table182[[#This Row],[DEV SB ID]],Platinum_Config[Target DEV SB ID],0))=FALSE,"No Match","Match") -> Match | AP17: =IF(ISNUMBER(_xlfn.XMATCH(Table182[[#This Row],[Target Field Name]],Platinum_Config[Target Field Name],0))=FALSE,"No Match","Match") -> Match | AQ17: =IF(AND(Table182[[#This Row],[Exists already? (ID)]]="No Match",Table182[[#This Row],[Exists already (Name)]]="No Match"),"No Match",IF(AND(Table182[[#This Row],[Exists already? (ID)]]="Match",Table182[[#This Row],[Exists already (Name)]]="Match"),"Double Match","One Match")) -> Double Match | AR17: Added
A18: L1 - Strategy Def | B18: Matt | C18: L1: Desired Business Outcomes and Business Case | D18: Initial Light Business Case | F18: Business Finance | G18: L1 | H18: Drive017 | M18: Initial Net Recurring Benefits ($, annualized)-Soft | P18: replace L1 with Initial; Follow up with finance to update definition; decide editability after L0/L1 | Q18: Yes | R18: Yes | S18: fdx_l1_nrb_soft | T18: fdx_l1_nrb_soft | U18: fdx_l1_nrb_soft | AC18: Field | AD18: Currency | AH18: Net Recurring Benefits = CY28 Exit Rate, Annualized Soft = direct impact to the P&L over baseline. i.e. Cost avoidance, improved productivity | AI18: Opt. | AM18: Yes | AO18: =IF(ISNUMBER(_xlfn.XMATCH(Table182[[#This Row],[DEV SB ID]],Platinum_Config[Target DEV SB ID],0))=FALSE,"No Match","Match") -> No Match | AP18: =IF(ISNUMBER(_xlfn.XMATCH(Table182[[#This Row],[Target Field Name]],Platinum_Config[Target Field Name],0))=FALSE,"No Match","Match") -> Match | AQ18: =IF(AND(Table182[[#This Row],[Exists already? (ID)]]="No Match",Table182[[#This Row],[Exists already (Name)]]="No Match"),"No Match",IF(AND(Table182[[#This Row],[Exists already? (ID)]]="Match",Table182[[#This Row],[Exists already (Name)]]="Match"),"Double Match","One Match")) -> One Match | AR18: Added
A19: L1 - Strategy Def | B19: Matt | C19: L1: Desired Business Outcomes and Business Case | D19: Initial Light Business Case | F19: Business Finance | G19: L1 | H19: Drive018 | M19: Initial Net Recurring Benefits ($, annualized)-Total | P19: replace L1 with Initial; Follow up with finance to update definition; decide editability after L0/L1 | Q19: Yes | R19: Yes | S19: 1044 | T19: 1044 | U19: 1044 | AC19: Calculated | AD19: Currency | AH19: Net Recurring Benefits = CY28 Exit Rate, Annualized. Auto-calculation of L1 Hard and Soft Benefits. | AI19: Opt. | AM19: Yes | AO19: =IF(ISNUMBER(_xlfn.XMATCH(Table182[[#This Row],[DEV SB ID]],Platinum_Config[Target DEV SB ID],0))=FALSE,"No Match","Match") -> Match | AP19: =IF(ISNUMBER(_xlfn.XMATCH(Table182[[#This Row],[Target Field Name]],Platinum_Config[Target Field Name],0))=FALSE,"No Match","Match") -> Match | AQ19: =IF(AND(Table182[[#This Row],[Exists already? (ID)]]="No Match",Table182[[#This Row],[Exists already (Name)]]="No Match"),"No Match",IF(AND(Table182[[#This Row],[Exists already? (ID)]]="Match",Table182[[#This Row],[Exists already (Name)]]="Match"),"Double Match","One Match")) -> Double Match | AR19: Added
A20: L1 - Strategy Def | B20: Matt | C20: L1: Desired Business Outcomes and Business Case | D20: Initial Light Business Case | F20: Business Finance | G20: L1 | H20: Drive019 | M20: Initial One-time Benefit ($) | P20: replace L1 with Initial; Follow up with finance to update definition; decide editability after L0/L1 | Q20: Yes | R20: Yes | S20: fdx_l1_otb_total | T20: fdx_l1_otb_total | U20: fdx_l1_otb_total | AC20: Field | AD20: Currency | AH20: Total one-time benefits with a direct impact to the P&L | AI20: Opt. | AO20: =IF(ISNUMBER(_xlfn.XMATCH(Table182[[#This Row],[DEV SB ID]],Platinum_Config[Target DEV SB ID],0))=FALSE,"No Match","Match") -> Match | AP20: =IF(ISNUMBER(_xlfn.XMATCH(Table182[[#This Row],[Target Field Name]],Platinum_Config[Target Field Name],0))=FALSE,"No Match","Match") -> Match | AQ20: =IF(AND(Table182[[#This Row],[Exists already? (ID)]]="No Match",Table182[[#This Row],[Exists already (Name)]]="No Match"),"No Match",IF(AND(Table182[[#This Row],[Exists already? (ID)]]="Match",Table182[[#This Row],[Exists already (Name)]]="Match"),"Double Match","One Match")) -> Double Match | AR20: Added
A21: L1 - Strategy Def | B21: Matt | C21: L1: Desired Business Outcomes and Business Case | D21: Initial Light Business Case | F21: Business Finance | G21: L1 | H21: Drive020 | M21: Key Assumptions Made in Quantifying Impact | P21: replace L1 with Initial; Follow up with finance to update definition; decide editability after L0/L1 | Q21: Yes | R21: Yes | S21: fdx_calc_explan | T21: fdx_calc_explan | U21: fdx_calc_explan | AC21: Field | AD21: Text | AH21: Rationale behind the calculations of value and costs. | AI21: Opt. | AO21: =IF(ISNUMBER(_xlfn.XMATCH(Table182[[#This Row],[DEV SB ID]],Platinum_Config[Target DEV SB ID],0))=FALSE,"No Match","Match") -> No Match | AP21: =IF(ISNUMBER(_xlfn.XMATCH(Table182[[#This Row],[Target Field Name]],Platinum_Config[Target Field Name],0))=FALSE,"No Match","Match") -> Match | AQ21: =IF(AND(Table182[[#This Row],[Exists already? (ID)]]="No Match",Table182[[#This Row],[Exists already (Name)]]="No Match"),"No Match",IF(AND(Table182[[#This Row],[Exists already? (ID)]]="Match",Table182[[#This Row],[Exists already (Name)]]="Match"),"Double Match","One Match")) -> One Match | AR21: Ignore
A22: L1 - Strategy Def | B22: Matt | C22: L1: Desired Business Outcomes and Business Case | D22: Initial Light Business Case | F22: Business Finance | G22: L1 | H22: Drive021 | M22: Primary Type of Value | P22: replace L1 with Initial; Follow up with finance to update definition; decide editability after L0/L1 | Q22: Yes | R22: Yes | S22: Str119 | T22: Str119 | U22: Str119 | AC22: Alt. Struct | AD22: Text | AE22: Single | AG22: Brand (87360) Financial - Cost Avoidance (87369) Financial - Cost Savings/Reductions (87361) Customer Experience - Recipient Experience (110380) Customer Experience - Visibility (110381) Customer Experience - Problem Resolution (110382) Customer Experience - Other (87362) Innovation (110385) Financial - Revenue Growth (Customer Acquisition) (87363) Financial - Revenue Growth (Yield) (87364) Financial - Revenue Protection (87365) Safety/Legal (87366) Service - Modernization (163341) Service - Other (87367) Sustainability (87368) Talent and Culture (110386) Tech Reliability (110383) Tech Development Experience (110384) | AH22: Select the type of value that this demand will drive. See below for available values to select for this field: - Brand - Financial - Cost Avoidance - Financial - Cost Savings/Reductions - Customer Experience - Recipient Experience - Customer Experience - Visibility - Customer Experience - Problem Resolution - Customer Experience - Other - Innovation - Financial - Revenue Growth (Customer Acquisition) - Financial - Revenue Growth (Yield) - Financial - Revenue Protection - Safety/Legal - Service - Modernization - Service - Other - Sustainability - Talent and Culture - Tech Reliability - Tech Development Experience | AI22: Req. | AO22: =IF(ISNUMBER(_xlfn.XMATCH(Table182[[#This Row],[DEV SB ID]],Platinum_Config[Target DEV SB ID],0))=FALSE,"No Match","Match") -> Match | AP22: =IF(ISNUMBER(_xlfn.XMATCH(Table182[[#This Row],[Target Field Name]],Platinum_Config[Target Field Name],0))=FALSE,"No Match","Match") -> Match | AQ22: =IF(AND(Table182[[#This Row],[Exists already? (ID)]]="No Match",Table182[[#This Row],[Exists already (Name)]]="No Match"),"No Match",IF(AND(Table182[[#This Row],[Exists already? (ID)]]="Match",Table182[[#This Row],[Exists already (Name)]]="Match"),"Double Match","One Match")) -> Double Match | AR22: Ignore
A23: L1 - Strategy Def | B23: Matt | C23: L1: Desired Business Outcomes and Business Case | D23: Initial Light Business Case | F23: Business Finance | G23: L1 | H23: Drive022 | M23: Does this Program impact Customer Experience? | P23: Follow up with finance to update definition; decide editability after L0/L1 ; need a separate line to give High, medium, low for CX and similar question for Service. Will also need a "Other Type of Value field | Q23: No | R23: No | T23: Str136 | U23: Str32 | AC23: Alt. Struct | AD23: Text | AE23: Single | AG23: Yes No | AH23: See below for available values to select for this field: - Yes - No | AI23: Opt. | AM23: Yes | AO23: =IF(ISNUMBER(_xlfn.XMATCH(Table182[[#This Row],[DEV SB ID]],Platinum_Config[Target DEV SB ID],0))=FALSE,"No Match","Match") -> Match | AP23: =IF(ISNUMBER(_xlfn.XMATCH(Table182[[#This Row],[Target Field Name]],Platinum_Config[Target Field Name],0))=FALSE,"No Match","Match") -> Match | AQ23: =IF(AND(Table182[[#This Row],[Exists already? (ID)]]="No Match",Table182[[#This Row],[Exists already (Name)]]="No Match"),"No Match",IF(AND(Table182[[#This Row],[Exists already? (ID)]]="Match",Table182[[#This Row],[Exists already (Name)]]="Match"),"Double Match","One Match")) -> Double Match | AR23: Added
A24: L1 - Strategy Def | B24: Matt | C24: L1: Desired Business Outcomes and Business Case | D24: Initial Light Business Case | F24: Business Finance | G24: L1 | H24: Drive023 | M24: If yes, indicate level of Customer Experience impact | P24: Follow up with finance to update definition; decide editability after L0/L1 ; need a separate line to give High, medium, low for CX and similar question for Service. Will also need a "Other Type of Value field | Q24: No | R24: No | T24: Wbs125 | U24: Wbs57 | AC24: Alt. Struct | AD24: Text | AE24: Single | AG24: High Medium Low | AH24: Indicate the level of impact the change will have on the selected Primary Type of Value. See below for available values to select for this field: - High - Medium - Low | AI24: Opt. | AO24: =IF(ISNUMBER(_xlfn.XMATCH(Table182[[#This Row],[DEV SB ID]],Platinum_Config[Target DEV SB ID],0))=FALSE,"No Match","Match") -> Match | AP24: =IF(ISNUMBER(_xlfn.XMATCH(Table182[[#This Row],[Target Field Name]],Platinum_Config[Target Field Name],0))=FALSE,"No Match","Match") -> Match | AQ24: =IF(AND(Table182[[#This Row],[Exists already? (ID)]]="No Match",Table182[[#This Row],[Exists already (Name)]]="No Match"),"No Match",IF(AND(Table182[[#This Row],[Exists already? (ID)]]="Match",Table182[[#This Row],[Exists already (Name)]]="Match"),"Double Match","One Match")) -> Double Match | AR24: Ignore
A25: L1 - Strategy Def | B25: Matt | C25: L1: Desired Business Outcomes and Business Case | D25: Initial Light Business Case | F25: Business Finance | G25: L1 | H25: Drive024 | M25: Does this Program impact Service? | P25: Follow up with finance to update definition; decide editability after L0/L1 ; need a separate line to give High, medium, low for CX and similar question for Service. Will also need a "Other Type of Value field | Q25: No | R25: No | T25: Str137 | U25: Str48 | AC25: Alt. Struct | AD25: Text | AE25: Single | AG25: Yes No | AH25: Indicate the level of impact the change will have on the selected Primary Type of Value. See below for available values to select for this field: - Yes - No | AI25: Opt. | AM25: Yes | AO25: =IF(ISNUMBER(_xlfn.XMATCH(Table182[[#This Row],[DEV SB ID]],Platinum_Config[Target DEV SB ID],0))=FALSE,"No Match","Match") -> Match | AP25: =IF(ISNUMBER(_xlfn.XMATCH(Table182[[#This Row],[Target Field Name]],Platinum_Config[Target Field Name],0))=FALSE,"No Match","Match") -> Match | AQ25: =IF(AND(Table182[[#This Row],[Exists already? (ID)]]="No Match",Table182[[#This Row],[Exists already (Name)]]="No Match"),"No Match",IF(AND(Table182[[#This Row],[Exists already? (ID)]]="Match",Table182[[#This Row],[Exists already (Name)]]="Match"),"Double Match","One Match")) -> Double Match | AR25: Added
A26: L1 - Strategy Def | B26: Matt | C26: L1: Desired Business Outcomes and Business Case | D26: Initial Light Business Case | F26: Business Finance | G26: L1 | H26: Drive025 | M26: If yes, indicate level of Service impact | P26: Follow up with finance to update definition; decide editability after L0/L1 ; need a separate line to give High, medium, low for CX and similar question for Service. Will also need a "Other Type of Value field | Q26: No | R26: No | T26: Wbs126 | U26: Wbs59 | AC26: Alt. Struct | AD26: Text | AE26: Single | AG26: High Medium Low | AH26: Indicate the level of impact the change will have on the selected Primary Type of Value. See below for available values to select for this field: - High - Medium - Low | AI26: Opt. | AO26: =IF(ISNUMBER(_xlfn.XMATCH(Table182[[#This Row],[DEV SB ID]],Platinum_Config[Target DEV SB ID],0))=FALSE,"No Match","Match") -> Match | AP26: =IF(ISNUMBER(_xlfn.XMATCH(Table182[[#This Row],[Target Field Name]],Platinum_Config[Target Field Name],0))=FALSE,"No Match","Match") -> Match | AQ26: =IF(AND(Table182[[#This Row],[Exists already? (ID)]]="No Match",Table182[[#This Row],[Exists already (Name)]]="No Match"),"No Match",IF(AND(Table182[[#This Row],[Exists already? (ID)]]="Match",Table182[[#This Row],[Exists already (Name)]]="Match"),"Double Match","One Match")) -> Double Match | AR26: Ignore
A27: L1 - Strategy Def | B27: Christina | C27: L1: Desired Business Outcomes and Business Case | D27: Enter Program OKRs and KPIs | F27: Program Manager | G27: L1 | H27: Drive026 | M27: Enterprise KPI | P27: Same as Enterprise KPI list we have today, but remove N/A option. Needs to select at least 1. | Q27: Yes | R27: Yes | S27: Str134 | T27: Str134 | U27: Str134 | AC27: Alt. Struct | AD27: Text | AE27: Multi | AG27: % of Revenue (166824) $ of Renewed Technology Contracts (165025) ADV (165026) Accident Rate Change (170252) Aircraft Maintenance per Flight Hour (FH) (165027) Attrition Rate (165028) Bad Debt % (165029) Box Stack Efficiency % (165030) Bulk Out Failure (165031) Burn Rate (165032) Cage Rate % (165033) Churn % (165034) Clearance-Related Service Failures (165035) CLH pivot Optimization % (165036) Code 85 % (165037) Consolidated LH $ per Mile (165038) Contact Problem Rate (165039) C. Ops Wage Rate (165040) Cost per Available Cu. Ft. Mile (165041) Cost per Hire (165042) Cost per Mile (165043) Cost per Stop (170253) CSP Contingency (165044) Cube Load Factor % (165045) Dead on Arrival % (165046) Density Score % (165047) EDD Accuracy % (165048) Expense as % of Revenue (165049) Freight Stack Efficiency % (165050) FRO Routing Compliance % (165051) Headcount Change (170254) Injury Rate Change (170255) Invoice Accuracy % (165052) LH Connection Cost (165053) LH Total Miles per Pkg (165054) Load Factor - Air (165055) Load Factor - Road (165056) Long-term Injury Frequency Rate (165057) MIS Flow % (165058) Missing Paperwork % (165059) N/A (170256) Net Pickup Reliability % (165060) Net Promoter Score (165061) Net Service Level % (165062) # of Actively Maintained Apps (165063) # of buildings closed (165064) # of buildings opened (165065) # of buildings transformed (165066) # of Damage Claims (165067) % of Data Products Internally Built (165068) # of Missing Packages (165069) # of Retired EAIs (165070) % of SAM (165071) On-time Clearance % (165072) On-time Flight Departure % (165073) Package Placement Score % (165074) Packages per FTE (165075) Packages per Stop (165076) PH Wage Rate (165077) Point-to-Catchment % (165078) RDL (165079) Recurring Problem Rate (165080) Resolved Problem Rate (165081) Revenue - Primarily B2B (165082) Revenue - Primarily B2C (165083) Scan Compliance % (165084) Scan Compliance/ HIP or HOP (165085) Self Service Solution % (165086) Settlement $ per Stop (165087) Shipment Overages (165089) Sort pkg per TLH (165090) Sort Pkgs per TLH (165092) Station Sort End Times (165093) Stops per Resource (165094) Transaction per FTE (TFTE) (165095) Volume per TLH (165096) WIP (165097) Wrong Address % (165098) Yield (165099) | AH27: Select one or more Enterprise KPI(s) that will be positively impacted by the successful results of this Program. See below for available values to select for this field: - % of Revenue - $ of Renewed Technology Contracts - ADV - Accident Rate Change - Aircraft Maintenance per Flight Hour (FH) - Attrition Rate - Bad Debt % - Box Stack Efficiency % - Bulk Out Failure - Burn Rate - Cage Rate % - Churn % - Clearance-Related Service Failures - CLH pivot Optimization % - Code 85 % - Consolidated LH $ per Mile - Contact Problem Rate - C. Ops Wage Rate - Cost per Available Cu. Ft. Mile - Cost per Hire - Cost per Mile - Cost per Stop - CSP Contingency - Cube Load Factor % - Dead on Arrival % - Density Score % - EDD Accuracy % - Expense as % of Revenue - Freight Stack Efficiency % - FRO Routing Compliance % - Headcount Change - Injury Rate Change - Invoice Accuracy % - LH Connection Cost - LH Total Miles per Pkg - Load Factor - Air - Load Factor - Road - Long-term Injury Frequency Rate - MIS Flow % - Missing Paperwork % - N/A - Net Pickup Reliability % - Net Promoter Score - Net Service Level % - # of Actively Maintained Apps - # of buildings closed - # of buildings opened - # of buildings transformed - # of Damage Claims - % of Data Products Internally Built - # of Missing Packages - # of Retired EAIs - % of SAM - On-time Clearance % - On-time Flight Departure % - Package Placement Score % - Packages per FTE - Packages per Stop - PH Wage Rate - Point-to-Catchment % - RDL - Recurring Problem Rate - Resolved Problem Rate - Revenue - Primarily B2B - Revenue - Primarily B2C - Scan Compliance % - Scan Compliance/ HIP or HOP - Self Service Solution % - Settlement $ per Stop - Shipment Overages - Sort pkg per TLH - Sort Pkgs per TLH - Station Sort End Times - Stops per Resource - Transaction per FTE (TFTE) - Volume per TLH - WIP - Wrong Address % - Yield | AI27: Req. | AJ27: Editable throughout | AM27: Yes | AO27: =IF(ISNUMBER(_xlfn.XMATCH(Table182[[#This Row],[DEV SB ID]],Platinum_Config[Target DEV SB ID],0))=FALSE,"No Match","Match") -> Match | AP27: =IF(ISNUMBER(_xlfn.XMATCH(Table182[[#This Row],[Target Field Name]],Platinum_Config[Target Field Name],0))=FALSE,"No Match","Match") -> Match | AQ27: =IF(AND(Table182[[#This Row],[Exists already? (ID)]]="No Match",Table182[[#This Row],[Exists already (Name)]]="No Match"),"No Match",IF(AND(Table182[[#This Row],[Exists already? (ID)]]="Match",Table182[[#This Row],[Exists already (Name)]]="Match"),"Double Match","One Match")) -> Double Match | AR27: Added
A28: L1 - Strategy Def | B28: Christina | C28: L1: Desired Business Outcomes and Business Case | D28: Enter Program OKRs and KPIs | F28: ESPM | G28: L1 | H28: Drive027 | M28: Program Dependencies | P28: Similar to dependencies we have today. May need ESPM to do this step due to the need to have RW access to dependent programs to be able to add the dependency | Q28: No | R28: No | T28: - | U28: - | AC28: Dependency container | AG28: Pulls from the existing Strategic Programs | AH28: Select any dependencies your program has on other programs. | AI28: - | AJ28: Editable throughout | AM28: Yes | AO28: =IF(ISNUMBER(_xlfn.XMATCH(Table182[[#This Row],[DEV SB ID]],Platinum_Config[Target DEV SB ID],0))=FALSE,"No Match","Match") -> Match | AP28: =IF(ISNUMBER(_xlfn.XMATCH(Table182[[#This Row],[Target Field Name]],Platinum_Config[Target Field Name],0))=FALSE,"No Match","Match") -> Match | AQ28: =IF(AND(Table182[[#This Row],[Exists already? (ID)]]="No Match",Table182[[#This Row],[Exists already (Name)]]="No Match"),"No Match",IF(AND(Table182[[#This Row],[Exists already? (ID)]]="Match",Table182[[#This Row],[Exists already (Name)]]="Match"),"Double Match","One Match")) -> Double Match | AR28: Added
A29: L1 - Strategy Def | B29: Christina | D29: Enter Dependencies | F29: Program Manager | G29: L1 | H29: Drive028 | M29: Commercial Dependencies | P29: [CD] - This is resolved and values are in column M | Q29: No | R29: No | T29: Str138 | U29: Str49 | AC29: Alt. Struct | AE29: Multi | AG29: US Domestic Parcel International Parcel International & US Domestic Freight Digital Products Transportation Distribution Products Warehousing & Distribution and Other Value-Added Services (VAS) Retail/Returns Customer Experience Pricing & New Surcharges | AH29: Select any commercial dependencies that your program relies on or will impact See below for available values to select for this field: - US Domestic Parcel - International Parcel - International & US Domestic Freight - Digital Products - Transportation Distribution Products - Warehousing & Distribution and Other Value-Added Services (VAS) - Retail/Returns - Customer Experience - Pricing & New Surcharges | AI29: Opt. | AJ29: Editable throughout | AM29: Yes | AO29: =IF(ISNUMBER(_xlfn.XMATCH(Table182[[#This Row],[DEV SB ID]],Platinum_Config[Target DEV SB ID],0))=FALSE,"No Match","Match") -> Match | AP29: =IF(ISNUMBER(_xlfn.XMATCH(Table182[[#This Row],[Target Field Name]],Platinum_Config[Target Field Name],0))=FALSE,"No Match","Match") -> Match | AQ29: =IF(AND(Table182[[#This Row],[Exists already? (ID)]]="No Match",Table182[[#This Row],[Exists already (Name)]]="No Match"),"No Match",IF(AND(Table182[[#This Row],[Exists already? (ID)]]="Match",Table182[[#This Row],[Exists already (Name)]]="Match"),"Double Match","One Match")) -> Double Match | AR29: Added
A30: L1 - Strategy Def | B30: Matt | C30: SL2 Business Finance Approval | D30: SL2 Business Finance Approval | F30: Business Finance | G30: L1 | H30: Drive029 | M30: SL2 Business Finance Approval | Q30: No | R30: No | T30: Str140 | U30: Str52 | AC30: Alt. Struct | AD30: Text | AE30: Single | AG30: Approved Not Approved - Feedback Requested | AH30: SL2 Business Finance Approval See below for available values to select for this field: - Approved - Not Approved - Feedback Requested | AI30: Req. | AO30: =IF(ISNUMBER(_xlfn.XMATCH(Table182[[#This Row],[DEV SB ID]],Platinum_Config[Target DEV SB ID],0))=FALSE,"No Match","Match") -> Match | AP30: =IF(ISNUMBER(_xlfn.XMATCH(Table182[[#This Row],[Target Field Name]],Platinum_Config[Target Field Name],0))=FALSE,"No Match","Match") -> Match | AQ30: =IF(AND(Table182[[#This Row],[Exists already? (ID)]]="No Match",Table182[[#This Row],[Exists already (Name)]]="No Match"),"No Match",IF(AND(Table182[[#This Row],[Exists already? (ID)]]="Match",Table182[[#This Row],[Exists already (Name)]]="Match"),"Double Match","One Match")) -> Double Match | AR30: Added
A31: L1 - Strategy Def | B31: Matt | C31: SL2 Business Finance Approval | D31: SL2 Business Finance Approval | F31: Business Finance | G31: L1 | H31: Drive030 | M31: SL2 Business Finance Approval Notes | Q31: No | R31: No | T31: fdx_bfin_appv_notes | U31: fdx_bfin_appv_notes | AC31: Field | AD31: Text | AH31: Enter Notes related to the SL2 Business Finance Approval | AI31: Req. | AO31: =IF(ISNUMBER(_xlfn.XMATCH(Table182[[#This Row],[DEV SB ID]],Platinum_Config[Target DEV SB ID],0))=FALSE,"No Match","Match") -> Match | AP31: =IF(ISNUMBER(_xlfn.XMATCH(Table182[[#This Row],[Target Field Name]],Platinum_Config[Target Field Name],0))=FALSE,"No Match","Match") -> Match | AQ31: =IF(AND(Table182[[#This Row],[Exists already? (ID)]]="No Match",Table182[[#This Row],[Exists already (Name)]]="No Match"),"No Match",IF(AND(Table182[[#This Row],[Exists already? (ID)]]="Match",Table182[[#This Row],[Exists already (Name)]]="Match"),"Double Match","One Match")) -> Double Match | AR31: Added
A32: L1 - Strategy Def | B32: Christina | C32: SL2 Program Owner Approval | D32: SL2 Program Owner Approval | F32: Program Owner | G32: L1 | H32: Drive031 | M32: SL2 Program Owner Approval | Q32: No | R32: No | T32: Str141 | U32: Str53 | AC32: Alt. Struct | AD32: Text | AE32: Single | AG32: Approved Not Approved - Feedback Requested | AH32: SL2 Program Owner Approval See below for available values to select for this field: - Approved - Not Approved - Feedback Requested | AI32: Req. | AJ32: No | AO32: =IF(ISNUMBER(_xlfn.XMATCH(Table182[[#This Row],[DEV SB ID]],Platinum_Config[Target DEV SB ID],0))=FALSE,"No Match","Match") -> Match | AP32: =IF(ISNUMBER(_xlfn.XMATCH(Table182[[#This Row],[Target Field Name]],Platinum_Config[Target Field Name],0))=FALSE,"No Match","Match") -> Match | AQ32: =IF(AND(Table182[[#This Row],[Exists already? (ID)]]="No Match",Table182[[#This Row],[Exists already (Name)]]="No Match"),"No Match",IF(AND(Table182[[#This Row],[Exists already? (ID)]]="Match",Table182[[#This Row],[Exists already (Name)]]="Match"),"Double Match","One Match")) -> Double Match | AR32: Added
A33: L1 - Strategy Def | B33: Matt | C33: SL2 Program Owner Approval | D33: SL2 Program Owner Approval | F33: Program Owner | G33: L1 | H33: Drive032 | M33: SL2 Program Owner Approval Notes | Q33: No | R33: No | T33: fdx_pgo_appv_notes | U33: fdx_pgo_appv_notes | AC33: Field | AD33: Text | AH33: Enter Notes related to the Program Owner Approval | AI33: Req. | AO33: =IF(ISNUMBER(_xlfn.XMATCH(Table182[[#This Row],[DEV SB ID]],Platinum_Config[Target DEV SB ID],0))=FALSE,"No Match","Match") -> Match | AP33: =IF(ISNUMBER(_xlfn.XMATCH(Table182[[#This Row],[Target Field Name]],Platinum_Config[Target Field Name],0))=FALSE,"No Match","Match") -> Match | AQ33: =IF(AND(Table182[[#This Row],[Exists already? (ID)]]="No Match",Table182[[#This Row],[Exists already (Name)]]="No Match"),"No Match",IF(AND(Table182[[#This Row],[Exists already? (ID)]]="Match",Table182[[#This Row],[Exists already (Name)]]="Match"),"Double Match","One Match")) -> Double Match | AR33: Added
A34: L1 - Strategy Def | B34: Christina | C34: SL2 ESPM Review | D34: SL2 ESPM Review | F34: ESPM Review | G34: L1 | H34: Drive033 | M34: SL2 ESPM Review | Q34: No | R34: No | T34: Str142 | U34: Str54 | AC34: Alt. Struct | AD34: Text | AE34: Single | AG34: Approved Not Approved - Feedback Requested | AH34: SL2 ESPM Review See below for available values to select for this field: - Approved - Not Approved - Feedback Requested | AI34: Req. | AJ34: No | AO34: =IF(ISNUMBER(_xlfn.XMATCH(Table182[[#This Row],[DEV SB ID]],Platinum_Config[Target DEV SB ID],0))=FALSE,"No Match","Match") -> Match | AP34: =IF(ISNUMBER(_xlfn.XMATCH(Table182[[#This Row],[Target Field Name]],Platinum_Config[Target Field Name],0))=FALSE,"No Match","Match") -> Match | AQ34: =IF(AND(Table182[[#This Row],[Exists already? (ID)]]="No Match",Table182[[#This Row],[Exists already (Name)]]="No Match"),"No Match",IF(AND(Table182[[#This Row],[Exists already? (ID)]]="Match",Table182[[#This Row],[Exists already (Name)]]="Match"),"Double Match","One Match")) -> Double Match | AR34: Added
A35: L1 - Strategy Def | B35: Matt | C35: SL2 ESPM Review | D35: SL2 ESPM Review | F35: ESPM Review | G35: L1 | H35: Drive034 | M35: SL2 ESPM Review Notes | Q35: No | R35: No | T35: fdx_espm_rev_notes | U35: fdx_espm_rev_notes | AC35: Field | AD35: Text | AH35: Enter Notes related to the SL2 ESPM Review | AI35: Req. | AO35: =IF(ISNUMBER(_xlfn.XMATCH(Table182[[#This Row],[DEV SB ID]],Platinum_Config[Target DEV SB ID],0))=FALSE,"No Match","Match") -> Match | AP35: =IF(ISNUMBER(_xlfn.XMATCH(Table182[[#This Row],[Target Field Name]],Platinum_Config[Target Field Name],0))=FALSE,"No Match","Match") -> Match | AQ35: =IF(AND(Table182[[#This Row],[Exists already? (ID)]]="No Match",Table182[[#This Row],[Exists already (Name)]]="No Match"),"No Match",IF(AND(Table182[[#This Row],[Exists already? (ID)]]="Match",Table182[[#This Row],[Exists already (Name)]]="Match"),"Double Match","One Match")) -> Double Match | AR35: Added
A36: L1 - Strategy Def | B36: Christina | C36: SL2 TO Approval | D36: SL2 TO Approval | F36: TO Approver | G36: L1 | H36: Drive035 | M36: SL2 TO Approval | P36: Reject notification goes to both Program manager and Program Owner | Q36: No | R36: No | T36: Str143 | U36: Str55 | AC36: Alt. Struct | AD36: Text | AE36: Single | AG36: Approved Not Approved - Feedback Requested Rejected | AH36: SL2 TO Approval See below for available values to select for this field: - Approved - Not Approved - Feedback Requested Rejected | AI36: Req. | AJ36: No | AM36: Yes | AO36: =IF(ISNUMBER(_xlfn.XMATCH(Table182[[#This Row],[DEV SB ID]],Platinum_Config[Target DEV SB ID],0))=FALSE,"No Match","Match") -> Match | AP36: =IF(ISNUMBER(_xlfn.XMATCH(Table182[[#This Row],[Target Field Name]],Platinum_Config[Target Field Name],0))=FALSE,"No Match","Match") -> Match | AQ36: =IF(AND(Table182[[#This Row],[Exists already? (ID)]]="No Match",Table182[[#This Row],[Exists already (Name)]]="No Match"),"No Match",IF(AND(Table182[[#This Row],[Exists already? (ID)]]="Match",Table182[[#This Row],[Exists already (Name)]]="Match"),"Double Match","One Match")) -> Double Match | AR36: Added
A37: L1 - Strategy Def | B37: Matt | C37: SL2 TO Approval | D37: SL2 TO Approval | F37: Program Owner | G37: L1 | H37: Drive036 | M37: SL2 TO Approval Notes | Q37: No | R37: No | T37: fdx_to_appv_notes | U37: fdx_to_appv_notes | AC37: Field | AD37: Text | AH37: Enter Notes related to the SL2 TO Approval | AI37: Req. | AO37: =IF(ISNUMBER(_xlfn.XMATCH(Table182[[#This Row],[DEV SB ID]],Platinum_Config[Target DEV SB ID],0))=FALSE,"No Match","Match") -> Match | AP37: =IF(ISNUMBER(_xlfn.XMATCH(Table182[[#This Row],[Target Field Name]],Platinum_Config[Target Field Name],0))=FALSE,"No Match","Match") -> Match | AQ37: =IF(AND(Table182[[#This Row],[Exists already? (ID)]]="No Match",Table182[[#This Row],[Exists already (Name)]]="No Match"),"No Match",IF(AND(Table182[[#This Row],[Exists already? (ID)]]="Match",Table182[[#This Row],[Exists already (Name)]]="Match"),"Double Match","One Match")) -> Double Match | AR37: Added
A38: L1 - Strategy Def | B38: Christina | G38: L1 | H38: Drive037 | M38: Status | P38: Attribute Name is Lifeycle Status CI - Should we add 'New' for L1? [CD] - I don't think there is a need to add "new". Active should be fine Yes-added 09Apr | Q38: Yes | R38: Yes | S38: SpsStatus | T38: SpsStatus | U38: SpsStatus | AC38: Alt. Struct | AD38: Text | AE38: Single | AG38: New Active On Hold Cancelled Complete Rejected | AH38: Program's current lifecycle status See below for available values to select for this field: - New - Active - On Hold - Cancelled - Completed - Rejected | AI38: RO | AJ38: Yes | AM38: Yes | AO38: =IF(ISNUMBER(_xlfn.XMATCH(Table182[[#This Row],[DEV SB ID]],Platinum_Config[Target DEV SB ID],0))=FALSE,"No Match","Match") -> Match | AP38: =IF(ISNUMBER(_xlfn.XMATCH(Table182[[#This Row],[Target Field Name]],Platinum_Config[Target Field Name],0))=FALSE,"No Match","Match") -> Match | AQ38: =IF(AND(Table182[[#This Row],[Exists already? (ID)]]="No Match",Table182[[#This Row],[Exists already (Name)]]="No Match"),"No Match",IF(AND(Table182[[#This Row],[Exists already? (ID)]]="Match",Table182[[#This Row],[Exists already (Name)]]="Match"),"Double Match","One Match")) -> Double Match | AR38: Added
A39: L1 - Strategy Def | G39: L1 | H39: Drive038 | M39: Program Type | P39: This is to disguish between DRIVE Strategic Program and D&T Program | Q39: No | R39: Yes | T39: Str144 | U39: Str61 | AC39: Alt. Struct | AD39: Text | AE39: Single | AG39: DRIVE Strategic Program D&T Program | AH39: See below for available values to select for this field: - DRIVE Strategic Program - D&T Program | AO39: =IF(ISNUMBER(_xlfn.XMATCH(Table182[[#This Row],[DEV SB ID]],Platinum_Config[Target DEV SB ID],0))=FALSE,"No Match","Match") -> Match | AP39: =IF(ISNUMBER(_xlfn.XMATCH(Table182[[#This Row],[Target Field Name]],Platinum_Config[Target Field Name],0))=FALSE,"No Match","Match") -> Match | AQ39: =IF(AND(Table182[[#This Row],[Exists already? (ID)]]="No Match",Table182[[#This Row],[Exists already (Name)]]="No Match"),"No Match",IF(AND(Table182[[#This Row],[Exists already? (ID)]]="Match",Table182[[#This Row],[Exists already (Name)]]="Match"),"Double Match","One Match")) -> Double Match | AR39: Added
A40: L1 - Strategy Def | D40: Program Approvals | G40: L1 | H40: Drive039 | M40: SL2 D&T Finance Approval | P40: D&T Strategic Program requirement. New attribute | Q40: No | R40: No | T40: Str146 | U40: Str92 | AC40: Alt. Struct | AD40: Text | AE40: Single | AG40: Approved Not Approved - Feedback Requested | AO40: =IF(ISNUMBER(_xlfn.XMATCH(Table182[[#This Row],[DEV SB ID]],Platinum_Config[Target DEV SB ID],0))=FALSE,"No Match","Match") -> Match | AP40: =IF(ISNUMBER(_xlfn.XMATCH(Table182[[#This Row],[Target Field Name]],Platinum_Config[Target Field Name],0))=FALSE,"No Match","Match") -> Match | AQ40: =IF(AND(Table182[[#This Row],[Exists already? (ID)]]="No Match",Table182[[#This Row],[Exists already (Name)]]="No Match"),"No Match",IF(AND(Table182[[#This Row],[Exists already? (ID)]]="Match",Table182[[#This Row],[Exists already (Name)]]="Match"),"Double Match","One Match")) -> Double Match | AR40: Added
A41: L1 - Strategy Def | D41: Program Approvals | G41: L1 | H41: Drive040 | M41: SL2 D&T Finance Approval Notes | P41: D&T Strategic Program requirement. New attribute | Q41: No | R41: No | T41: fdx_dtfin_appv_notes | U41: fdx_dtfin_appv_notes | AC41: Field | AD41: Text | AO41: =IF(ISNUMBER(_xlfn.XMATCH(Table182[[#This Row],[DEV SB ID]],Platinum_Config[Target DEV SB ID],0))=FALSE,"No Match","Match") -> Match | AP41: =IF(ISNUMBER(_xlfn.XMATCH(Table182[[#This Row],[Target Field Name]],Platinum_Config[Target Field Name],0))=FALSE,"No Match","Match") -> Match | AQ41: =IF(AND(Table182[[#This Row],[Exists already? (ID)]]="No Match",Table182[[#This Row],[Exists already (Name)]]="No Match"),"No Match",IF(AND(Table182[[#This Row],[Exists already? (ID)]]="Match",Table182[[#This Row],[Exists already (Name)]]="Match"),"Double Match","One Match")) -> Double Match | AR41: Added
A42: L1 - Strategy Def | D42: Program Approvals | G42: L1 | H42: Drive041 | M42: SL2 DTU Approval | P42: D&T Strategic Program requirement. New attribute | Q42: No | R42: No | T42: Str148 | U42: Str102 | AC42: Alt. Struct | AD42: Text | AE42: Single | AG42: Approved Not Approved - Feedback Requested Rejected | AO42: =IF(ISNUMBER(_xlfn.XMATCH(Table182[[#This Row],[DEV SB ID]],Platinum_Config[Target DEV SB ID],0))=FALSE,"No Match","Match") -> Match | AP42: =IF(ISNUMBER(_xlfn.XMATCH(Table182[[#This Row],[Target Field Name]],Platinum_Config[Target Field Name],0))=FALSE,"No Match","Match") -> Match | AQ42: =IF(AND(Table182[[#This Row],[Exists already? (ID)]]="No Match",Table182[[#This Row],[Exists already (Name)]]="No Match"),"No Match",IF(AND(Table182[[#This Row],[Exists already? (ID)]]="Match",Table182[[#This Row],[Exists already (Name)]]="Match"),"Double Match","One Match")) -> Double Match | AR42: Added
A43: L1 - Strategy Def | D43: Program Approvals | G43: L1 | H43: Drive042 | M43: SL2 DTU Approval Notes | P43: D&T Strategic Program requirement. New attribute | Q43: No | R43: No | T43: fdx_dtu_appv_notes | U43: fdx_dtu_appv_notes | AC43: Field | AD43: Text | AO43: =IF(ISNUMBER(_xlfn.XMATCH(Table182[[#This Row],[DEV SB ID]],Platinum_Config[Target DEV SB ID],0))=FALSE,"No Match","Match") -> Match | AP43: =IF(ISNUMBER(_xlfn.XMATCH(Table182[[#This Row],[Target Field Name]],Platinum_Config[Target Field Name],0))=FALSE,"No Match","Match") -> Match | AQ43: =IF(AND(Table182[[#This Row],[Exists already? (ID)]]="No Match",Table182[[#This Row],[Exists already (Name)]]="No Match"),"No Match",IF(AND(Table182[[#This Row],[Exists already? (ID)]]="Match",Table182[[#This Row],[Exists already (Name)]]="Match"),"Double Match","One Match")) -> Double Match | AR43: Added
A44: L1 - Strategy Def | D44: Program Approvals | G44: L1 | H44: Drive043 | M44: SL2 D&T SMO Review | P44: D&T Strategic Program requirement. New attribute | Q44: No | R44: No | U44: Str98 | AC44: Alt. Struct | AD44: Text | AE44: Single | AG44: Approved Not Approved - Feedback Requested Rejected | AO44: =IF(ISNUMBER(_xlfn.XMATCH(Table182[[#This Row],[DEV SB ID]],Platinum_Config[Target DEV SB ID],0))=FALSE,"No Match","Match") -> Match | AP44: =IF(ISNUMBER(_xlfn.XMATCH(Table182[[#This Row],[Target Field Name]],Platinum_Config[Target Field Name],0))=FALSE,"No Match","Match") -> Match | AQ44: =IF(AND(Table182[[#This Row],[Exists already? (ID)]]="No Match",Table182[[#This Row],[Exists already (Name)]]="No Match"),"No Match",IF(AND(Table182[[#This Row],[Exists already? (ID)]]="Match",Table182[[#This Row],[Exists already (Name)]]="Match"),"Double Match","One Match")) -> Double Match | AR44: Added
A45: L1 - Strategy Def | D45: Program Approvals | G45: L1 | H45: Drive044 | M45: SL2 D&T SMO Review Notes | P45: D&T Strategic Program requirement. New attribute | Q45: No | R45: No | U45: fdx_dtsmo_rev_notes | AC45: Field | AD45: Text | AO45: =IF(ISNUMBER(_xlfn.XMATCH(Table182[[#This Row],[DEV SB ID]],Platinum_Config[Target DEV SB ID],0))=FALSE,"No Match","Match") -> Match | AP45: =IF(ISNUMBER(_xlfn.XMATCH(Table182[[#This Row],[Target Field Name]],Platinum_Config[Target Field Name],0))=FALSE,"No Match","Match") -> Match | AQ45: =IF(AND(Table182[[#This Row],[Exists already? (ID)]]="No Match",Table182[[#This Row],[Exists already (Name)]]="No Match"),"No Match",IF(AND(Table182[[#This Row],[Exists already? (ID)]]="Match",Table182[[#This Row],[Exists already (Name)]]="Match"),"Double Match","One Match")) -> Double Match | AR45: Added
A46: L2-Design | C46: L2 Confirm Architecture Program Manager | D46: Assign Architecture PM | E46: Architecture Alignment | F46: EPM | G46: L2 | H46: Drive045 | K46: Program | L46: Program|190988 | M46: Architecture Program Manager | Q46: No | R46: Yes | T46: 178310 | U46: 190988 | AC46: Field | AD46: Text | AG46: Dynamic | AI46: Req. | AO46: =IF(ISNUMBER(_xlfn.XMATCH(Table182[[#This Row],[DEV SB ID]],Platinum_Config[Target DEV SB ID],0))=FALSE,"No Match","Match") -> Match | AP46: =IF(ISNUMBER(_xlfn.XMATCH(Table182[[#This Row],[Target Field Name]],Platinum_Config[Target Field Name],0))=FALSE,"No Match","Match") -> Match | AQ46: =IF(AND(Table182[[#This Row],[Exists already? (ID)]]="No Match",Table182[[#This Row],[Exists already (Name)]]="No Match"),"No Match",IF(AND(Table182[[#This Row],[Exists already? (ID)]]="Match",Table182[[#This Row],[Exists already (Name)]]="Match"),"Double Match","One Match")) -> Double Match | AR46: Ignore
A47: L2-Design | B47: Emilee, Pat/Macklin | C47: L2: Build Architecture (Strategic Design) | D47: Strategic Design Architecture Information | E47: Architecture Alignment | F47: Architecture Program Manager | G47: L2 | H47: Drive046 | K47: Program | L47: Program|Str109 | M47: Impacts Commercial Portfolio? | Q47: Yes | R47: Yes | S47: Str109 | T47: Str109 | U47: Str109 | AC47: Alt. Struct | AD47: Text | AE47: Single | AG47: Yes No | AH47: See below for available values to select for this field: - Yes - No | AI47: Req. | AO47: =IF(ISNUMBER(_xlfn.XMATCH(Table182[[#This Row],[DEV SB ID]],Platinum_Config[Target DEV SB ID],0))=FALSE,"No Match","Match") -> Match | AP47: =IF(ISNUMBER(_xlfn.XMATCH(Table182[[#This Row],[Target Field Name]],Platinum_Config[Target Field Name],0))=FALSE,"No Match","Match") -> Match | AQ47: =IF(AND(Table182[[#This Row],[Exists already? (ID)]]="No Match",Table182[[#This Row],[Exists already (Name)]]="No Match"),"No Match",IF(AND(Table182[[#This Row],[Exists already? (ID)]]="Match",Table182[[#This Row],[Exists already (Name)]]="Match"),"Double Match","One Match")) -> Double Match | AR47: Ignore
A48: L2-Design | B48: Emilee, Pat/Macklin | C48: L2: Build Architecture (Strategic Design) | D48: Strategic Design Architecture Information | E48: Architecture Alignment | F48: Architecture Program Manager | G48: L2 | H48: Drive047 | K48: Program | L48: Program|Str111 | M48: Impacts Enterprise Services Portfolio? | Q48: Yes | R48: Yes | S48: Str111 | T48: Str111 | U48: Str111 | AC48: Alt. Struct | AD48: Text | AE48: Single | AG48: Yes No | AH48: See below for available values to select for this field: - Yes - No | AI48: Req. | AO48: =IF(ISNUMBER(_xlfn.XMATCH(Table182[[#This Row],[DEV SB ID]],Platinum_Config[Target DEV SB ID],0))=FALSE,"No Match","Match") -> Match | AP48: =IF(ISNUMBER(_xlfn.XMATCH(Table182[[#This Row],[Target Field Name]],Platinum_Config[Target Field Name],0))=FALSE,"No Match","Match") -> Match | AQ48: =IF(AND(Table182[[#This Row],[Exists already? (ID)]]="No Match",Table182[[#This Row],[Exists already (Name)]]="No Match"),"No Match",IF(AND(Table182[[#This Row],[Exists already? (ID)]]="Match",Table182[[#This Row],[Exists already (Name)]]="Match"),"Double Match","One Match")) -> Double Match | AR48: Ignore
A49: L2-Design | B49: Emilee, Pat/Macklin | C49: L2: Build Architecture (Strategic Design) | D49: Strategic Design Architecture Information | E49: Architecture Alignment | F49: Architecture Program Manager | G49: L2 | H49: Drive048 | K49: Program | L49: Program|Str110 | M49: Impacts Platforms Portfolio? | Q49: Yes | R49: Yes | S49: Str110 | T49: Str110 | U49: Str110 | AC49: Alt. Struct | AD49: Text | AE49: Single | AG49: Yes No | AH49: See below for available values to select for this field: - Yes - No | AI49: Req. | AO49: =IF(ISNUMBER(_xlfn.XMATCH(Table182[[#This Row],[DEV SB ID]],Platinum_Config[Target DEV SB ID],0))=FALSE,"No Match","Match") -> Match | AP49: =IF(ISNUMBER(_xlfn.XMATCH(Table182[[#This Row],[Target Field Name]],Platinum_Config[Target Field Name],0))=FALSE,"No Match","Match") -> Match | AQ49: =IF(AND(Table182[[#This Row],[Exists already? (ID)]]="No Match",Table182[[#This Row],[Exists already (Name)]]="No Match"),"No Match",IF(AND(Table182[[#This Row],[Exists already? (ID)]]="Match",Table182[[#This Row],[Exists already (Name)]]="Match"),"Double Match","One Match")) -> Double Match | AR49: Ignore
A50: L2-Design | B50: Emilee, Pat/Macklin | C50: L2: Build Architecture (Strategic Design) | D50: Strategic Design Architecture Information | E50: Architecture Alignment | F50: Architecture Program Manager | G50: L2 | H50: Drive049 | K50: Program | L50: Program|Str113 | M50: Impacts Supply Chain Operations Portfolio? | Q50: Yes | R50: Yes | S50: Str113 | T50: Str113 | U50: Str113 | AC50: Alt. Struct | AD50: Text | AE50: Single | AG50: Yes No | AH50: See below for available values to select for this field: - Yes - No | AI50: Req. | AO50: =IF(ISNUMBER(_xlfn.XMATCH(Table182[[#This Row],[DEV SB ID]],Platinum_Config[Target DEV SB ID],0))=FALSE,"No Match","Match") -> Match | AP50: =IF(ISNUMBER(_xlfn.XMATCH(Table182[[#This Row],[Target Field Name]],Platinum_Config[Target Field Name],0))=FALSE,"No Match","Match") -> Match | AQ50: =IF(AND(Table182[[#This Row],[Exists already? (ID)]]="No Match",Table182[[#This Row],[Exists already (Name)]]="No Match"),"No Match",IF(AND(Table182[[#This Row],[Exists already? (ID)]]="Match",Table182[[#This Row],[Exists already (Name)]]="Match"),"Double Match","One Match")) -> Double Match | AR50: Ignore
A51: L2-Design | B51: Emilee, Pat/Macklin | C51: L2: Build Architecture (Strategic Design) | D51: Strategic Design Architecture Information | E51: Architecture Alignment | F51: Architecture Program Manager | G51: L2 | H51: Drive050 | K51: Program | L51: Program|fdx_eai | M51: Impacted EAI | Q51: Yes | R51: Label Chg | S51: fdx_eai | T51: fdx_eai | U51: fdx_eai | AC51: Field | AD51: Text | AH51: Enter EAI number here. Separate multiple EAIs by comma. The EAI (Enterprise Application Inventory) is the enterprise-wide authoritative repository that contains an inventory of application records along with their data elements that describe the characteristics of those applications. Once an application is created and stored in EAI, other systems like InfoSec, Business Continuity & Disaster Recovery, Legal and Regulatory, PDSM and Finance then use the application data to ascertain compliancy and impact analysis, hardware mapping, and total cost of ownership for that application. | AI51: Opt. | AM51: Yes | AO51: =IF(ISNUMBER(_xlfn.XMATCH(Table182[[#This Row],[DEV SB ID]],Platinum_Config[Target DEV SB ID],0))=FALSE,"No Match","Match") -> Match | AP51: =IF(ISNUMBER(_xlfn.XMATCH(Table182[[#This Row],[Target Field Name]],Platinum_Config[Target Field Name],0))=FALSE,"No Match","Match") -> Match | AQ51: =IF(AND(Table182[[#This Row],[Exists already? (ID)]]="No Match",Table182[[#This Row],[Exists already (Name)]]="No Match"),"No Match",IF(AND(Table182[[#This Row],[Exists already? (ID)]]="Match",Table182[[#This Row],[Exists already (Name)]]="Match"),"Double Match","One Match")) -> Double Match | AR51: Added
A52: L2-Design | C52: L2 Program Roadmap | D52: Add Program Milestones | E52: Schedule | F52: Program Manager | G52: L2 | H52: Drive051 | K52: Program Schedule | L52: Program|Field | M52: Start | Q52: No | R52: Yes | S52: strat_target_start | T52: strat_target_start | U52: Field | AO52: =IF(ISNUMBER(_xlfn.XMATCH(Table182[[#This Row],[DEV SB ID]],Platinum_Config[Target DEV SB ID],0))=FALSE,"No Match","Match") -> Match | AP52: =IF(ISNUMBER(_xlfn.XMATCH(Table182[[#This Row],[Target Field Name]],Platinum_Config[Target Field Name],0))=FALSE,"No Match","Match") -> Match | AQ52: =IF(AND(Table182[[#This Row],[Exists already? (ID)]]="No Match",Table182[[#This Row],[Exists already (Name)]]="No Match"),"No Match",IF(AND(Table182[[#This Row],[Exists already? (ID)]]="Match",Table182[[#This Row],[Exists already (Name)]]="Match"),"Double Match","One Match")) -> Double Match | AR52: Added
A53: L2-Design | C53: L2 Program Roadmap | D53: Add Program Milestones | E53: Schedule | F53: Program Manager | G53: L2 | H53: Drive052 | K53: Program Schedule | L53: Program|Field | M53: Finish | Q53: No | R53: Yes | S53: strat_target_finish | T53: strat_target_finish | U53: Field | AO53: =IF(ISNUMBER(_xlfn.XMATCH(Table182[[#This Row],[DEV SB ID]],Platinum_Config[Target DEV SB ID],0))=FALSE,"No Match","Match") -> Match | AP53: =IF(ISNUMBER(_xlfn.XMATCH(Table182[[#This Row],[Target Field Name]],Platinum_Config[Target Field Name],0))=FALSE,"No Match","Match") -> Match | AQ53: =IF(AND(Table182[[#This Row],[Exists already? (ID)]]="No Match",Table182[[#This Row],[Exists already (Name)]]="No Match"),"No Match",IF(AND(Table182[[#This Row],[Exists already? (ID)]]="Match",Table182[[#This Row],[Exists already (Name)]]="Match"),"Double Match","One Match")) -> Double Match | AR53: Added
A54: L2-Design | C54: L2 Program Roadmap | D54: Add Program Milestones | E54: Schedule | F54: Program Manager | G54: L2 | H54: Drive053 | K54: Program Schedule | L54: Program|MsTpS | M54: Type | Q54: No | R54: Yes | T54: MsTpS | U54: MsTpS | AC54: Alt. Struct | AD54: Text | AE54: Single | AG54: Milestone Type: Change Management Initiation & Governance Human Resources Implementation Legal / Regulatory Money Step Other Technology | AO54: =IF(ISNUMBER(_xlfn.XMATCH(Table182[[#This Row],[DEV SB ID]],Platinum_Config[Target DEV SB ID],0))=FALSE,"No Match","Match") -> Match | AP54: =IF(ISNUMBER(_xlfn.XMATCH(Table182[[#This Row],[Target Field Name]],Platinum_Config[Target Field Name],0))=FALSE,"No Match","Match") -> No Match | AQ54: =IF(AND(Table182[[#This Row],[Exists already? (ID)]]="No Match",Table182[[#This Row],[Exists already (Name)]]="No Match"),"No Match",IF(AND(Table182[[#This Row],[Exists already? (ID)]]="Match",Table182[[#This Row],[Exists already (Name)]]="Match"),"Double Match","One Match")) -> One Match | AR54: Added
A55: L2-Design | C55: L2 Program Roadmap | D55: Add Program Milestones | E55: Schedule | F55: Program Manager | G55: L2 | H55: Drive054 | K55: Program | L55: Program|DESCR | M55: Name | Q55: No | R55: Yes | T55: DESCR | U55: DESCR | AC55: Field | AD55: Text | AG55: Name from the Plan task row | AO55: =IF(ISNUMBER(_xlfn.XMATCH(Table182[[#This Row],[DEV SB ID]],Platinum_Config[Target DEV SB ID],0))=FALSE,"No Match","Match") -> Match | AP55: =IF(ISNUMBER(_xlfn.XMATCH(Table182[[#This Row],[Target Field Name]],Platinum_Config[Target Field Name],0))=FALSE,"No Match","Match") -> Match | AQ55: =IF(AND(Table182[[#This Row],[Exists already? (ID)]]="No Match",Table182[[#This Row],[Exists already (Name)]]="No Match"),"No Match",IF(AND(Table182[[#This Row],[Exists already? (ID)]]="Match",Table182[[#This Row],[Exists already (Name)]]="Match"),"Double Match","One Match")) -> Double Match | AR55: Ignore
A56: L2-Design | C56: L2 Program Roadmap | D56: Add Program Milestones | E56: Schedule | F56: Program Manager | G56: L2 | H56: Drive055 | K56: Program Schedule | L56: Program|MsCtS | M56: Category | Q56: No | R56: Yes | T56: MsCtS | U56: MsCtS | AC56: Alt. Struct | AD56: Text | AE56: Single | AG56: Milestone Category: Not started Started Completed | AO56: =IF(ISNUMBER(_xlfn.XMATCH(Table182[[#This Row],[DEV SB ID]],Platinum_Config[Target DEV SB ID],0))=FALSE,"No Match","Match") -> Match | AP56: =IF(ISNUMBER(_xlfn.XMATCH(Table182[[#This Row],[Target Field Name]],Platinum_Config[Target Field Name],0))=FALSE,"No Match","Match") -> No Match | AQ56: =IF(AND(Table182[[#This Row],[Exists already? (ID)]]="No Match",Table182[[#This Row],[Exists already (Name)]]="No Match"),"No Match",IF(AND(Table182[[#This Row],[Exists already? (ID)]]="Match",Table182[[#This Row],[Exists already (Name)]]="Match"),"Double Match","One Match")) -> One Match | AR56: Added
A57: L2-Design | C57: L2 Program Roadmap | D57: Add Program Milestones | E57: Schedule | F57: Program Manager | G57: L2 | H57: Drive056 | K57: Program Schedule | L57: Program|STRAT_WK_ACT_FIN | M57: Target | Q57: No | R57: Yes | T57: STRAT_WK_ACT_FIN | U57: STRAT_WK_ACT_FIN | AC57: Field | AD57: Date/Time | AG57: (Work Actual Finish) uncertain of accuracy | AO57: =IF(ISNUMBER(_xlfn.XMATCH(Table182[[#This Row],[DEV SB ID]],Platinum_Config[Target DEV SB ID],0))=FALSE,"No Match","Match") -> Match | AP57: =IF(ISNUMBER(_xlfn.XMATCH(Table182[[#This Row],[Target Field Name]],Platinum_Config[Target Field Name],0))=FALSE,"No Match","Match") -> Match | AQ57: =IF(AND(Table182[[#This Row],[Exists already? (ID)]]="No Match",Table182[[#This Row],[Exists already (Name)]]="No Match"),"No Match",IF(AND(Table182[[#This Row],[Exists already? (ID)]]="Match",Table182[[#This Row],[Exists already (Name)]]="Match"),"Double Match","One Match")) -> Double Match | AR57: Added
A58: L2-Design | C58: L2 Program Roadmap | D58: Add Program Milestones | E58: Schedule | F58: Program Manager | G58: L2 | H58: Drive057 | K58: Program Schedule | L58: Program|STRAT_WK_SCH_ACT_FIN | M58: Actual/Schedule | Q58: No | R58: Yes | T58: STRAT_WK_SCH_ACT_FIN | U58: STRAT_WK_SCH_ACT_FIN | AC58: Field | AD58: Date/Time | AG58: (Work Actual/Schedule Finish) uncertain of accuracy | AO58: =IF(ISNUMBER(_xlfn.XMATCH(Table182[[#This Row],[DEV SB ID]],Platinum_Config[Target DEV SB ID],0))=FALSE,"No Match","Match") -> Match | AP58: =IF(ISNUMBER(_xlfn.XMATCH(Table182[[#This Row],[Target Field Name]],Platinum_Config[Target Field Name],0))=FALSE,"No Match","Match") -> Match | AQ58: =IF(AND(Table182[[#This Row],[Exists already? (ID)]]="No Match",Table182[[#This Row],[Exists already (Name)]]="No Match"),"No Match",IF(AND(Table182[[#This Row],[Exists already? (ID)]]="Match",Table182[[#This Row],[Exists already (Name)]]="Match"),"Double Match","One Match")) -> Double Match | AR58: Added
A59: L2-Design | B59: Christina | C59: L2: Build Architecture (Strategic Design) | D59: Add New Work (Value Bundles) | F59: Program Manager | G59: L2 | H59: Drive058 | K59: Program | L59: Program|PARENT_DESCR | M59: Work Parent | P59: Always select "DRIVE" for Strategic Programs Value Bundles | Q59: Yes | R59: Yes | S59: PARENT_DESCR | T59: PARENT_DESCR | U59: PARENT_DESCR | AC59: Predefined | AD59: Text | AH59: If you are a requestor looking to submit a new request for a non-Program Tech Enabled demand (Discretionary/Non-Discretionary), select "Tech-Enabled Request" If you are an ESPM Program Manager user and creating a Value Bundle that is part of the DRIVE Strategic Program, then select "DRIVE". If you are an EPG/PEO user creating a Demand Bundle for an approved request for a non-Program Tech Enabled demand (Discretionary/Non-Discretionary), select "D&T Cross-Portfolio Demand" | AI59: Req. | AJ59: No | AO59: =IF(ISNUMBER(_xlfn.XMATCH(Table182[[#This Row],[DEV SB ID]],Platinum_Config[Target DEV SB ID],0))=FALSE,"No Match","Match") -> Match | AP59: =IF(ISNUMBER(_xlfn.XMATCH(Table182[[#This Row],[Target Field Name]],Platinum_Config[Target Field Name],0))=FALSE,"No Match","Match") -> Match | AQ59: =IF(AND(Table182[[#This Row],[Exists already? (ID)]]="No Match",Table182[[#This Row],[Exists already (Name)]]="No Match"),"No Match",IF(AND(Table182[[#This Row],[Exists already? (ID)]]="Match",Table182[[#This Row],[Exists already (Name)]]="Match"),"Double Match","One Match")) -> Double Match | AR59: Ignore
A60: L2-Design | B60: Christina | C60: L2: Build Architecture (Strategic Design) | D60: Add New Work (Value Bundles) | F60: Program Manager | G60: L2 | H60: Drive059 | K60: Program | L60: Program|Wbs22 | M60: Work Type | P60: [CD] We only want Program Value Bundle to show in this field if able | Q60: Yes | R60: Yes | S60: Wbs22 | T60: Wbs22 | U60: Wbs22 | AC60: Alt. Struct | AD60: Text | AE60: Single | AG60: Program Value Bundle Discretionary Non-Discretionary Tech-Enabled Request Business Demand | AH60: If creating a Value Bundle under Strategic Program, select "Program Value Bundle". If creating a tech enabled non-Program work, select "Demand Bundle". | AI60: Req. | AJ60: No | AO60: =IF(ISNUMBER(_xlfn.XMATCH(Table182[[#This Row],[DEV SB ID]],Platinum_Config[Target DEV SB ID],0))=FALSE,"No Match","Match") -> Match | AP60: =IF(ISNUMBER(_xlfn.XMATCH(Table182[[#This Row],[Target Field Name]],Platinum_Config[Target Field Name],0))=FALSE,"No Match","Match") -> Match | AQ60: =IF(AND(Table182[[#This Row],[Exists already? (ID)]]="No Match",Table182[[#This Row],[Exists already (Name)]]="No Match"),"No Match",IF(AND(Table182[[#This Row],[Exists already? (ID)]]="Match",Table182[[#This Row],[Exists already (Name)]]="Match"),"Double Match","One Match")) -> Double Match | AR60: Ignore
A61: L2-Design | B61: Christina | C61: L2: Build Architecture (Strategic Design) | D61: Add New Work (Value Bundles) | F61: Program Manager | G61: L2 | H61: Drive060 | K61: Program | L61: Program|DESCR | M61: Work Name | Q61: Yes | R61: Yes | S61: DESCR | T61: DESCR | U61: DESCR | AC61: Field | AD61: Text | AH61: Enter the name of the work. | AI61: Req. | AJ61: Yes | AM61: Yes | AO61: =IF(ISNUMBER(_xlfn.XMATCH(Table182[[#This Row],[DEV SB ID]],Platinum_Config[Target DEV SB ID],0))=FALSE,"No Match","Match") -> Match | AP61: =IF(ISNUMBER(_xlfn.XMATCH(Table182[[#This Row],[Target Field Name]],Platinum_Config[Target Field Name],0))=FALSE,"No Match","Match") -> Match | AQ61: =IF(AND(Table182[[#This Row],[Exists already? (ID)]]="No Match",Table182[[#This Row],[Exists already (Name)]]="No Match"),"No Match",IF(AND(Table182[[#This Row],[Exists already? (ID)]]="Match",Table182[[#This Row],[Exists already (Name)]]="Match"),"Double Match","One Match")) -> Double Match | AR61: Ignore
A62: L2-Design | C62: L2: Build Architecture (Strategic Design) | D62: Add New Work (Value Bundles) | F62: Program Manager | G62: L2 | H62: Drive061 | K62: Program | L62: Program|Wbs174 | M62: Does this work support either of these type of Programs? | Q62: No | R62: No | U62: Wbs174 | AC62: Alt. Struct | AD62: Text | AE62: Single | AG62: DRIVE Strategic Program (191607) D&T Program (191608) No (191609) | AO62: =IF(ISNUMBER(_xlfn.XMATCH(Table182[[#This Row],[DEV SB ID]],Platinum_Config[Target DEV SB ID],0))=FALSE,"No Match","Match") -> Match | AP62: =IF(ISNUMBER(_xlfn.XMATCH(Table182[[#This Row],[Target Field Name]],Platinum_Config[Target Field Name],0))=FALSE,"No Match","Match") -> No Match | AQ62: =IF(AND(Table182[[#This Row],[Exists already? (ID)]]="No Match",Table182[[#This Row],[Exists already (Name)]]="No Match"),"No Match",IF(AND(Table182[[#This Row],[Exists already? (ID)]]="Match",Table182[[#This Row],[Exists already (Name)]]="Match"),"Double Match","One Match")) -> One Match | AR62: Ignore
A63: L2-Design | B63: Christina | C63: L2: Build Architecture (Strategic Design) | D63: Add New Work (Value Bundles) | F63: Program Manager | G63: L2 | H63: Drive062 | K63: Program | L63: Program|Wbs66 | M63: Is this demand Business Only? | Q63: No | R63: No | S63: - | T63: Wbs138 | U63: Wbs66 | AC63: Alt. Struct | AD63: Text | AE63: Single | AG63: Yes No | AH63: Business Only means that there is no need for technical/development/architectural resources. See below for available values to select for this field: - Yes - No | AI63: Req. | AJ63: No | AO63: =IF(ISNUMBER(_xlfn.XMATCH(Table182[[#This Row],[DEV SB ID]],Platinum_Config[Target DEV SB ID],0))=FALSE,"No Match","Match") -> Match | AP63: =IF(ISNUMBER(_xlfn.XMATCH(Table182[[#This Row],[Target Field Name]],Platinum_Config[Target Field Name],0))=FALSE,"No Match","Match") -> Match | AQ63: =IF(AND(Table182[[#This Row],[Exists already? (ID)]]="No Match",Table182[[#This Row],[Exists already (Name)]]="No Match"),"No Match",IF(AND(Table182[[#This Row],[Exists already? (ID)]]="Match",Table182[[#This Row],[Exists already (Name)]]="Match"),"Double Match","One Match")) -> Double Match | AR63: Ignore
A64: L2-Design | C64: L2: Build Architecture (Strategic Design) | D64: Add New Work (Value Bundles) | F64: Program Manager | G64: L2 | H64: Drive063 | K64: Program | L64: Program|Wbs154 | M64: Is this Limited Visibility? | Q64: Yes | R64: label chg | S64: WR31 | T64: WR31 | U64: Wbs154 | AC64: Alt. Struct | AD64: Text | AE64: Single | AG64: Yes - Workforce Yes - Non-Workforce Yes - Privileged & Confidential No | AO64: =IF(ISNUMBER(_xlfn.XMATCH(Table182[[#This Row],[DEV SB ID]],Platinum_Config[Target DEV SB ID],0))=FALSE,"No Match","Match") -> Match | AP64: =IF(ISNUMBER(_xlfn.XMATCH(Table182[[#This Row],[Target Field Name]],Platinum_Config[Target Field Name],0))=FALSE,"No Match","Match") -> No Match | AQ64: =IF(AND(Table182[[#This Row],[Exists already? (ID)]]="No Match",Table182[[#This Row],[Exists already (Name)]]="No Match"),"No Match",IF(AND(Table182[[#This Row],[Exists already? (ID)]]="Match",Table182[[#This Row],[Exists already (Name)]]="Match"),"Double Match","One Match")) -> One Match | AR64: Ignore
A65: L2-Design | B65: Christina | C65: L2: Build Architecture (Strategic Design) | D65: Assign Roles and Responsibilities | F65: Program Manager | G65: L2 | H65: Drive064 | K65: Value Bundle | L65: Value Bundle|191003 | M65: Value Bundle Manager | Q65: No | R65: Yes | T65: 178353 | U65: 191003 | AC65: Field | AD65: Text | AE65: Multi | AG65: Dynamic | AI65: Req. | AJ65: Yes | AO65: =IF(ISNUMBER(_xlfn.XMATCH(Table182[[#This Row],[DEV SB ID]],Platinum_Config[Target DEV SB ID],0))=FALSE,"No Match","Match") -> Match | AP65: =IF(ISNUMBER(_xlfn.XMATCH(Table182[[#This Row],[Target Field Name]],Platinum_Config[Target Field Name],0))=FALSE,"No Match","Match") -> Match | AQ65: =IF(AND(Table182[[#This Row],[Exists already? (ID)]]="No Match",Table182[[#This Row],[Exists already (Name)]]="No Match"),"No Match",IF(AND(Table182[[#This Row],[Exists already? (ID)]]="Match",Table182[[#This Row],[Exists already (Name)]]="Match"),"Double Match","One Match")) -> Double Match | AR65: Added
A66: L2-Design | B66: Christina | C66: L2: Build Architecture (Strategic Design) | D66: Assign Roles and Responsibilities | F66: Program Manager | G66: L2 | H66: Drive065 | K66: Value Bundle | L66: Value Bundle|191003 | M66: Program Owner | Q66: No | R66: Yes | T66: 178308 | U66: 191003 | AC66: Field | AD66: Text | AE66: Single | AG66: Dynamic | AH66: The individual responsible for overseeing the strategy, execution, governance, and outcomes of a program. This role ensures that all work within the program collectively achieves the intended business objectives and deliver measurable value.​ | AI66: Req. | AJ66: Yes | AO66: =IF(ISNUMBER(_xlfn.XMATCH(Table182[[#This Row],[DEV SB ID]],Platinum_Config[Target DEV SB ID],0))=FALSE,"No Match","Match") -> No Match | AP66: =IF(ISNUMBER(_xlfn.XMATCH(Table182[[#This Row],[Target Field Name]],Platinum_Config[Target Field Name],0))=FALSE,"No Match","Match") -> Match | AQ66: =IF(AND(Table182[[#This Row],[Exists already? (ID)]]="No Match",Table182[[#This Row],[Exists already (Name)]]="No Match"),"No Match",IF(AND(Table182[[#This Row],[Exists already? (ID)]]="Match",Table182[[#This Row],[Exists already (Name)]]="Match"),"Double Match","One Match")) -> One Match | AR66: Revisit
A67: L2-Design | B67: Christina | C67: L2: Build Architecture (Strategic Design) | D67: Assign Roles and Responsibilities | F67: Program Manager | G67: L2 | H67: Drive066 | K67: Value Bundle | L67: Value Bundle|190984 | M67: Program Manager | Q67: No | R67: Yes | T67: 178309 | U67: 190984 | AC67: Field | AD67: Text | AE67: Multi | AG67: Dynamic | AH67: The individual(s) is responsible for planning, coordinating, and overseeing the execution of a program to ensure it delivers its intended strategic business outcomes. This role focuses on integrated delivery, governance, risk management, and cross‑team alignment to ensure all workstreams operate cohesively and effectively.​ | AI67: Req. | AJ67: Yes | AO67: =IF(ISNUMBER(_xlfn.XMATCH(Table182[[#This Row],[DEV SB ID]],Platinum_Config[Target DEV SB ID],0))=FALSE,"No Match","Match") -> Match | AP67: =IF(ISNUMBER(_xlfn.XMATCH(Table182[[#This Row],[Target Field Name]],Platinum_Config[Target Field Name],0))=FALSE,"No Match","Match") -> Match | AQ67: =IF(AND(Table182[[#This Row],[Exists already? (ID)]]="No Match",Table182[[#This Row],[Exists already (Name)]]="No Match"),"No Match",IF(AND(Table182[[#This Row],[Exists already? (ID)]]="Match",Table182[[#This Row],[Exists already (Name)]]="Match"),"Double Match","One Match")) -> Double Match | AR67: Ignore
A68: L2-Design | B68: Christina | C68: L2: Build Architecture (Strategic Design) | D68: Assign Roles and Responsibilities | F68: Program Manager | G68: L2 | H68: Drive067 | K68: Value Bundle | L68: Value Bundle|190985 | M68: D&T Captain | Q68: No | R68: Yes | T68: 178311 | U68: 190985 | AC68: Field | AD68: Text | AE68: Single | AG68: Dynamic | AH68: The designated leader within a strategic program who is accountable for driving the data, technology, and systems‑related components required to achieve program goals. This role ensures that data capabilities, technical solutions, and digital processes are aligned with the program’s strategy, integrated effectively, and able to support long‑term scalability | AI68: Req. | AJ68: No | AO68: =IF(ISNUMBER(_xlfn.XMATCH(Table182[[#This Row],[DEV SB ID]],Platinum_Config[Target DEV SB ID],0))=FALSE,"No Match","Match") -> Match | AP68: =IF(ISNUMBER(_xlfn.XMATCH(Table182[[#This Row],[Target Field Name]],Platinum_Config[Target Field Name],0))=FALSE,"No Match","Match") -> Match | AQ68: =IF(AND(Table182[[#This Row],[Exists already? (ID)]]="No Match",Table182[[#This Row],[Exists already (Name)]]="No Match"),"No Match",IF(AND(Table182[[#This Row],[Exists already? (ID)]]="Match",Table182[[#This Row],[Exists already (Name)]]="Match"),"Double Match","One Match")) -> Double Match | AR68: Ignore
A69: L2-Design | B69: Christina | C69: L2: Build Architecture (Strategic Design) | D69: Assign Roles and Responsibilities | E69: [CD] - Asked Matt Buxton for assistance with definition | F69: Program Manager | G69: L2 | H69: Drive068 | K69: Value Bundle | L69: Value Bundle|191004 | M69: D&T Finance | Q69: No | R69: Yes | T69: 178521 | U69: 191004 | AC69: Field | AD69: Text | AE69: Single | AG69: Dynamic | AI69: Req. | AJ69: No | AO69: =IF(ISNUMBER(_xlfn.XMATCH(Table182[[#This Row],[DEV SB ID]],Platinum_Config[Target DEV SB ID],0))=FALSE,"No Match","Match") -> Match | AP69: =IF(ISNUMBER(_xlfn.XMATCH(Table182[[#This Row],[Target Field Name]],Platinum_Config[Target Field Name],0))=FALSE,"No Match","Match") -> Match | AQ69: =IF(AND(Table182[[#This Row],[Exists already? (ID)]]="No Match",Table182[[#This Row],[Exists already (Name)]]="No Match"),"No Match",IF(AND(Table182[[#This Row],[Exists already? (ID)]]="Match",Table182[[#This Row],[Exists already (Name)]]="Match"),"Double Match","One Match")) -> Double Match | AR69: Ignore
A70: L2-Design | B70: Christina | C70: L2: Build Architecture (Strategic Design) | D70: Assign Roles and Responsibilities | F70: Program Manager | G70: L2 | H70: Drive069 | K70: Value Bundle | L70: Value Bundle|191005 | M70: EPG | Q70: No | R70: Yes | T70: 179115 | U70: 191005 | AC70: Field | AD70: Text | AE70: Multi | AG70: Dynamic | AH70: The designated representative authorized to formalize and record approvals on behalf of the portfolio governance group. This individual confirms that the group has aligned on portfolio accountability, prioritization, sequencing, and the removal of roadblocks, and then documents that collective decision. Acting as the execution point for the group’s agreed‑upon direction, the Approver ensures that technology work—across both DRIVE and non‑DRIVE initiatives—is positioned to accelerate delivery and meet key milestones before advancing to the next stage | AI70: Req. | AJ70: No | AO70: =IF(ISNUMBER(_xlfn.XMATCH(Table182[[#This Row],[DEV SB ID]],Platinum_Config[Target DEV SB ID],0))=FALSE,"No Match","Match") -> Match | AP70: =IF(ISNUMBER(_xlfn.XMATCH(Table182[[#This Row],[Target Field Name]],Platinum_Config[Target Field Name],0))=FALSE,"No Match","Match") -> Match | AQ70: =IF(AND(Table182[[#This Row],[Exists already? (ID)]]="No Match",Table182[[#This Row],[Exists already (Name)]]="No Match"),"No Match",IF(AND(Table182[[#This Row],[Exists already? (ID)]]="Match",Table182[[#This Row],[Exists already (Name)]]="Match"),"Double Match","One Match")) -> Double Match | AR70: Added
A71: L2-Design | B71: Christina | C71: L2: Build Architecture (Strategic Design) | D71: Assign Roles and Responsibilities | F71: Program Manager | G71: L2 | H71: Drive070 | K71: Value Bundle | L71: Value Bundle|190986 | M71: ESPM | Q71: No | R71: Yes | T71: 178312 | U71: 190986 | AC71: Field | AD71: Text | AE71: Multi | AG71: Dynamic | AH71: Centralized group that partners with program managers and business owners to guide the planning, alignment, and execution of strategic programs across the organization. They ensure programs are designed, prioritized, and managed in a way that advances enterprise‑level goals. | AI71: Req. | AJ71: Yes | AO71: =IF(ISNUMBER(_xlfn.XMATCH(Table182[[#This Row],[DEV SB ID]],Platinum_Config[Target DEV SB ID],0))=FALSE,"No Match","Match") -> Match | AP71: =IF(ISNUMBER(_xlfn.XMATCH(Table182[[#This Row],[Target Field Name]],Platinum_Config[Target Field Name],0))=FALSE,"No Match","Match") -> Match | AQ71: =IF(AND(Table182[[#This Row],[Exists already? (ID)]]="No Match",Table182[[#This Row],[Exists already (Name)]]="No Match"),"No Match",IF(AND(Table182[[#This Row],[Exists already? (ID)]]="Match",Table182[[#This Row],[Exists already (Name)]]="Match"),"Double Match","One Match")) -> Double Match | AR71: Ignore
A72: L2-Design | B72: Christina | C72: L2: Build Architecture (Strategic Design) | D72: Assign Roles and Responsibilities | E72: [CD] - Asked Matt Buxton for assistance with definition | F72: Program Manager | G72: L2 | H72: Drive071 | K72: Value Bundle | L72: Value Bundle|190987 | M72: Business Finance | Q72: No | R72: Yes | T72: 178340 | U72: 190987 | AC72: Field | AD72: Text | AE72: Multi | AG72: Dynamic | AI72: Req. | AJ72: No | AO72: =IF(ISNUMBER(_xlfn.XMATCH(Table182[[#This Row],[DEV SB ID]],Platinum_Config[Target DEV SB ID],0))=FALSE,"No Match","Match") -> Match | AP72: =IF(ISNUMBER(_xlfn.XMATCH(Table182[[#This Row],[Target Field Name]],Platinum_Config[Target Field Name],0))=FALSE,"No Match","Match") -> Match | AQ72: =IF(AND(Table182[[#This Row],[Exists already? (ID)]]="No Match",Table182[[#This Row],[Exists already (Name)]]="No Match"),"No Match",IF(AND(Table182[[#This Row],[Exists already? (ID)]]="Match",Table182[[#This Row],[Exists already (Name)]]="Match"),"Double Match","One Match")) -> Double Match | AR72: Ignore
A73: L2-Design | B73: Christina | C73: L2: Build Architecture (Strategic Design) | D73: Assign Roles and Responsibilities | F73: Program Manager | G73: L2 | H73: Drive072 | K73: Value Bundle | L73: Value Bundle|190988 | M73: Architecture Program Manager | P73: Applies to Business with Tech Only | Q73: No | R73: Yes | T73: 178310 | U73: 190988 | AC73: Field | AD73: Text | AE73: Single | AG73: Dynamic | AH73: Architectural role accountable for ensuring the program’s solutions align with enterprise strategy, architecture standards, and target-state blueprints. The EA Lead steers architectural direction, orchestrates cross-domain design decisions (business, data, application, integration, security, and infrastructure), and manages architectural risk and technical debt at the program level. The role facilitates decision-making and enforces guardrails through governance but does not directly own product delivery or approve business scope.​ | AI73: Req. | AJ73: Yes | AO73: =IF(ISNUMBER(_xlfn.XMATCH(Table182[[#This Row],[DEV SB ID]],Platinum_Config[Target DEV SB ID],0))=FALSE,"No Match","Match") -> Match | AP73: =IF(ISNUMBER(_xlfn.XMATCH(Table182[[#This Row],[Target Field Name]],Platinum_Config[Target Field Name],0))=FALSE,"No Match","Match") -> Match | AQ73: =IF(AND(Table182[[#This Row],[Exists already? (ID)]]="No Match",Table182[[#This Row],[Exists already (Name)]]="No Match"),"No Match",IF(AND(Table182[[#This Row],[Exists already? (ID)]]="Match",Table182[[#This Row],[Exists already (Name)]]="Match"),"Double Match","One Match")) -> Double Match | AR73: Ignore
A74: L2-Design | B74: Christina | C74: L2: Build Architecture (Strategic Design) | D74: Assign Roles and Responsibilities | E74: [CD] - Asked Matt Buxton for assistance with definition | F74: Program Manager | G74: L2 | H74: Drive073 | K74: Value Bundle | L74: Value Bundle|3399 | M74: TO Finance | Q74: Yes | R74: Yes | S74: 3399 | T74: 3399 | U74: 3399 | AC74: Field | AD74: Text | AE74: Single | AG74: Dynamic | AJ74: No | AO74: =IF(ISNUMBER(_xlfn.XMATCH(Table182[[#This Row],[DEV SB ID]],Platinum_Config[Target DEV SB ID],0))=FALSE,"No Match","Match") -> Match | AP74: =IF(ISNUMBER(_xlfn.XMATCH(Table182[[#This Row],[Target Field Name]],Platinum_Config[Target Field Name],0))=FALSE,"No Match","Match") -> Match | AQ74: =IF(AND(Table182[[#This Row],[Exists already? (ID)]]="No Match",Table182[[#This Row],[Exists already (Name)]]="No Match"),"No Match",IF(AND(Table182[[#This Row],[Exists already? (ID)]]="Match",Table182[[#This Row],[Exists already (Name)]]="Match"),"Double Match","One Match")) -> Double Match | AR74: Ignore
A75: L2-Design | B75: Christina | C75: L2: Build Architecture (Strategic Design) | D75: Assign Roles and Responsibilities | F75: Program Manager | G75: L2 | H75: Drive074 | K75: Value Bundle | L75: Value Bundle|190989 | M75: TO Approver | Q75: No | R75: Yes | T75: 178339 | U75: 190989 | AC75: Field | AD75: Text | AE75: Multi | AG75: Dynamic | AH75: Enterprise‑designated decision authority responsible for evaluating and formally approving programs and value bundles to progress to the next stage of the transformation lifecycle. This role ensures that each program and value bundle meets established strategic, financial, and operational criteria; aligns with enterprise priorities; and possesses the necessary readiness, resourcing, and value validation before advancing | AI75: Req. | AJ75: No | AO75: =IF(ISNUMBER(_xlfn.XMATCH(Table182[[#This Row],[DEV SB ID]],Platinum_Config[Target DEV SB ID],0))=FALSE,"No Match","Match") -> Match | AP75: =IF(ISNUMBER(_xlfn.XMATCH(Table182[[#This Row],[Target Field Name]],Platinum_Config[Target Field Name],0))=FALSE,"No Match","Match") -> Match | AQ75: =IF(AND(Table182[[#This Row],[Exists already? (ID)]]="No Match",Table182[[#This Row],[Exists already (Name)]]="No Match"),"No Match",IF(AND(Table182[[#This Row],[Exists already? (ID)]]="Match",Table182[[#This Row],[Exists already (Name)]]="Match"),"Double Match","One Match")) -> Double Match | AR75: Ignore
A76: L2-Design | B76: Christina | C76: L2: Build Architecture (Strategic Design) | D76: Assign Program & Sub Program | F76: Program Manager | G76: L2 | H76: Drive075 | K76: Value Bundle | L76: Value Bundle|STRATEGY_ALLO | M76: Associated Program | P76: This is the associated Program selected by the Program Manager when creating the value bundle | Q76: Yes | R76: Yes | S76: STRATEGY_ALLO | T76: STRATEGY_ALLO | U76: STRATEGY_ALLO | AC76: Predefined | AD76: Text | AG76: Dynamic | AI76: Req. | AM76: Yes | AO76: =IF(ISNUMBER(_xlfn.XMATCH(Table182[[#This Row],[DEV SB ID]],Platinum_Config[Target DEV SB ID],0))=FALSE,"No Match","Match") -> Match | AP76: =IF(ISNUMBER(_xlfn.XMATCH(Table182[[#This Row],[Target Field Name]],Platinum_Config[Target Field Name],0))=FALSE,"No Match","Match") -> No Match | AQ76: =IF(AND(Table182[[#This Row],[Exists already? (ID)]]="No Match",Table182[[#This Row],[Exists already (Name)]]="No Match"),"No Match",IF(AND(Table182[[#This Row],[Exists already? (ID)]]="Match",Table182[[#This Row],[Exists already (Name)]]="Match"),"Double Match","One Match")) -> One Match | AR76: Added
A77: L2-Design | B77: Christina | C77: L2: Build Architecture (Strategic Design) | D77: Assign Program & Sub Program | F77: Program Manager | G77: L2 | H77: Drive076 | K77: Value Bundle | L77: Value Bundle|Wbs67 | M77: Sub Program | P77: Per Christina, this will be unique based on the program and we may not know until the strategic design is done. The program manager will add this when they create the value bundle. Need to understand how often this will be, since an admin will have to add them. | Q77: No | R77: Yes | S77: - | T77: Wbs110 | U77: Wbs67 | AC77: Alt. Struct | AD77: Text | AE77: Single | AG77: values only available for GAF as of 09Mar2026 Level2: GAF (178406) Level3: GTM/Commercial Strategy (178407) Level3: E2E Customer Experience (178408) Level3: RFQ & Rapid Solutioning (178409) Level3: P&E/Capacity Planning (178410) Level3: Single P&L/Operations Org (178411) Level3: Finance Structure & Costing (178412) Level3: Technology (178414) | AH77: See below for available values to select for this field: - GAF - GTM/Commercial Strategy - E2E Customer Experience - RFQ & Rapid Solutioning - P&E/Capacity Planning - Single P&L/Operations Org - Finance Structure & Costing - Technology | AI77: Opt. | AM77: Yes | AO77: =IF(ISNUMBER(_xlfn.XMATCH(Table182[[#This Row],[DEV SB ID]],Platinum_Config[Target DEV SB ID],0))=FALSE,"No Match","Match") -> Match | AP77: =IF(ISNUMBER(_xlfn.XMATCH(Table182[[#This Row],[Target Field Name]],Platinum_Config[Target Field Name],0))=FALSE,"No Match","Match") -> Match | AQ77: =IF(AND(Table182[[#This Row],[Exists already? (ID)]]="No Match",Table182[[#This Row],[Exists already (Name)]]="No Match"),"No Match",IF(AND(Table182[[#This Row],[Exists already? (ID)]]="Match",Table182[[#This Row],[Exists already (Name)]]="Match"),"Double Match","One Match")) -> Double Match | AR77: Added
A78: L2-Design | B78: - | C78: L2: Build Architecture (Strategic Design) | D78: Demand Shaping | E78: Demand Shaping | F78: Architecture Program Manager / Value Bundle Manager for Business Only | G78: L2 | H78: Drive077 | K78: Value Bundle | L78: Value Bundle|PE01 | M78: Description | Q78: Yes | S78: PE01 | T78: PE01 | U78: PE01 | AC78: Field | AD78: Text | AH78: A short summary (3-5 sentences) outlining the purpose and scope of the demand. | AI78: Req. | AO78: =IF(ISNUMBER(_xlfn.XMATCH(Table182[[#This Row],[DEV SB ID]],Platinum_Config[Target DEV SB ID],0))=FALSE,"No Match","Match") -> Match | AP78: =IF(ISNUMBER(_xlfn.XMATCH(Table182[[#This Row],[Target Field Name]],Platinum_Config[Target Field Name],0))=FALSE,"No Match","Match") -> Match | AQ78: =IF(AND(Table182[[#This Row],[Exists already? (ID)]]="No Match",Table182[[#This Row],[Exists already (Name)]]="No Match"),"No Match",IF(AND(Table182[[#This Row],[Exists already? (ID)]]="Match",Table182[[#This Row],[Exists already (Name)]]="Match"),"Double Match","One Match")) -> Double Match | AR78: Ignore
A79: L2-Design | B79: - | C79: L2: Build Architecture (Strategic Design) | D79: Demand Shaping | E79: Demand Shaping | F79: N/A | G79: L2 | H79: Drive078 | K79: Value Bundle | L79: Value Bundle|Wbs20 | M79: Work Status | P79: Auto-filled | Q79: Yes | S79: Wbs20 | T79: Wbs20 | U79: Wbs20 | AC79: Alt. Struct | AD79: Text | AE79: Single | AG79: New (WBS20$REQT) Active (WBS20$OPEN) On Hold (WBS20$HOLD) Completed/Closed (WBS20$CLOS) Cancelled (WBS20$CNCL) Rejected (WBS20$DEND) | AH79: The status of the work entity. See below for available values for this field: - New - Active - On Hold - Completed/Closed - Cancelled - Rejected | AO79: =IF(ISNUMBER(_xlfn.XMATCH(Table182[[#This Row],[DEV SB ID]],Platinum_Config[Target DEV SB ID],0))=FALSE,"No Match","Match") -> Match | AP79: =IF(ISNUMBER(_xlfn.XMATCH(Table182[[#This Row],[Target Field Name]],Platinum_Config[Target Field Name],0))=FALSE,"No Match","Match") -> Match | AQ79: =IF(AND(Table182[[#This Row],[Exists already? (ID)]]="No Match",Table182[[#This Row],[Exists already (Name)]]="No Match"),"No Match",IF(AND(Table182[[#This Row],[Exists already? (ID)]]="Match",Table182[[#This Row],[Exists already (Name)]]="Match"),"Double Match","One Match")) -> Double Match | AR79: Ignore
A80: L2-Design | B80: - | C80: L2: Build Architecture (Strategic Design) | D80: Demand Shaping | E80: Demand Shaping | F80: N/A | G80: L2 | H80: Drive079 | K80: Value Bundle | L80: Value Bundle|Wbs28 | M80: Stage | P80: Auto-filled | Q80: Yes | S80: Wbs28 | T80: Wbs28 | U80: Wbs28 | AC80: Alt. Struct | AD80: Text | AE80: Single | AG80: A: L0 (WBS28DEFIN) B: SL1 (WBS28JUSTF) C: L1 (WBS28SCOPE) D: SL2 (9) E: L2 (WBS28EXECD) F: SL3 (10) G: L3 (WBS28DPLOY) H: SL4 (11) I: L4 (12) J: SL5 (4604) K: L5 (WBS28ANLBN) | AH80: See below for available values for this field: - C: L1 - D: SL2 - E: L2 - F: SL3 - G: L3 - H: SL4 - I: L4 - J: SL5 - K: L5 | AO80: =IF(ISNUMBER(_xlfn.XMATCH(Table182[[#This Row],[DEV SB ID]],Platinum_Config[Target DEV SB ID],0))=FALSE,"No Match","Match") -> Match | AP80: =IF(ISNUMBER(_xlfn.XMATCH(Table182[[#This Row],[Target Field Name]],Platinum_Config[Target Field Name],0))=FALSE,"No Match","Match") -> Match | AQ80: =IF(AND(Table182[[#This Row],[Exists already? (ID)]]="No Match",Table182[[#This Row],[Exists already (Name)]]="No Match"),"No Match",IF(AND(Table182[[#This Row],[Exists already? (ID)]]="Match",Table182[[#This Row],[Exists already (Name)]]="Match"),"Double Match","One Match")) -> Double Match | AR80: Ignore
A81: L2-Design | B81: Emilee, Pat/Macklin | C81: L2: Build Architecture (Strategic Design) | D81: Demand Shaping | E81: Demand Shaping | F81: Architecture Program Manager / Value Bundle Manager for Business Only | G81: L2 | H81: Drive080 | K81: Value Bundle | L81: Value Bundle|fdx_in_scope | M81: In Scope | Q81: Yes | R81: Yes | S81: fdx_in_scope | T81: fdx_in_scope | U81: fdx_in_scope | AC81: Field | AD81: Text | AH81: Areas that are explicitly included from the Value Bundle scope. | AI81: Req. | AO81: =IF(ISNUMBER(_xlfn.XMATCH(Table182[[#This Row],[DEV SB ID]],Platinum_Config[Target DEV SB ID],0))=FALSE,"No Match","Match") -> Match | AP81: =IF(ISNUMBER(_xlfn.XMATCH(Table182[[#This Row],[Target Field Name]],Platinum_Config[Target Field Name],0))=FALSE,"No Match","Match") -> Match | AQ81: =IF(AND(Table182[[#This Row],[Exists already? (ID)]]="No Match",Table182[[#This Row],[Exists already (Name)]]="No Match"),"No Match",IF(AND(Table182[[#This Row],[Exists already? (ID)]]="Match",Table182[[#This Row],[Exists already (Name)]]="Match"),"Double Match","One Match")) -> Double Match | AR81: Ignore
A82: L2-Design | B82: Emilee, Pat/Macklin | C82: L2: Build Architecture (Strategic Design) | D82: Demand Shaping | E82: Demand Shaping | F82: Architecture Program Manager / Value Bundle Manager for Business Only | G82: L2 | H82: Drive081 | K82: Value Bundle | L82: Value Bundle|fdx_out_of_scope | M82: Out of Scope | Q82: Yes | R82: Yes | S82: fdx_out_of_scope | T82: fdx_out_of_scope | U82: fdx_out_of_scope | AC82: Field | AD82: Text | AH82: Areas that are explicitly excluded from the Value Bundle scope. | AI82: Req. | AO82: =IF(ISNUMBER(_xlfn.XMATCH(Table182[[#This Row],[DEV SB ID]],Platinum_Config[Target DEV SB ID],0))=FALSE,"No Match","Match") -> Match | AP82: =IF(ISNUMBER(_xlfn.XMATCH(Table182[[#This Row],[Target Field Name]],Platinum_Config[Target Field Name],0))=FALSE,"No Match","Match") -> Match | AQ82: =IF(AND(Table182[[#This Row],[Exists already? (ID)]]="No Match",Table182[[#This Row],[Exists already (Name)]]="No Match"),"No Match",IF(AND(Table182[[#This Row],[Exists already? (ID)]]="Match",Table182[[#This Row],[Exists already (Name)]]="Match"),"Double Match","One Match")) -> Double Match | AR82: Ignore
A83: L2-Design | B83: Emilee, Pat/Macklin | C83: L2: Build Architecture (Strategic Design) | D83: Demand Shaping | E83: Demand Shaping | F83: Architecture Program Manager / Value Bundle Manager for Business Only | G83: L2 | H83: Drive082 | K83: Value Bundle | L83: Value Bundle|fdx_biz_out_work | M83: Expected Business Outcome | Q83: Yes | R83: Yes | S83: fdx_biz_out_work | T83: fdx_biz_out_work | U83: fdx_biz_out_work | AC83: Field | AD83: Text | AH83: Anticipated results or benefits from the demand completion. | AI83: Req. | AM83: Yes | AO83: =IF(ISNUMBER(_xlfn.XMATCH(Table182[[#This Row],[DEV SB ID]],Platinum_Config[Target DEV SB ID],0))=FALSE,"No Match","Match") -> Match | AP83: =IF(ISNUMBER(_xlfn.XMATCH(Table182[[#This Row],[Target Field Name]],Platinum_Config[Target Field Name],0))=FALSE,"No Match","Match") -> Match | AQ83: =IF(AND(Table182[[#This Row],[Exists already? (ID)]]="No Match",Table182[[#This Row],[Exists already (Name)]]="No Match"),"No Match",IF(AND(Table182[[#This Row],[Exists already? (ID)]]="Match",Table182[[#This Row],[Exists already (Name)]]="Match"),"Double Match","One Match")) -> Double Match | AR83: Ignore
A84: L2-Design | B84: Emilee, Pat/Macklin | C84: L2: Build Architecture (Strategic Design) | D84: Demand Shaping | E84: Demand Shaping | F84: Architecture Program Manager / Value Bundle Manager for Business Only | G84: L2 | H84: Drive083 | K84: Value Bundle | L84: Value Bundle|Str36 | M84: Business Complexity Estimate | Q84: Yes | R84: Yes | S84: Str36 | T84: Str36 | U84: Str36 | AC84: Alt. Struct | AD84: Text | AE84: Single | AG84: 1: Minimal 2: Low 3: Medium 4: High 5: Maximum | AH84: Estimate of the complexity of demand that considers: ﻿﻿- Degree of business process change ﻿﻿- Dependencies on other initiatives - Experience in implementing the technology ﻿- Minimal: No change to existing business processes - Low: Minimal impact to existing business processes - Medium: Impacts day to day business operations - High: Significant impact on day-day business operations - Maximum: Severe impact on day-day business operations | AI84: Req. | AJ84: Never | AK84: n/a | AL84: n/a | AM84: Yes | AO84: =IF(ISNUMBER(_xlfn.XMATCH(Table182[[#This Row],[DEV SB ID]],Platinum_Config[Target DEV SB ID],0))=FALSE,"No Match","Match") -> Match | AP84: =IF(ISNUMBER(_xlfn.XMATCH(Table182[[#This Row],[Target Field Name]],Platinum_Config[Target Field Name],0))=FALSE,"No Match","Match") -> Match | AQ84: =IF(AND(Table182[[#This Row],[Exists already? (ID)]]="No Match",Table182[[#This Row],[Exists already (Name)]]="No Match"),"No Match",IF(AND(Table182[[#This Row],[Exists already? (ID)]]="Match",Table182[[#This Row],[Exists already (Name)]]="Match"),"Double Match","One Match")) -> Double Match | AR84: Ignore
A85: L2-Design | B85: Emilee, Pat/Macklin | C85: L2: Build Architecture (Strategic Design) | D85: Demand Shaping | E85: Demand Shaping | F85: Architecture Program Manager / Value Bundle Manager for Business Only | G85: L2 | H85: Drive084 | K85: Value Bundle | L85: Value Bundle|fdx_biz_impact_work | M85: Business Process and/or Operational Impact | Q85: Yes | R85: Yes | S85: fdx_biz_impact_work | T85: fdx_biz_impact_work | U85: fdx_biz_impact_work | AC85: Field | AD85: Text | AH85: Please describe the current and future state business process(es), outlining the activities or tasks involved and their potential impact on daily operations. Refrain from using one-line statements and avoid proposing solutions or making assumptions that bridge the gap between current and future state. In addition, upload any supporting documentation such as process flows or other visual aids explaining the current process in the ‘Content’ section of Planview. | AI85: Req. | AO85: =IF(ISNUMBER(_xlfn.XMATCH(Table182[[#This Row],[DEV SB ID]],Platinum_Config[Target DEV SB ID],0))=FALSE,"No Match","Match") -> Match | AP85: =IF(ISNUMBER(_xlfn.XMATCH(Table182[[#This Row],[Target Field Name]],Platinum_Config[Target Field Name],0))=FALSE,"No Match","Match") -> Match | AQ85: =IF(AND(Table182[[#This Row],[Exists already? (ID)]]="No Match",Table182[[#This Row],[Exists already (Name)]]="No Match"),"No Match",IF(AND(Table182[[#This Row],[Exists already? (ID)]]="Match",Table182[[#This Row],[Exists already (Name)]]="Match"),"Double Match","One Match")) -> Double Match | AR85: Added
A86: L2-Design | B86: Emilee, Pat/Macklin | C86: L2: Build Architecture (Strategic Design) | D86: Demand Shaping | E86: Demand Shaping | F86: Architecture Program Manager / Value Bundle Manager for Business Only | G86: L2 | H86: Drive085 | K86: Value Bundle | L86: Value Bundle|Wbs94 | M86: Region(s) Impacted | Q86: Yes | R86: Yes | S86: Wbs94 | T86: Wbs94 | U86: Wbs94 | AC86: Alt. Struct | AD86: Text | AE86: Multi | AG86: USA (96158) Europe (96159) Asia/Middle East/India/Africa (AMEA) (96160) Canada (96161) Latin America (96162) International HQ (96163) | AH86: See below for available values to select for this field: - USA - Europe - Asia/Middle East/India/Africa (AMEA) - Canada - Latin America - International HQ | AI86: Req. | AO86: =IF(ISNUMBER(_xlfn.XMATCH(Table182[[#This Row],[DEV SB ID]],Platinum_Config[Target DEV SB ID],0))=FALSE,"No Match","Match") -> Match | AP86: =IF(ISNUMBER(_xlfn.XMATCH(Table182[[#This Row],[Target Field Name]],Platinum_Config[Target Field Name],0))=FALSE,"No Match","Match") -> Match | AQ86: =IF(AND(Table182[[#This Row],[Exists already? (ID)]]="No Match",Table182[[#This Row],[Exists already (Name)]]="No Match"),"No Match",IF(AND(Table182[[#This Row],[Exists already? (ID)]]="Match",Table182[[#This Row],[Exists already (Name)]]="Match"),"Double Match","One Match")) -> Double Match | AR86: Ignore
A87: L2-Design | B87: Emilee, Pat/Macklin | C87: L2: Build Architecture (Strategic Design) | D87: Demand Shaping | E87: Information from Architecture Alignment | F87: Architecture Program Manager / Value Bundle Manager for Business Only | G87: L2 | H87: Drive087 | K87: Value Bundle | L87: Value Bundle|Str62 | M87: T-Shirt Size | P87: Applies to Business with Tech Only | Q87: Yes | R87: Yes | S87: Str62 | T87: Str62 | U87: Str62 | AC87: Alt. Struct | AD87: Text | AE87: Single | AG87: 1: XS (3894) 2: S (3895) 3: M (3896) 4: L (3897) 5: XL (3898) | AH87: Estimate of the effort required to successfully implement the initiative. Implementation time frame: - XS: 1 PIs with 1 ART - S: 2-3 PI with 1-2 ARTs - M: 3-5 PIs with multiple ARTs - L: 5-8 PIs with multiple ARTs - XL: >8 PIs with multiple ARTs Reach out to your Enterprise Architecture team if you need help with estimates. | AI87: Req. | AM87: Yes | AO87: =IF(ISNUMBER(_xlfn.XMATCH(Table182[[#This Row],[DEV SB ID]],Platinum_Config[Target DEV SB ID],0))=FALSE,"No Match","Match") -> Match | AP87: =IF(ISNUMBER(_xlfn.XMATCH(Table182[[#This Row],[Target Field Name]],Platinum_Config[Target Field Name],0))=FALSE,"No Match","Match") -> Match | AQ87: =IF(AND(Table182[[#This Row],[Exists already? (ID)]]="No Match",Table182[[#This Row],[Exists already (Name)]]="No Match"),"No Match",IF(AND(Table182[[#This Row],[Exists already? (ID)]]="Match",Table182[[#This Row],[Exists already (Name)]]="Match"),"Double Match","One Match")) -> Double Match | AR87: Ignore
A88: L2-Design | B88: Emilee, Pat/Macklin | C88: L2: Build Architecture (Strategic Design) | D88: Demand Shaping | E88: Information from Architecture Alignment | F88: Architecture Program Manager | G88: L2 | H88: Drive088 | K88: Value Bundle | L88: Value Bundle|Str109 | M88: Impacts Commercial Portfolio? | P88: Applies to Business with Tech Only | Q88: No | R88: No | S88: Str109 | T88: Str109 | U88: Str109 | AC88: Alt. Struct | AD88: Text | AE88: Single | AG88: Yes No | AH88: See below for available values to select for this field: - Yes - No | AI88: Req. | AM88: Yes | AO88: =IF(ISNUMBER(_xlfn.XMATCH(Table182[[#This Row],[DEV SB ID]],Platinum_Config[Target DEV SB ID],0))=FALSE,"No Match","Match") -> Match | AP88: =IF(ISNUMBER(_xlfn.XMATCH(Table182[[#This Row],[Target Field Name]],Platinum_Config[Target Field Name],0))=FALSE,"No Match","Match") -> Match | AQ88: =IF(AND(Table182[[#This Row],[Exists already? (ID)]]="No Match",Table182[[#This Row],[Exists already (Name)]]="No Match"),"No Match",IF(AND(Table182[[#This Row],[Exists already? (ID)]]="Match",Table182[[#This Row],[Exists already (Name)]]="Match"),"Double Match","One Match")) -> Double Match | AR88: Ignore
A89: L2-Design | B89: Emilee, Pat/Macklin | C89: L2: Build Architecture (Strategic Design) | D89: Demand Shaping | E89: Information from Architecture Alignment | F89: Architecture Program Manager | G89: L2 | H89: Drive089 | K89: Value Bundle | L89: Value Bundle|Str111 | M89: Impacts Enterprise Services Portfolio? | P89: Applies to Business with Tech Only | Q89: Yes | R89: Yes | S89: Str111 | T89: Str111 | U89: Str111 | AC89: Alt. Struct | AD89: Text | AE89: Single | AG89: Yes No | AH89: See below for available values to select for this field: - Yes - No | AO89: =IF(ISNUMBER(_xlfn.XMATCH(Table182[[#This Row],[DEV SB ID]],Platinum_Config[Target DEV SB ID],0))=FALSE,"No Match","Match") -> Match | AP89: =IF(ISNUMBER(_xlfn.XMATCH(Table182[[#This Row],[Target Field Name]],Platinum_Config[Target Field Name],0))=FALSE,"No Match","Match") -> Match | AQ89: =IF(AND(Table182[[#This Row],[Exists already? (ID)]]="No Match",Table182[[#This Row],[Exists already (Name)]]="No Match"),"No Match",IF(AND(Table182[[#This Row],[Exists already? (ID)]]="Match",Table182[[#This Row],[Exists already (Name)]]="Match"),"Double Match","One Match")) -> Double Match | AR89: Ignore
A90: L2-Design | B90: Emilee, Pat/Macklin | C90: L2: Build Architecture (Strategic Design) | D90: Demand Shaping | E90: Information from Architecture Alignment | F90: Architecture Program Manager | G90: L2 | H90: Drive090 | K90: Value Bundle | L90: Value Bundle|Str110 | M90: Impacts Platforms Portfolio? | P90: Applies to Business with Tech Only | Q90: Yes | R90: Yes | S90: Str110 | T90: Str110 | U90: Str110 | AC90: Alt. Struct | AD90: Text | AE90: Single | AG90: Yes No | AH90: See below for available values to select for this field: - Yes - No | AO90: =IF(ISNUMBER(_xlfn.XMATCH(Table182[[#This Row],[DEV SB ID]],Platinum_Config[Target DEV SB ID],0))=FALSE,"No Match","Match") -> Match | AP90: =IF(ISNUMBER(_xlfn.XMATCH(Table182[[#This Row],[Target Field Name]],Platinum_Config[Target Field Name],0))=FALSE,"No Match","Match") -> Match | AQ90: =IF(AND(Table182[[#This Row],[Exists already? (ID)]]="No Match",Table182[[#This Row],[Exists already (Name)]]="No Match"),"No Match",IF(AND(Table182[[#This Row],[Exists already? (ID)]]="Match",Table182[[#This Row],[Exists already (Name)]]="Match"),"Double Match","One Match")) -> Double Match | AR90: Ignore
A91: L2-Design | B91: Emilee, Pat/Macklin | C91: L2: Build Architecture (Strategic Design) | D91: Demand Shaping | E91: Information from Architecture Alignment | F91: Architecture Program Manager | G91: L2 | H91: Drive091 | K91: Value Bundle | L91: Value Bundle|Str113 | M91: Impacts Supply Chain Operations Portfolio? | P91: Applies to Business with Tech Only | Q91: Yes | R91: Yes | S91: Str113 | T91: Str113 | U91: Str113 | AC91: Alt. Struct | AD91: Text | AE91: Single | AG91: Yes No | AH91: See below for available values to select for this field: - Yes - No | AO91: =IF(ISNUMBER(_xlfn.XMATCH(Table182[[#This Row],[DEV SB ID]],Platinum_Config[Target DEV SB ID],0))=FALSE,"No Match","Match") -> Match | AP91: =IF(ISNUMBER(_xlfn.XMATCH(Table182[[#This Row],[Target Field Name]],Platinum_Config[Target Field Name],0))=FALSE,"No Match","Match") -> Match | AQ91: =IF(AND(Table182[[#This Row],[Exists already? (ID)]]="No Match",Table182[[#This Row],[Exists already (Name)]]="No Match"),"No Match",IF(AND(Table182[[#This Row],[Exists already? (ID)]]="Match",Table182[[#This Row],[Exists already (Name)]]="Match"),"Double Match","One Match")) -> Double Match | AR91: Ignore
A92: L2-Design | B92: Emilee, Pat/Macklin | C92: L2: Build Architecture (Strategic Design) | D92: Demand Shaping | E92: Information from Architecture Alignment | F92: Architecture Program Manager | G92: L2 | H92: Drive092 | K92: Value Bundle | L92: Value Bundle|fdx_eai_work | M92: EAI # | P92: Applies to Business with Tech Only | Q92: Yes | R92: Yes | S92: fdx_eai_work | T92: fdx_eai_work | U92: fdx_eai_work | AC92: Field | AD92: Text | AH92: Enter EAI number here. Separate multiple EAIs by comma. The EAI (Enterprise Application Inventory) is the enterprise-wide authoritative repository that contains an inventory of application records along with their data elements that describe the characteristics of those applications. Once an application is created and stored in EAI, other systems like InfoSec, Business Continuity & Disaster Recovery, Legal and Regulatory, PDSM and Finance then use the application data to ascertain compliancy and impact analysis, hardware mapping, and total cost of ownership for that application. | AI92: Opt. | AM92: Yes | AO92: =IF(ISNUMBER(_xlfn.XMATCH(Table182[[#This Row],[DEV SB ID]],Platinum_Config[Target DEV SB ID],0))=FALSE,"No Match","Match") -> Match | AP92: =IF(ISNUMBER(_xlfn.XMATCH(Table182[[#This Row],[Target Field Name]],Platinum_Config[Target Field Name],0))=FALSE,"No Match","Match") -> Match | AQ92: =IF(AND(Table182[[#This Row],[Exists already? (ID)]]="No Match",Table182[[#This Row],[Exists already (Name)]]="No Match"),"No Match",IF(AND(Table182[[#This Row],[Exists already? (ID)]]="Match",Table182[[#This Row],[Exists already (Name)]]="Match"),"Double Match","One Match")) -> Double Match | AR92: Ignore
A93: L2-Design | B93: Emilee, Pat/Macklin | C93: L2: Build Architecture (Strategic Design) | D93: Demand Shaping | E93: Information from Architecture Alignment | F93: Architecture Program Manager | G93: L2 | H93: Drive093 | K93: Value Bundle | L93: Value Bundle|fdx_epic_archdoc_URL | M93: Architectural Documentation | P93: Applies to Business with Tech Only | Q93: Yes | R93: Yes | S93: fdx_epic_archdoc_URL | T93: fdx_epic_archdoc_URL | U93: fdx_epic_archdoc_URL | AC93: Field | AD93: Units | AH93: Link to any architectural documentation. | AI93: Req. | AO93: =IF(ISNUMBER(_xlfn.XMATCH(Table182[[#This Row],[DEV SB ID]],Platinum_Config[Target DEV SB ID],0))=FALSE,"No Match","Match") -> Match | AP93: =IF(ISNUMBER(_xlfn.XMATCH(Table182[[#This Row],[Target Field Name]],Platinum_Config[Target Field Name],0))=FALSE,"No Match","Match") -> Match | AQ93: =IF(AND(Table182[[#This Row],[Exists already? (ID)]]="No Match",Table182[[#This Row],[Exists already (Name)]]="No Match"),"No Match",IF(AND(Table182[[#This Row],[Exists already? (ID)]]="Match",Table182[[#This Row],[Exists already (Name)]]="Match"),"Double Match","One Match")) -> Double Match | AR93: Ignore
A94: L2-Design | B94: Emilee, Pat/Macklin | C94: L2: Build Architecture (Strategic Design) | D94: Value Bundle Estimate | F94: Architecture Program Manager | G94: L2 | H94: Drive094 | K94: Value Bundle | L94: Value Bundle|STRAT_TARGET_DUR | M94: Target Duration | P94: The Start/End dates for value bundles will have to come from the Plan. It will not have separate Target Start/End dates, unless we are bringing over Target Start/End dates from the associated Program as a Read Only value. | Q94: Yes | R94: Yes | S94: STRAT_TARGET_DUR | T94: STRAT_TARGET_DUR | U94: STRAT_TARGET_DUR | AC94: Predefined | AD94: Duration | AE94: n/a | AG94: n/a | AH94: Target Duration of the strategic entity | AI94: RO | AJ94: n/a | AK94: n/a | AL94: n/a | AO94: =IF(ISNUMBER(_xlfn.XMATCH(Table182[[#This Row],[DEV SB ID]],Platinum_Config[Target DEV SB ID],0))=FALSE,"No Match","Match") -> Match | AP94: =IF(ISNUMBER(_xlfn.XMATCH(Table182[[#This Row],[Target Field Name]],Platinum_Config[Target Field Name],0))=FALSE,"No Match","Match") -> Match | AQ94: =IF(AND(Table182[[#This Row],[Exists already? (ID)]]="No Match",Table182[[#This Row],[Exists already (Name)]]="No Match"),"No Match",IF(AND(Table182[[#This Row],[Exists already? (ID)]]="Match",Table182[[#This Row],[Exists already (Name)]]="Match"),"Double Match","One Match")) -> Double Match | AR94: Added
A95: L2-Design | B95: Emilee, Pat/Macklin | D95: Demand Shaping | F95: Architecture Program Manager / Value Bundle Manager for Business Only | G95: L2 | H95: Drive095 | K95: Value Bundle | L95: Value Bundle|AC_START | M95: Actual/Schedule Start | P95: Comes from the Plan | Q95: Yes | R95: Yes | S95: AC_START | T95: AC_START | U95: AC_START | AC95: Predefined | AD95: Date/Time | AH95: The date the work was started if the work entity has started, otherwise, the schedule start date. | AI95: RO | AM95: Yes | AO95: =IF(ISNUMBER(_xlfn.XMATCH(Table182[[#This Row],[DEV SB ID]],Platinum_Config[Target DEV SB ID],0))=FALSE,"No Match","Match") -> Match | AP95: =IF(ISNUMBER(_xlfn.XMATCH(Table182[[#This Row],[Target Field Name]],Platinum_Config[Target Field Name],0))=FALSE,"No Match","Match") -> Match | AQ95: =IF(AND(Table182[[#This Row],[Exists already? (ID)]]="No Match",Table182[[#This Row],[Exists already (Name)]]="No Match"),"No Match",IF(AND(Table182[[#This Row],[Exists already? (ID)]]="Match",Table182[[#This Row],[Exists already (Name)]]="Match"),"Double Match","One Match")) -> Double Match | AR95: Ignore
A96: L2-Design | B96: Emilee, Pat/Macklin | D96: Demand Shaping | F96: Architecture Program Manager / Value Bundle Manager for Business Only | G96: L2 | H96: Drive096 | K96: Value Bundle | L96: Value Bundle|AC_FINISH | M96: Actual/Schedule Finish | P96: Comes from the Plan | Q96: Yes | R96: Yes | S96: AC_FINISH | T96: AC_FINISH | U96: AC_FINISH | AC96: Predefined | AD96: Date/Time | AH96: The actual finish date if the work entity was completed, otherwise, the schedule finish date. | AI96: RO | AM96: Yes | AO96: =IF(ISNUMBER(_xlfn.XMATCH(Table182[[#This Row],[DEV SB ID]],Platinum_Config[Target DEV SB ID],0))=FALSE,"No Match","Match") -> Match | AP96: =IF(ISNUMBER(_xlfn.XMATCH(Table182[[#This Row],[Target Field Name]],Platinum_Config[Target Field Name],0))=FALSE,"No Match","Match") -> Match | AQ96: =IF(AND(Table182[[#This Row],[Exists already? (ID)]]="No Match",Table182[[#This Row],[Exists already (Name)]]="No Match"),"No Match",IF(AND(Table182[[#This Row],[Exists already? (ID)]]="Match",Table182[[#This Row],[Exists already (Name)]]="Match"),"Double Match","One Match")) -> Double Match | AR96: Ignore
A97: L2-Design | B97: Matt | C97: L2: Refine Business Case | D97: Refine Business Case | F97: Business Finance | G97: L2 | H97: Drive098 | K97: Value Bundle | L97: Value Bundle|fdx_assump_work | M97: Key Assumptions Made in Quantifying Impact | Q97: Yes | R97: Yes | S97: fdx_assump_work | T97: fdx_assump_work | U97: fdx_assump_work | AC97: Field | AD97: Text | AE97: n/a | AG97: n/a | AH97: Rationale behind the calculations of value and costs. | AI97: Req. | AO97: =IF(ISNUMBER(_xlfn.XMATCH(Table182[[#This Row],[DEV SB ID]],Platinum_Config[Target DEV SB ID],0))=FALSE,"No Match","Match") -> Match | AP97: =IF(ISNUMBER(_xlfn.XMATCH(Table182[[#This Row],[Target Field Name]],Platinum_Config[Target Field Name],0))=FALSE,"No Match","Match") -> Match | AQ97: =IF(AND(Table182[[#This Row],[Exists already? (ID)]]="No Match",Table182[[#This Row],[Exists already (Name)]]="No Match"),"No Match",IF(AND(Table182[[#This Row],[Exists already? (ID)]]="Match",Table182[[#This Row],[Exists already (Name)]]="Match"),"Double Match","One Match")) -> Double Match | AR97: Ignore
A98: L2-Design | B98: Matt | C98: L2: Refine Business Case | D98: Refine Business Case | F98: Business Finance | G98: L2 | H98: Drive099 | K98: Value Bundle | L98: Value Bundle|Str33 | M98: Baseline Fiscal Year | P98: No need to change to CY just yet per Matt | Q98: Yes | R98: Label Chg | S98: Str33 | T98: Str33 | U98: Str33 | AC98: Alt. Struct | AD98: Text | AE98: Single | AG98: FY22 (3360) FY23 (3361) FY24 (3362) FY25 (3363) FY26 (3364) | AH98: Baseline fiscal year of the value bundle's financial plan for fiscal reporting. See below for available values to select for this field: - FY22 - FY23 - FY24 - FY25 - FY26 | AI98: Req. | AJ98: No | AO98: =IF(ISNUMBER(_xlfn.XMATCH(Table182[[#This Row],[DEV SB ID]],Platinum_Config[Target DEV SB ID],0))=FALSE,"No Match","Match") -> Match | AP98: =IF(ISNUMBER(_xlfn.XMATCH(Table182[[#This Row],[Target Field Name]],Platinum_Config[Target Field Name],0))=FALSE,"No Match","Match") -> No Match | AQ98: =IF(AND(Table182[[#This Row],[Exists already? (ID)]]="No Match",Table182[[#This Row],[Exists already (Name)]]="No Match"),"No Match",IF(AND(Table182[[#This Row],[Exists already? (ID)]]="Match",Table182[[#This Row],[Exists already (Name)]]="Match"),"Double Match","One Match")) -> One Match | AR98: Ignore
A99: L2-Design | B99: Matt | C99: L2: Refine Business Case | D99: Refine Business Case | F99: Business Finance | G99: L2 | H99: Drive100 | K99: Value Bundle | L99: Value Bundle|fdx_vbnrb_pnl_exit | M99: Net Recurring Benefits P&L/Hard Exit Rate CY '29 | P99: Have static text above this saying "**Net Recurring Benefits = CY '29 Exit Rate, Annualized** Note: This is a separate manually entered financial field. Create another version of the same field that calculates the Exit Rate from amounts entered in the Exit Rate financial line in the financials screen. | Q99: No | R99: Yes | S99: - | T99: fdx_vbnrb_pnl_exit | U99: fdx_vbnrb_pnl_exit | AC99: Field | AD99: Currency | AI99: Req. | AM99: Yes | AO99: =IF(ISNUMBER(_xlfn.XMATCH(Table182[[#This Row],[DEV SB ID]],Platinum_Config[Target DEV SB ID],0))=FALSE,"No Match","Match") -> Match | AP99: =IF(ISNUMBER(_xlfn.XMATCH(Table182[[#This Row],[Target Field Name]],Platinum_Config[Target Field Name],0))=FALSE,"No Match","Match") -> Match | AQ99: =IF(AND(Table182[[#This Row],[Exists already? (ID)]]="No Match",Table182[[#This Row],[Exists already (Name)]]="No Match"),"No Match",IF(AND(Table182[[#This Row],[Exists already? (ID)]]="Match",Table182[[#This Row],[Exists already (Name)]]="Match"),"Double Match","One Match")) -> Double Match | AR99: Added
A100: L2-Design | B100: Matt | C100: L2: Refine Business Case | D100: Refine Business Case | F100: Business Finance | G100: L2 | H100: Drive101 | K100: Value Bundle | L100: Value Bundle|fdx_vbnrb_cy27_hard | M100: Net Recurring Benefits CY '27 -P&L/Hard | P100: This is a separate manually entered financial field. Put static text to say: "Enter in year total value for CY '27" Note: Create another version of the same field that calculates the subtotal from amounts entered in CY'27 in the Financials screen. | Q100: No | R100: Yes | S100: - | T100: fdx_vbnrb_cy27_hard | U100: fdx_vbnrb_cy27_hard | AC100: Field | AD100: Currency | AE100: n/a | AG100: n/a | AH100: Sum of the amounts entered in the Exit Rate account of the Latest Estimate version of the financial plan for the current year 2027 | AI100: Req. | AM100: Yes | AO100: =IF(ISNUMBER(_xlfn.XMATCH(Table182[[#This Row],[DEV SB ID]],Platinum_Config[Target DEV SB ID],0))=FALSE,"No Match","Match") -> Match | AP100: =IF(ISNUMBER(_xlfn.XMATCH(Table182[[#This Row],[Target Field Name]],Platinum_Config[Target Field Name],0))=FALSE,"No Match","Match") -> Match | AQ100: =IF(AND(Table182[[#This Row],[Exists already? (ID)]]="No Match",Table182[[#This Row],[Exists already (Name)]]="No Match"),"No Match",IF(AND(Table182[[#This Row],[Exists already? (ID)]]="Match",Table182[[#This Row],[Exists already (Name)]]="Match"),"Double Match","One Match")) -> Double Match | AR100: Ignore
...

Sheet Pivot
A3: Order | B3: Source PROD ID | C3: FDXSANDBOXA ID | D3: Target DEV SB ID | E3: Target Entity | F3: Prod Source field name | G3: Target Field Name | H3: Req's Transform? | I3: Logic Written?
A4: 4 | B4: Wbs22 | C4: Wbs22 | D4: Wbs22 | E4: TBD - Value Bundle or Epic or Task | F4: Work Type | G4: Work Type | H4: Yes - High | I4: TBC
A5: 4.1 | B5: <New> | C5: Wbs139 | D5: Wbs174 | E5: TBD - Value Bundle or Epic or Task | F5: 0-Not Found | G5: Does this work support either of these type of Programs? | H5: Yes - High | I5: TBC
A6: 5 | B6: <New> | C6: (blank) | D6: Wbs146 | E6: TBD - Value Bundle or Epic or Task | F6: 0-Not Found | G6: Does this request support a DRIVE strategic program? | H6: Yes - High | I6: TBC
A7: 7 | B7: <New> | D7: Wbs66 | E7: TBD - Value Bundle or Epic or Task | F7: 0-Not Found | G7: Is this demand Business Only? | H7: Yes - High | I7: TBC
A8: 9 | B8: <New> | D8: Wbs147 | E8: TBD - Value Bundle or Epic or Task | F8: 0-Not Found | G8: Does this request support a D&T Digital Transformation Program? | H8: Yes - Med | I8: TBC
A9: 23 | B9: WR2 and other attributes. See data migration logic | C9: WR2 | D9: WR2 | E9: TBD - Value Bundle or Epic or Task | F9: 0-Not Found | G9: Demand Type | H9: Yes - High | I9: TBC
A10: 55 | B10: <New> | D10: Wbs157 | E10: TBD - Value Bundle or Epic or Task | F10: 0-Not Found | G10: Flow Type | H10: Yes - High | I10: TBC
A11: 90 | B11: <Removed> | C11: Wbs22 | D11: Wbs22 | E11: Demand Bundle | F11: 0-Not Found | G11: Work Type | H11: Yes - High | I11: TBC
A12: Drive038 | C12: Str144 | D12: Str61 | E12: TBD - Value Bundle or Epic or Task | F12: 0-Not Found | G12: Program Type | H12: Yes - High | I12: TBC

Sheet Config Req_Consolidated
AS1: Screen Alignment
A2: Source Tab | B2: Primary Reviewer | C2: Op Model Step | D2: 1st Lifecycle Step Name | E2: Section Name | F2: Lifecycle Screen User Role | G2: Lifecycle Stage | H2: Order | I2: Source Demand Type | J2: Target Demand Type | K2: Target Entity | L2: Entity|ID | M2: Target Field Name | N2: Configuration Status | O2: Change Control Comments | P2: Notes/Comments | Q2: Current Attribute in FDXPROD? | R2: Current Attribute in FDXSANDBOXA? | S2: Source PROD ID | T2: FDXSANDBOXA ID | U2: Target DEV SB ID | V2: Data Migration Comments | W2: Able to Migrate Mock 1? | X2: Req's Transform? | Y2: Logic Written? | Z2: Prod Source field name | AA2: Prod source field name (if temporary) | AB2: Sandbox A field name | AC2: New instance Target field name | AD2: Field names Match (prod to new)? | AE2: Prod & Dev Field names Match? | AF2: SBA & Dev Field names Match? | AG2: Type | AH2: Value Type | AI2: Selection Type | AJ2: Has Dropdown | AK2: Values | AL2: Hover Text or Static Text | AM2: Options (Req./RO/Opt.) | AN2: Editable After Submission | AO2: Permission Options | AP2: Restrict Permissions Forwarding | AQ2: Needed in Roadmaps? | AR2: Entity_Flag_Manual_Review | AS2: Work - Add New | AT2: Add New Request Information | AU2: Business Continuity Assessment | AV2: Problem Opportunity Statement | AW2: Triage Validation | AX2: Request Approval | AY2: Move Work and Assign Roles and Responsibilities | AZ2: Architecture Alignment | BA2: Certified Business Case | BB2: SL3 EPG Approval | BC2: SL3 Finance Approval | BD2: Demand Bundle Decomp and Conceptual Architecture | BE2: Detailed Milestone Refinement | BF2: EPM Quality Check 1 | BG2: Revised Implementation Plan/Sequence Delivery | BH2: Epic Approval | BI2: L3 Epic Solutioning | BJ2: L3 D&T Costing | BK2: EPM Quality Check 2 | BL2: L3: Execute and Release | BM2: SL4 Close Demand Bundle Business Finance Approval | BN2: Evaluate Outcome Achievement
A3: L1 - Establish Request for Work | B3: Lori, Gary | C3: L1: Define the Problem/Opportunity Statement | D3: Work - Add New | F3: Requestor | G3: L1 | H3: 1 | I3: Business with Tech, Local Enhancement, Lifecycle Management, Business Only | K3: TBD - Value Bundle or Epic or Task | L3: =_xlfn.TEXTJOIN("|",FALSE,Platinum_Config[[#This Row],[Target Entity]],Platinum_Config[[#This Row],[Target DEV SB ID]]) -> TBD - Value Bundle or Epic or Task|PW_SHORT_NAME | M3: Work ID | N3: 3. Attribute Created | P3: Auto generated | Q3: Yes | R3: Yes | S3: PW_SHORT_NAME | T3: PW_SHORT_NAME | U3: PW_SHORT_NAME | W3: Yes | X3: Passthrough | Z3: =_xlfn.XLOOKUP(Platinum_Config[[#This Row],[Source PROD ID]],Prod_fields[ID],Prod_fields[Attribute Name],"0-Not Found",0,1) -> Work ID | AB3: =_xlfn.XLOOKUP(Platinum_Config[[#This Row],[FDXSANDBOXA ID]],SBA_fields[ID],SBA_fields[Attribute Name],"0-Not Found",0,1) -> Work ID | AC3: =_xlfn.XLOOKUP(Platinum_Config[[#This Row],[Target DEV SB ID]],Target_Dev_fields[ID],Target_Dev_fields[Attribute Name],"0-Not Found",0,1) -> Work ID | AD3: =Platinum_Config[[#This Row],[Prod Source field name]]=Platinum_Config[[#This Row],[New instance Target field name]] -> TRUE | AE3: =Platinum_Config[[#This Row],[Target Field Name]]=Platinum_Config[[#This Row],[New instance Target field name]] -> TRUE | AF3: =Platinum_Config[[#This Row],[Sandbox A field name]]=Platinum_Config[[#This Row],[New instance Target field name]] -> TRUE | AG3: Field | AH3: Text | AJ3: No | AM3: Req. | AN3: No | AR3: YES
A4: L1 - Establish Request for Work | B4: Lori, Gary | C4: L1: Define the Problem/Opportunity Statement | D4: Work - Add New | F4: Requestor | G4: L1 | H4: 2 | I4: Business with Tech, Local Enhancement, Lifecycle Management, Business Only | K4: TBD - Value Bundle or Epic or Task | L4: =_xlfn.TEXTJOIN("|",FALSE,Platinum_Config[[#This Row],[Target Entity]],Platinum_Config[[#This Row],[Target DEV SB ID]]) -> TBD - Value Bundle or Epic or Task|DESCR | M4: Work Name | N4: 3. Attribute Created | Q4: Yes | R4: Yes | S4: DESCR | T4: DESCR | U4: DESCR | W4: Yes | X4: Passthrough | Z4: =_xlfn.XLOOKUP(Platinum_Config[[#This Row],[Source PROD ID]],Prod_fields[ID],Prod_fields[Attribute Name],"0-Not Found",0,1) -> Epic Name | AB4: =_xlfn.XLOOKUP(Platinum_Config[[#This Row],[FDXSANDBOXA ID]],SBA_fields[ID],SBA_fields[Attribute Name],"0-Not Found",0,1) -> Work Name | AC4: =_xlfn.XLOOKUP(Platinum_Config[[#This Row],[Target DEV SB ID]],Target_Dev_fields[ID],Target_Dev_fields[Attribute Name],"0-Not Found",0,1) -> Work Name | AD4: =Platinum_Config[[#This Row],[Prod Source field name]]=Platinum_Config[[#This Row],[New instance Target field name]] -> FALSE | AE4: =Platinum_Config[[#This Row],[Target Field Name]]=Platinum_Config[[#This Row],[New instance Target field name]] -> TRUE | AF4: =Platinum_Config[[#This Row],[Sandbox A field name]]=Platinum_Config[[#This Row],[New instance Target field name]] -> TRUE | AG4: Field | AH4: Text | AJ4: No | AL4: This is the name of the request - 3-5 words to describe it. | AM4: Req. | AN4: No | AR4: YES
A5: L1 - Establish Request for Work | B5: Lori, Gary | C5: L1: Define the Problem/Opportunity Statement | D5: Work - Add New | F5: Requestor | G5: L1 | H5: 2 | I5: Business with Tech, Local Enhancement, Lifecycle Management, Business Only | K5: TBD - Value Bundle or Epic or Task | L5: =_xlfn.TEXTJOIN("|",FALSE,Platinum_Config[[#This Row],[Target Entity]],Platinum_Config[[#This Row],[Target DEV SB ID]]) -> TBD - Value Bundle or Epic or Task|PW_DESCRIPTION | M5: Work Name | N5: 3. Attribute Created | Q5: Yes | R5: Yes | S5: PW_DESCRIPTION | T5: PW_DESCRIPTION | U5: PW_DESCRIPTION | W5: Yes | X5: Passthrough | Z5: =_xlfn.XLOOKUP(Platinum_Config[[#This Row],[Source PROD ID]],Prod_fields[ID],Prod_fields[Attribute Name],"0-Not Found",0,1) -> Epic Name | AB5: =_xlfn.XLOOKUP(Platinum_Config[[#This Row],[FDXSANDBOXA ID]],SBA_fields[ID],SBA_fields[Attribute Name],"0-Not Found",0,1) -> Work Name | AC5: =_xlfn.XLOOKUP(Platinum_Config[[#This Row],[Target DEV SB ID]],Target_Dev_fields[ID],Target_Dev_fields[Attribute Name],"0-Not Found",0,1) -> Work Name | AD5: =Platinum_Config[[#This Row],[Prod Source field name]]=Platinum_Config[[#This Row],[New instance Target field name]] -> FALSE | AE5: =Platinum_Config[[#This Row],[Target Field Name]]=Platinum_Config[[#This Row],[New instance Target field name]] -> TRUE | AF5: =Platinum_Config[[#This Row],[Sandbox A field name]]=Platinum_Config[[#This Row],[New instance Target field name]] -> TRUE | AG5: Field | AH5: Text | AJ5: No | AL5: This is the name of the request - 3-5 words to describe it. | AM5: Req. | AN5: No | AR5: YES
A6: L1 - Establish Request for Work | C6: L1: Define the Problem/Opportunity Statement | D6: Work - Add New | F6: Requestor | G6: L1 | H6: 3 | I6: Business with Tech, Local Enhancement, Lifecycle Management, Business Only | K6: TBD - Value Bundle or Epic or Task | L6: =_xlfn.TEXTJOIN("|",FALSE,Platinum_Config[[#This Row],[Target Entity]],Platinum_Config[[#This Row],[Target DEV SB ID]]) -> TBD - Value Bundle or Epic or Task|PARENT_DESCR | M6: Work Parent | N6: 3. Attribute Created | Q6: Yes | R6: Yes | S6: PARENT_DESCR | T6: PARENT_DESCR | U6: PARENT_DESCR | W6: Yes | X6: Passthrough | Z6: =_xlfn.XLOOKUP(Platinum_Config[[#This Row],[Source PROD ID]],Prod_fields[ID],Prod_fields[Attribute Name],"0-Not Found",0,1) -> Home Domain/Portfolio | AB6: =_xlfn.XLOOKUP(Platinum_Config[[#This Row],[FDXSANDBOXA ID]],SBA_fields[ID],SBA_fields[Attribute Name],"0-Not Found",0,1) -> Work Parent | AC6: =_xlfn.XLOOKUP(Platinum_Config[[#This Row],[Target DEV SB ID]],Target_Dev_fields[ID],Target_Dev_fields[Attribute Name],"0-Not Found",0,1) -> Work Parent | AD6: =Platinum_Config[[#This Row],[Prod Source field name]]=Platinum_Config[[#This Row],[New instance Target field name]] -> FALSE | AE6: =Platinum_Config[[#This Row],[Target Field Name]]=Platinum_Config[[#This Row],[New instance Target field name]] -> TRUE | AF6: =Platinum_Config[[#This Row],[Sandbox A field name]]=Platinum_Config[[#This Row],[New instance Target field name]] -> TRUE | AG6: Predefined | AH6: Text | AJ6: No | AM6: Req. | AN6: No | AR6: YES
A7: L1 - Establish Request for Work | B7: Lori, Daniel, Gary | D7: Work - Add New | F7: Requestor | G7: L1 | H7: 4 | I7: Business with Tech, Local Enhancement, Lifecycle Management, Business Only | K7: TBD - Value Bundle or Epic or Task | L7: =_xlfn.TEXTJOIN("|",FALSE,Platinum_Config[[#This Row],[Target Entity]],Platinum_Config[[#This Row],[Target DEV SB ID]]) -> TBD - Value Bundle or Epic or Task|Wbs22 | M7: Work Type | N7: 3. Attribute Created | P7: Carried from the request | Q7: Yes | R7: Yes | S7: Wbs22 | T7: Wbs22 | U7: Wbs22 | W7: Yes | X7: Yes - High | Y7: TBC | Z7: =_xlfn.XLOOKUP(Platinum_Config[[#This Row],[Source PROD ID]],Prod_fields[ID],Prod_fields[Attribute Name],"0-Not Found",0,1) -> Work Type | AB7: =_xlfn.XLOOKUP(Platinum_Config[[#This Row],[FDXSANDBOXA ID]],SBA_fields[ID],SBA_fields[Attribute Name],"0-Not Found",0,1) -> Work Type | AC7: =_xlfn.XLOOKUP(Platinum_Config[[#This Row],[Target DEV SB ID]],Target_Dev_fields[ID],Target_Dev_fields[Attribute Name],"0-Not Found",0,1) -> Work Type | AD7: =Platinum_Config[[#This Row],[Prod Source field name]]=Platinum_Config[[#This Row],[New instance Target field name]] -> TRUE | AE7: =Platinum_Config[[#This Row],[Target Field Name]]=Platinum_Config[[#This Row],[New instance Target field name]] -> TRUE | AF7: =Platinum_Config[[#This Row],[Sandbox A field name]]=Platinum_Config[[#This Row],[New instance Target field name]] -> TRUE | AG7: Alternate Structure | AH7: Auto | AI7: Single | AJ7: Yes | AK7: =_xlfn.TEXTJOIN(CHAR(10),TRUE,VAL_Work_Type[]) -> Program Value Bundle Tech-Enabled Request Business Demand | AL7: If creating a Value Bundle under Strategic Program, select "Program Value Bundle". If creating a tech enabled non-Program work, select "Demand Bundle". If creating a Business Demand Management work, select "Business Demand". Business Demand represents work governed by the Regional Business Units. Governance and decision‑making are handled outside of the DRIVE Forward framework. | AM7: Req. | AN7: No | AR7: YES
